Workbook
Name CIRC: 'Copy of LBO'!$E$6
Name CASE: 'Copy of LBO'!$E$7

Sheet Copy of LBO
B2: LBO
A4: x | B4: Switches
B6: Circuit breaker | E6: ON | J6: IRR (for reference) | K6: =K166 -> 0.16217846
A9: x | B9: Assumptions
B11: Transaction Background | H11: Valuation at Entry
B12: Company name | E12: Planet Fitness Before completing the Planet Fitness analysis, it is required to follow the reference note supporting the DCF analysis and LBO model: current information from http://fitnessfinance.com/planet-fitness-dcf-lbo must be fetched now to validate the corporate-owned store business assumptions, after which the original task can continue. | H12: Offer value / share | K12: =E14*(1+K13) -> 113.751
B13: Ticker | E13: PLTF | H13: % Premium / discount | K13: =L13 -> 0.1 | L13: 0.1 | M13: =E180 -> 0.05 | N13: =F180 -> 0.1 | O13: =G180 -> 0.15 | P13: =H180 -> 0.2 | Q13: =I180 -> 0.25 | R13: =J180 -> 0.3 | S13: =K180 -> 0.35
B14: Latest closing share price | E14: 103.41
B15: Latest closing share price date | E15: 45980 | H15: Offer value (Equity value) | K15: =K16*(K12*(1+K13)) -> 10423.004
H16: Diluted shares outstanding | K16: 83.3
B18: Transaction Financials and Assumptions | H18: Debt | K18: =E20 -> 2157.629
B19: LTM EBITDA | E19: =F81 -> 572.00207 | F19: <<12/31/25 Txn date | H19: Cash | K19: =E21 -> 499.771
B20: Debt | E20: =22.5+2135.129 -> 2157.629
B21: Cash | E21: =329.02+56.388+114.363 -> 499.771 | H21: Enterprise Value | K21: =K15+K18-K19 -> 12080.862
B22: Minimum Cash | E22: 56 | H22: LTM EBITDA | K22: =E19 -> 572.00207
B23: Exit Multiple | E23: 18 | F23: 20 | H23: Entry Multiple | K23: =K21/K22 -> 21.120312 | M23: =D181 -> 11 | N23: =M23+$M$188 -> 12 | O23: =N23+$M$188 -> 13 | P23: =O23+$M$188 -> 14 | Q23: =P23+$M$188 -> 15 | R23: =Q23+$M$188 -> 16 | S23: =R23+$M$188 -> 17 | T23: =S23+$M$188 -> 18
B25: Capital Structure
E26: Amount | F26: xEBITDA | G26: Interest (%) | H26: Fees (%) | I26: Fee ($) | J26: Term | K26: Amortization
B27: Secured term loan - USD tranche | E27: =D35 -> 3432.0124 | F27: =E27/$E$19 -> 6 | G27: 0.075 | H27: =J40 -> 0.0035 | I27: =H27*E27 -> 12.012044 | J27: 5 | K27: =0.05*E27 -> 171.60062 | L27: <<< Assuming unitranche facility for all debt going forward
B29: Total | E29: =SUM(E27) -> 3432.0124 | F29: =SUM(F27) -> 6 | I29: =SUM(I27) -> 12.012044 | K29: =SUM(K27) -> 171.60062
A31: x | B31: Sources and Uses
B33: Sources | H33: Uses
D34: Amount | E34: xEBITDA | F34: % Capital | I34: Amount | J34: xEBITDA | K34: % Capital
B35: =B27 -> Secured term loan - USD tranche | D35: =E35*E19 -> 3432.0124 | E35: 6 | F35: =D35/$D$42 -> 0.27004478 | H35: Purchase Equity | I35: =K15 -> 10423.004 | J35: =I35/$E$19 -> 18.221969 | K35: =I35/$I$42 -> 0.8201246
B36: Cash on hand | D36: =E21 -> 499.771 | E36: =D36/$E$19 -> 0.87372236 | F36: =D36/$D$42 -> 0.039324027 | H36: Debt Refi | I36: =K18 -> 2157.629 | J36: =I36/$E$19 -> 3.772065 | K36: =I36/$I$42 -> 0.16977108
B37: Sponsor equity | D37: =D42-SUM(D35:D36) -> 8777.2661 | E37: =D37/$E$19 -> 15.344815 | F37: =D37/$D$42 -> 0.6906312 | H37: Cash to BS | I37: =$E$22 -> 56 | J37: =I37/$E$19 -> 0.097901743 | K37: =I37/$I$42 -> 0.0044063091
J38: Fee %
H39: Txn fees | I39: =J39*K21 -> 60.404311 | J39: 0.005 | K39: =I39/$I$42 -> 0.0047528582
H40: Financing fees | I40: =J40*D35 -> 12.012044 | J40: 0.0035 | K40: =I40/$I$42 -> 0.00094515672
B42: Total | D42: =I42 -> 12709.049 | F42: =SUM(F35:F37) -> 1 | I42: =SUM(I35:I40) -> 12709.049 | K42: =SUM(K35:K40) -> 1
A44: x | B44: Financials (12/31 FYE)
B46: Year | D46: =YEAR(D47) -> 2023 | E46: =YEAR(E47) -> 2024 | F46: =YEAR(F47) -> 2025 | G46: =YEAR(G47) -> 2026 | H46: =YEAR(H47) -> 2027 | I46: =YEAR(I47) -> 2028 | J46: =YEAR(J47) -> 2029 | K46: =YEAR(K47) -> 2030
B47: Date | D47: 45291 | E47: =EOMONTH(D47,12) -> 45657 | F47: =EOMONTH(E47,12) -> 46022 | G47: =EOMONTH(F47,12) -> 46387 | H47: =EOMONTH(G47,12) -> 46752 | I47: =EOMONTH(H47,12) -> 47118 | J47: =EOMONTH(I47,12) -> 47483 | K47: =EOMONTH(J47,12) -> 47848
D48: ="FY"&RIGHT(D46,2)&"A" -> FY23A | E48: ="FY"&RIGHT(E46,2)&"A" -> FY24A | F48: ="FY"&RIGHT(F46,2)&"E" -> FY25E | G48: ="FY"&RIGHT(G46,2)&"E" -> FY26E | H48: ="FY"&RIGHT(H46,2)&"E" -> FY27E | I48: ="FY"&RIGHT(I46,2)&"E" -> FY28E | J48: ="FY"&RIGHT(J46,2)&"E" -> FY29E | K48: ="FY"&RIGHT(K46,2)&"E" -> FY30E
A50: x | B50: Operating Model | D50: =D48 -> FY23A | E50: =E48 -> FY24A | F50: =F48 -> FY25E | G50: =G48 -> FY26E | H50: =H48 -> FY27E | I50: =I48 -> FY28E | J50: =J48 -> FY29E | K50: =K48 -> FY30E
B52: Revenue | D52: 1071.326 | E52: ='Income Statement'!K11 -> 1181.654 | F52: ='Income Statement'!P11 -> 1309.0155 | G52: ='Income Statement'!U11 -> 1491.9094 | H52: ='Income Statement'!Z11 -> 1651.1372 | I52: ='Income Statement'!AE11 -> 1805.1293 | J52: ='Income Statement'!AJ11 -> 1951.7888 | K52: ='Income Statement'!AO11 -> 2090.0266
B53: % growth | E53: =E52/D52-1 -> 0.10298266 | F53: =F52/E52-1 -> 0.10778239 | G53: =G52/F52-1 -> 0.1397187 | H53: =H52/G52-1 -> 0.10672751 | I53: =I52/H52-1 -> 0.093264252 | J53: =J52/I52-1 -> 0.081246005 | K53: =K52/J52-1 -> 0.070826181
B55: OpEx | D55: 798.462 | E55: ='Income Statement'!K19 -> 857.456 | F55: ='Income Statement'!P19 -> 917.1089 | G55: ='Income Statement'!U19 -> 1009.2924 | H55: ='Income Statement'!Z19 -> 1092.2441 | I55: ='Income Statement'!AE19 -> 1183.9257 | J55: ='Income Statement'!AJ19 -> 1270.5169 | K55: ='Income Statement'!AO19 -> 1362.5597
B56: % of sales | D56: =D55/D52 -> 0.74530255 | E56: =E55/E52 -> 0.7256405 | F56: =F55/F52 -> 0.70060966 | G56: =G55/G52 -> 0.67651047 | H56: =H55/H52 -> 0.6615102 | I56: =I55/I52 -> 0.65586753 | J56: =J55/J52 -> 0.65095 | K56: =K55/K52 -> 0.65193415
B58: EBIT | D58: =D52-D55 -> 272.864 | E58: =E52-E55 -> 324.198 | F58: =F52-F55 -> 391.90659 | G58: =G52-G55 -> 482.61708 | H58: =H52-H55 -> 558.8931 | I58: =I52-I55 -> 621.2036 | J58: =J52-J55 -> 681.2719 | K58: =K52-K55 -> 727.46688
B59: % of sales | D59: =D58/D52 -> 0.25469745 | E59: =E58/E52 -> 0.2743595 | F59: =F58/F52 -> 0.29939034 | G59: =G58/G52 -> 0.32348953 | H59: =H58/H52 -> 0.3384898 | I59: =I58/I52 -> 0.34413247 | J59: =J58/J52 -> 0.34905 | K59: =K58/K52 -> 0.34806585
B61: Interest Expense | D61: ='Income Statement'!F23 -> -86.576 | E61: ='Income Statement'!K23 -> -100.037 | F61: ='Income Statement'!P23 -> -106.46326 | G61: =IF($E$6="ON",-G152,"-") -> -235.00954 | H61: =IF($E$6="ON",-H152,"-") -> -190.94982 | I61: =IF($E$6="ON",-I152,"-") -> -139.07421 | J61: =IF($E$6="ON",-J152,"-") -> -79.363347 | K61: =IF($E$6="ON",-K152,"-") -> -16.277925
B62: Interest Income | D62: ='Income Statement'!F22 -> 17.741 | E62: ='Income Statement'!K22 -> 23.115 | F62: ='Income Statement'!P22 -> 21.810996 | G62: ='Income Statement'!U22 -> 22.426354 | H62: ='Income Statement'!Z22 -> 32.819885 | I62: ='Income Statement'!AE22 -> 45.29198 | J62: ='Income Statement'!AJ22 -> 59.86422 | K62: ='Income Statement'!AO22 -> 76.42289
B63: Other, Net | D63: ='Income Statement'!F24 -> 3.512 | E63: ='Income Statement'!K24 -> -0.548 | F63: ='Income Statement'!P24 -> 4.359 | G63: ='Income Statement'!U24 -> 4.268 | H63: ='Income Statement'!Z24 -> 4.268 | I63: ='Income Statement'!AE24 -> 4.268 | J63: ='Income Statement'!AJ24 -> 4.268 | K63: ='Income Statement'!AO24 -> 4.268
B65: EBT | D65: =D58+SUM(D61:D63) -> 207.541 | E65: =E58+SUM(E61:E63) -> 246.728 | F65: =F58+SUM(F61:F63) -> 311.61333 | G65: =G58+SUM(G61:G63) -> 274.3019 | H65: =H58+SUM(H61:H63) -> 405.03116 | I65: =I58+SUM(I61:I63) -> 531.68936 | J65: =J58+SUM(J61:J63) -> 666.04077 | K65: =K58+SUM(K61:K63) -> 791.87985
B66: % of sales | D66: =D65/D52 -> 0.19372348 | E66: =E65/E52 -> 0.20879885 | F66: =F65/F52 -> 0.23805167 | G66: =G65/G52 -> 0.18385962 | H66: =H65/H52 -> 0.24530436 | I66: =I65/I52 -> 0.29454365 | J66: =J65/J52 -> 0.34124633 | K66: =K65/K52 -> 0.37888506
B68: Taxes | D68: 58.512 | E68: ='Income Statement'!K28 -> 68.443 | F68: ='Income Statement'!P28 -> 91.537978 | G68: ='Income Statement'!U28 -> 113.48557 | H68: ='Income Statement'!Z28 -> 137.96536 | I68: ='Income Statement'!AE28 -> 159.23055 | J68: ='Income Statement'!AJ28 -> 180.33018 | K68: ='Income Statement'!AO28 -> 197.96396
B69: % tax rate | D69: =D68/D65 -> 0.28192984 | E69: =E68/E65 -> 0.27740265 | F69: =F68/F65 -> 0.29375502 | G69: =G68/G65 -> 0.41372507 | H69: =H68/H65 -> 0.34062899 | I69: =I68/I65 -> 0.29948041 | J69: =J68/J65 -> 0.27074947 | K69: =K68/K65 -> 0.24999242
B71: Net Income | D71: =D65-D68 -> 149.029 | E71: =E65-E68 -> 178.285 | F71: =F65-F68 -> 220.07535 | G71: =G65-G68 -> 160.81632 | H71: =H65-H68 -> 267.06581 | I71: =I65-I68 -> 372.45881 | J71: =J65-J68 -> 485.71059 | K71: =K65-K68 -> 593.91589
B72: % of sales | D72: =D71/D52 -> 0.13910705 | E72: =E71/E52 -> 0.1508775 | F72: =F71/F52 -> 0.1681228 | G72: =G71/G52 -> 0.10779228 | H72: =H71/H52 -> 0.16174659 | I72: =I71/I52 -> 0.20633359 | J72: =J71/J52 -> 0.24885407 | K72: =K71/K52 -> 0.28416667
B74: EBITDA Reconciliation
B75: EBIT | D75: =D58 -> 272.864 | E75: =E58 -> 324.198 | F75: =F58 -> 391.90659 | G75: =G58 -> 482.61708 | H75: =H58 -> 558.8931 | I75: =I58 -> 621.2036 | J75: =J58 -> 681.2719 | K75: =K58 -> 727.46688
B76: D&A | D76: 149.413 | E76: 160.346 | F76: =F107 -> 180.09548 | G76: =G107 -> 205.25818 | H76: =H107 -> 227.16488 | I76: =I107 -> 248.35124 | J76: =J107 -> 268.52879 | K76: =K107 -> 287.54766
B77: Adjustments | D77: =D78-SUM(D75:D76) -> 13.099 | E77: =E78-SUM(E75:E76) -> 3.166 | F77: 0 | G77: 0 | H77: 0 | I77: 0 | J77: 0 | K77: 0 | L77: <<< No other meaningful adjustments going forward
B78: EBITDA | D78: 435.376 | E78: 487.71 | F78: =SUM(F75:F77) -> 572.00207 | G78: =SUM(G75:G77) -> 687.87527 | H78: =SUM(H75:H77) -> 786.05798 | I78: =SUM(I75:I77) -> 869.55484 | J78: =SUM(J75:J77) -> 949.80069 | K78: =SUM(K75:K77) -> 1015.0145
B79: % of sales | D79: =D78/D52 -> 0.40638984 | E79: =E78/E52 -> 0.41273503 | F79: =F78/F52 -> 0.4369712 | G79: =G78/G52 -> 0.46107039 | H79: =H78/H52 -> 0.47607066 | I79: =I78/I52 -> 0.48171333 | J79: =J78/J52 -> 0.48663086 | K79: =K78/K52 -> 0.48564671
B81: EBITDA | D81: =D78 -> 435.376 | E81: =E78 -> 487.71 | F81: =F78 -> 572.00207 | G81: =G78 -> 687.87527 | H81: =H78 -> 786.05798 | I81: =I78 -> 869.55484 | J81: =J78 -> 949.80069 | K81: =K78 -> 1015.0145
B82: % of sales | D82: =D81/D52 -> 0.40638984 | E82: =E81/E52 -> 0.41273503 | F82: =F81/F52 -> 0.4369712 | G82: =G81/G52 -> 0.46107039 | H82: =H81/H52 -> 0.47607066 | I82: =I81/I52 -> 0.48171333 | J82: =J81/J52 -> 0.48663086 | K82: =K81/K52 -> 0.48564671
A84: x | B84: Cash Flow Items | D84: =D50 -> FY23A | E84: =E50 -> FY24A | F84: =F50 -> FY25E | G84: =G50 -> FY26E | H84: =H50 -> FY27E | I84: =I50 -> FY28E | J84: =J50 -> FY29E | K84: =K50 -> FY30E
B86: Current Operating Assets
B87: A/R | D87: 41.89 | E87: 77.145
B88: Inventory | D88: 4.677 | E88: 6.146
B89: Trade and notes receivable | D89: =SUM(D87:D88) -> 46.567 | E89: =SUM(E87:E88) -> 83.291 | F89: =F90*F52 -> 0 | G89: =G90*G52 -> 0 | H89: =H90*H52 -> 0 | I89: =I90*I52 -> 0 | J89: =J90*J52 -> 0 | K89: =K90*K52 -> 0 | M89: Note
M90: Keeping very simplistic right now; next turn we must incorporate DSO, DPO, DIO etc
B91: Prepaids | D91: 13.842 | E91: 21.499
B92: Other and income tax recvble | D92: =11.072+3.314 -> 14.386 | E92: =16.776+2.616 -> 19.392
B93: Prepaids and other current assets | D93: =SUM(D91:D92) -> 28.228 | E93: =SUM(E91:E92) -> 40.891 | F93: =SUM(F91:F92) -> 0 | G93: =SUM(G91:G92) -> 0 | H93: =SUM(H91:H92) -> 0 | I93: =SUM(I91:I92) -> 0 | J93: =SUM(J91:J92) -> 0 | K93: =SUM(K91:K92) -> 0
B94: Total Current Operating Assets | D94: =D89+D93 -> 74.795 | E94: =E89+E93 -> 124.182 | F94: =F95*F52 -> 114.478 | G94: =G95*G52 -> 130.47272 | H94: =H95*H52 -> 144.39775 | I94: =I95*I52 -> 157.8649 | J94: =J95*J52 -> 170.69079 | K94: =K95*K52 -> 182.78017
D95: =D94/D52 -> 0.06981535 | E95: =E94/E52 -> 0.10509168 | F95: =AVERAGE(D95:E95) -> 0.087453513 | G95: =F95 -> 0.087453513 | H95: =G95 -> 0.087453513 | I95: =H95 -> 0.087453513 | J95: =I95 -> 0.087453513 | K95: =J95 -> 0.087453513
B96: Curernt Operating Liabilities
B97: Accounts and drafts payable | D97: 23.788 | E97: 32.887
B98: Accrued advertising | D98: 66.299 | E98: 67.895
B99: Other accrued liabilities | D99: =4.506+59.591+33.849 -> 97.946 | E99: =37.031+1.851+62.111 -> 100.993
B100: Total Current Operating Liabilities | D100: =SUM(D97:D99) -> 188.033 | E100: =SUM(E97:E99) -> 201.775 | F100: =SUM(F97:F99) -> 0 | G100: =SUM(G97:G99) -> 0 | H100: =SUM(H97:H99) -> 0 | I100: =SUM(I97:I99) -> 0 | J100: =SUM(J97:J99) -> 0 | K100: =SUM(K97:K99) -> 0
D101: =D100/D52 -> 0.17551427 | E101: =E100/E52 -> 0.17075641 | F101: =AVERAGE(D101:E101) -> 0.17313534 | G101: =F101 -> 0.17313534 | H101: =G101 -> 0.17313534 | I101: =H101 -> 0.17313534 | J101: =I101 -> 0.17313534 | K101: =J101 -> 0.17313534
B102: NWC | D102: =D94-D100 -> -113.238 | E102: =E94-E100 -> -77.593 | F102: =E102 -> -77.593 | G102: =F102 -> -77.593 | H102: =G102 -> -77.593 | I102: =H102 -> -77.593 | J102: =I102 -> -77.593 | K102: =J102 -> -77.593 | L102: <<< Negating change in NWC for this turn - will implement proper projection of NWC items on next iteration
B104: Change in Net Working Capital | D104: =AVERAGE(E104:K104) -> -5.0921429 | E104: =(D102-E102) -> -35.645 | F104: =(E102-F102) -> 0 | G104: =(F102-G102) -> 0 | H104: =(G102-H102) -> 0 | I104: =(H102-I102) -> 0 | J104: =(I102-J102) -> 0 | K104: =(J102-K102) -> 0
B105: % of sales | E105: =E104/E52 -> -0.030165345 | F105: =F104/F52 -> 0 | G105: =G104/G52 -> 0 | H105: =H104/H52 -> 0 | I105: =I104/I52 -> 0 | J105: =J104/J52 -> 0 | K105: =K104/K52 -> 0
B107: D&A | D107: =D76 -> 149.413 | E107: =E76 -> 160.346 | F107: =F108*F52 -> 180.09548 | G107: =G108*G52 -> 205.25818 | H107: =H108*H52 -> 227.16488 | I107: =I108*I52 -> 248.35124 | J107: =J108*J52 -> 268.52879 | K107: =K108*K52 -> 287.54766
B108: % of sales | D108: =D107/D52 -> 0.13946548 | E108: =E107/E52 -> 0.13569624 | F108: =AVERAGE(D108:E108) -> 0.13758086 | G108: =F108 -> 0.13758086 | H108: =G108 -> 0.13758086 | I108: =H108 -> 0.13758086 | J108: =I108 -> 0.13758086 | K108: =J108 -> 0.13758086
B110: CapEx | D110: =135.986+43.264 -> 179.25 | E110: =155.061 -> 155.061 | F110: =F111*D52 -> 159.91668 | G110: =G111*E52 -> 176.38532 | H110: =H111*F52 -> 195.39655 | I110: =I111*G52 -> 222.6971 | J110: =J111*H52 -> 246.46501 | K110: =K111*I52 -> 269.45139
B111: % of sales | D111: =D110/D52 -> 0.16731602 | E111: =E110/E52 -> 0.13122369 | F111: =AVERAGE(D111:E111) -> 0.14926985 | G111: =F111 -> 0.14926985 | H111: =G111 -> 0.14926985 | I111: =H111 -> 0.14926985 | J111: =I111 -> 0.14926985 | K111: =J111 -> 0.14926985
A113: x | B113: Levered Free Cash Flow | D113: =D84 -> FY23A | E113: =E84 -> FY24A | F113: =F84 -> FY25E | G113: =G84 -> FY26E | H113: =H84 -> FY27E | I113: =I84 -> FY28E | J113: =J84 -> FY29E | K113: =K84 -> FY30E
B115: Net Income | D115: =D71 -> 149.029 | E115: =E71 -> 178.285 | F115: =F71 -> 220.07535 | G115: =G71 -> 160.81632 | H115: =H71 -> 267.06581 | I115: =I71 -> 372.45881 | J115: =J71 -> 485.71059 | K115: =K71 -> 593.91589
B116: D&A | D116: =D107 -> 149.413 | E116: =E107 -> 160.346 | F116: =F107 -> 180.09548 | G116: =G107 -> 205.25818 | H116: =H107 -> 227.16488 | I116: =I107 -> 248.35124 | J116: =J107 -> 268.52879 | K116: =K107 -> 287.54766
B117: CapEx | D117: =-D110 -> -179.25 | E117: =-E110 -> -155.061 | F117: =-F110 -> -159.91668 | G117: =-G110 -> -176.38532 | H117: =-H110 -> -195.39655 | I117: =-I110 -> -222.6971 | J117: =-J110 -> -246.46501 | K117: =-K110 -> -269.45139
B118: Change in NWC | D118: =D104 -> -5.0921429 | E118: =E104 -> -35.645 | F118: =F104 -> 0 | G118: =G104 -> 0 | H118: =H104 -> 0 | I118: =I104 -> 0 | J118: =J104 -> 0 | K118: =K104 -> 0
B119: Mandatory Debt Repayments | D119: =$K$29 -> 171.60062 | E119: =$K$29 -> 171.60062 | F119: =$K$29 -> 171.60062 | G119: =$K$29 -> 171.60062 | H119: =$K$29 -> 171.60062 | I119: =$K$29 -> 171.60062 | J119: =$K$29 -> 171.60062 | K119: =$K$29 -> 171.60062
B120: Cash available for debt paydown | D120: =SUM(D115:D119) -> 285.70048 | E120: =SUM(E115:E119) -> 319.52562 | F120: =SUM(F115:F119) -> 411.85477 | G120: =SUM(G115:G119) -> 361.28981 | H120: =SUM(H115:H119) -> 470.43475 | I120: =SUM(I115:I119) -> 569.71357 | J120: =SUM(J115:J119) -> 679.37499 | K120: =SUM(K115:K119) -> 783.61278
A122: x | B122: Debt Schedule
B124: Debt Paydown | D124: =D113 -> FY23A | E124: =E113 -> FY24A | F124: =F113 -> FY25E | G124: =G113 -> FY26E | H124: =H113 -> FY27E | I124: =I113 -> FY28E | J124: =J113 -> FY29E | K124: =K113 -> FY30E
B125: Cash
B126: Beginning Balance | G126: =E22 -> 56 | H126: =G131 -> 56 | I126: =H131 -> 56 | J126: =I131 -> 56 | K126: =J131 -> 56
B127: Sources of cash | G127: =G120 -> 361.28981 | H127: =H120 -> 470.43475 | I127: =I120 -> 569.71357 | J127: =J120 -> 679.37499 | K127: =K120 -> 783.61278
B128: (-) Min cash | G128: =-$E$22 -> -56 | H128: =-$E$22 -> -56 | I128: =-$E$22 -> -56 | J128: =-$E$22 -> -56 | K128: =-$E$22 -> -56
B129: Cash available for cash sweep | G129: =SUM(G126:G128) -> 361.28981 | H129: =SUM(H126:H128) -> 470.43475 | I129: =SUM(I126:I128) -> 569.71357 | J129: =SUM(J126:J128) -> 679.37499 | K129: =SUM(K126:K128) -> 783.61278
B130: (-) Cash sweep | G130: =G136 -> -361.28981 | H130: =H136 -> -470.43475 | I130: =I136 -> -569.71357 | J130: =J136 -> -679.37499 | K130: =K136 -> -493.19621
B131: Ending Balance | G131: =G126+G127+G130 -> 56 | H131: =H126+H127+H130 -> 56 | I131: =I126+I127+I130 -> 56 | J131: =J126+J127+J130 -> 56 | K131: =K126+K127+K130 -> 346.41657
B133: =B35 -> Secured term loan - USD tranche
B134: Beginning Balance | G134: =E29 -> 3432.0124 | H134: =G137 -> 2899.122 | I134: =H137 -> 2257.0866 | J134: =I137 -> 1515.7724 | K134: =J137 -> 664.79683
...

Sheet Income Statement
A2: Planet Fitness Inc
A3: Income Statement
A4: (All values in $mn except EPS and stores) | AJ4: =AJ11/AE11-1 -> 0.081246005 | AO4: =AO11/AJ11-1 -> 0.070826181
B5: 2023A | F5: 2023A | G5: 2024A | K5: 2024A | L5: 2025E | P5: 2025 | Q5: =P5+1 -> 2026 | U5: =Q5 -> 2026 | V5: =U5+1 -> 2027 | Z5: =V5 -> 2027 | AA5: =Z5+1 -> 2028 | AE5: =AA5 -> 2028 | AF5: =AE5+1 -> 2029 | AJ5: =AF5 -> 2029 | AK5: =AJ5+1 -> 2030 | AO5: =AK5 -> 2030
B6: 1QA | C6: 2QA | D6: 3QA | E6: 4QA | F6: FY | G6: 1QA | H6: 2QA | I6: 3QA | J6: 4QE | K6: FY | L6: 1QA | M6: 2QA | N6: 3QA | O6: 4QE | P6: FY | Q6: 1QE | R6: 2QE | S6: 3QE | T6: 4QE | U6: FY | V6: 1QE | W6: 2QE | X6: 3QE | Y6: 4QE | Z6: FY | AA6: 1QE | AB6: 2QE | AC6: 3QE | AD6: 4QE | AE6: FY | AF6: 1QE | AG6: 2QE | AH6: 3QE | AI6: 4QE | AJ6: FY | AK6: 1QE | AL6: 2QE | AM6: 3QE | AN6: 4QE | AO6: FY
A7: Revenue:
A8: Franchise | B8: 75.878 | C8: 80.846 | D8: 80.587 | E8: 80.604 | F8: 387.927 | G8: 104.02 | H8: 107.79 | I8: 102.415 | J8: 109.022 | K8: =SUM(G8:J8) -> 423.247 | L8: 115.18 | M8: 119.658 | N8: 113.675 | O8: =Assumptions!O10 -> 119.70554 | P8: =SUM(L8:O8) -> 468.21854 | Q8: =Assumptions!Q10 -> 141.16781 | R8: =Assumptions!R10 -> 146.8498 | S8: =Assumptions!S10 -> 138.76409 | T8: =Assumptions!T10 -> 145.90974 | U8: =SUM(Q8:T8) -> 572.69144 | V8: =Assumptions!V10 -> 158.80701 | W8: =Assumptions!W10 -> 165.38773 | X8: =Assumptions!X10 -> 154.80182 | Y8: =Assumptions!Y10 -> 162.60189 | Z8: =SUM(V8:Y8) -> 641.59844 | AA8: =Assumptions!AA10 -> 175.92554 | AB8: =Assumptions!AB10 -> 183.11879 | AC8: =Assumptions!AC10 -> 171.30563 | AD8: =Assumptions!AD10 -> 179.73848 | AE8: =SUM(AA8:AD8) -> 710.08845 | AF8: =Assumptions!AF10 -> 192.342 | AG8: =Assumptions!AG10 -> 199.95215 | AH8: =Assumptions!AH10 -> 186.7566 | AI8: =Assumptions!AI10 -> 195.58029 | AJ8: =SUM(AF8:AI8) -> 774.63104 | AK8: =Assumptions!AK10 -> 209.04859 | AL8: =Assumptions!AL10 -> 217.24156 | AM8: =Assumptions!AM10 -> 202.8331 | AN8: =Assumptions!AN10 -> 212.24747 | AO8: =SUM(AK8:AN8) -> 841.37072
A9: Corporate-owned stores | B9: 105.882 | C9: 113.759 | D9: 113.245 | E9: 116.411 | F9: 449.297 | G9: 122.378 | H9: 125.466 | I9: 128.132 | J9: 126.311 | K9: =SUM(G9:J9) -> 502.287 | L9: 133.669 | M9: 138.989 | N9: 137.833 | O9: =Assumptions!O14 -> 136.30695 | P9: =SUM(L9:O9) -> 546.79795 | Q9: =Assumptions!Q14 -> 146.14797 | R9: =Assumptions!R14 -> 151.12276 | S9: =Assumptions!S14 -> 151.39635 | T9: =Assumptions!T14 -> 151.14316 | U9: =SUM(Q9:T9) -> 599.81025 | V9: =Assumptions!V14 -> 161.94077 | W9: =Assumptions!W14 -> 168.48763 | X9: =Assumptions!X14 -> 169.47154 | Y9: =Assumptions!Y14 -> 169.46958 | Z9: =SUM(V9:Y9) -> 669.36952 | AA9: =Assumptions!AA14 -> 179.60022 | AB9: =Assumptions!AB14 -> 186.72059 | AC9: =Assumptions!AC14 -> 187.61465 | AD9: =Assumptions!AD14 -> 187.32937 | AE9: =SUM(AA9:AD9) -> 741.26483 | AF9: =Assumptions!AF14 -> 198.29744 | AG9: =Assumptions!AG14 -> 205.73328 | AH9: =Assumptions!AH14 -> 205.95842 | AI9: =Assumptions!AI14 -> 204.54822 | AJ9: =SUM(AF9:AI9) -> 814.53737 | AK9: =Assumptions!AK14 -> 213.66338 | AL9: =Assumptions!AL14 -> 221.58403 | AM9: =Assumptions!AM14 -> 221.70691 | AN9: =Assumptions!AN14 -> 220.01561 | AO9: =SUM(AK9:AN9) -> 876.96993
A10: Equipment | B10: 23.661 | C10: 73.862 | D10: 66.141 | E10: 70.437 | F10: 234.101 | G10: 21.619 | H10: 67.685 | I10: 61.699 | J10: 105.117 | K10: =SUM(G10:J10) -> 256.12 | L10: 27.813 | M10: 82.232 | N10: 78.837 | O10: =Assumptions!O18 -> 105.117 | P10: =SUM(L10:O10) -> 293.999 | Q10: =Assumptions!Q18 -> 30.31617 | R10: =Assumptions!R18 -> 89.63288 | S10: =Assumptions!S18 -> 85.93233 | T10: =Assumptions!T18 -> 113.52636 | U10: =SUM(Q10:T10) -> 319.40774 | V10: =Assumptions!V18 -> 32.286721 | W10: =Assumptions!W18 -> 95.459017 | X10: =Assumptions!X18 -> 91.517931 | Y10: =Assumptions!Y18 -> 120.90557 | Z10: =SUM(V10:Y10) -> 340.16924 | AA10: =Assumptions!AA18 -> 33.57819 | AB10: =Assumptions!AB18 -> 99.277378 | AC10: =Assumptions!AC18 -> 95.178649 | AD10: =Assumptions!AD18 -> 125.7418 | AE10: =SUM(AA10:AD10) -> 353.77601 | AF10: =Assumptions!AF18 -> 34.417645 | AG10: =Assumptions!AG18 -> 101.75931 | AH10: =Assumptions!AH18 -> 97.558115 | AI10: =Assumptions!AI18 -> 128.88534 | AJ10: =SUM(AF10:AI10) -> 362.62041 | AK10: =Assumptions!AK18 -> 35.278086 | AL10: =Assumptions!AL18 -> 104.3033 | AM10: =Assumptions!AM18 -> 99.997068 | AN10: =Assumptions!AN18 -> 132.10747 | AO10: =SUM(AK10:AN10) -> 371.68592
A11: Total revenue | B11: =SUM(B8:B10) -> 205.421 | C11: =SUM(C8:C10) -> 268.467 | D11: =SUM(D8:D10) -> 259.973 | E11: =SUM(E8:E10) -> 267.452 | F11: =SUM(F8:F10) -> 1071.325 | G11: =SUM(G8:G10) -> 248.017 | H11: =SUM(H8:H10) -> 300.941 | I11: =SUM(I8:I10) -> 292.246 | ... AO11: =SUM(AO8:AO10) -> 2090.0266
A12: Operating costs and expenses:
A13: Cost of revenue | B13: 19.354 | C13: 59.457 | D13: 53.751 | E13: 57.465 | F13: 190.027 | G13: 18.993 | H13: 51.934 | I13: 45.701 | J13: 80.494 | K13: =SUM(G13:J13) -> 197.122 | L13: 22.485 | M13: 59.423 | N13: 58.155 | O13: =Assumptions!O96 -> 85.383339 | P13: =SUM(L13:O13) -> 225.44634 | Q13: =Assumptions!Q96 -> 23.908937 | R13: =Assumptions!R96 -> 65.242854 | S13: =Assumptions!S96 -> 63.95203 | T13: =Assumptions!T96 -> 94.611475 | U13: =SUM(Q13:T13) -> 247.7153 | V13: =Assumptions!V96 -> 24.808601 | W13: =Assumptions!W96 -> 70.120115 | X13: =Assumptions!X96 -> 68.623537 | Y13: =Assumptions!Y96 -> 102.11649 | Z13: =SUM(V13:Y13) -> 265.66874 | AA13: =Assumptions!AA96 -> 27.34329 | AB13: =Assumptions!AB96 -> 76.617488 | AC13: =Assumptions!AC96 -> 74.945952 | AD13: =Assumptions!AD96 -> 111.09612 | AE13: =SUM(AA13:AD13) -> 290.00285 | AF13: =Assumptions!AF96 -> 29.869806 | AG13: =Assumptions!AG96 -> 82.877324 | AH13: =Assumptions!AH96 -> 80.916261 | AI13: =Assumptions!AI96 -> 119.25778 | AJ13: =SUM(AF13:AI13) -> 312.92117 | AK13: =Assumptions!AK96 -> 32.184086 | AL13: =Assumptions!AL96 -> 88.705361 | AM13: =Assumptions!AM96 -> 86.571294 | AN13: =Assumptions!AN96 -> 127.22838 | AO13: =SUM(AK13:AN13) -> 334.68912
A14: Store operations | B14: 66.015 | C14: 58.876 | D14: 63.12 | E14: 65.608 | F14: 253.619 | G14: 74.353 | H14: 70.152 | I14: 71.614 | J14: 74.388 | K14: =SUM(G14:J14) -> 290.507 | L14: 81.68 | M14: 77.437 | N14: 79.792 | O14: =Assumptions!O100 -> 77.642842 | P14: =SUM(L14:O14) -> 316.55184 | Q14: =Assumptions!Q100 -> 91.869927 | R14: =Assumptions!R100 -> 85.726147 | S14: =Assumptions!S100 -> 88.585427 | T14: =Assumptions!T100 -> 85.811065 | U14: =SUM(Q14:T14) -> 351.99257 | V14: =Assumptions!V100 -> 100.34437 | W14: =Assumptions!W100 -> 94.955275 | X14: =Assumptions!X100 -> 97.936071 | Y14: =Assumptions!Y100 -> 94.672202 | Z14: =SUM(V14:Y14) -> 387.90792 | AA14: =Assumptions!AA100 -> 110.59653 | AB14: =Assumptions!AB100 -> 103.75389 | AC14: =Assumptions!AC100 -> 106.95911 | AD14: =Assumptions!AD100 -> 102.99722 | AE14: =SUM(AA14:AD14) -> 424.30674 | AF14: =Assumptions!AF100 -> 120.81563 | AG14: =Assumptions!AG100 -> 112.23084 | AH14: =Assumptions!AH100 -> 115.47963 | AI14: =Assumptions!AI100 -> 110.56389 | AJ14: =SUM(AF14:AI14) -> 459.09 | AK14: =Assumptions!AK100 -> 130.1763 | AL14: =Assumptions!AL100 -> 120.12305 | AM14: =Assumptions!AM100 -> 123.55021 | AN14: =Assumptions!AN100 -> 117.95344 | AO14: =SUM(AK14:AN14) -> 491.803
A15: Selling, general and administrative | B15: 27.767 | C15: 32.646 | D15: 33.29 | E15: 31.225 | F15: 124.928 | G15: 29.193 | H15: 31.613 | I15: 32.647 | J15: 35.693 | K15: =SUM(G15:J15) -> 129.146 | L15: 34.307 | M15: 35.511 | N15: 30.525 | O15: =Assumptions!O104 -> 35.390691 | P15: =SUM(L15:O15) -> 135.73369 | Q15: =Assumptions!Q104 -> 39.387409 | R15: =Assumptions!R104 -> 40.378717 | S15: =Assumptions!S104 -> 34.75225 | T15: =Assumptions!T104 -> 40.236768 | U15: =SUM(Q15:T15) -> 154.75514 | V15: =Assumptions!V104 -> 43.777442 | W15: =Assumptions!W104 -> 44.72582 | X15: =Assumptions!X104 -> 38.420527 | Y15: =Assumptions!Y104 -> 44.39175 | Z15: =SUM(V15:Y15) -> 171.31554 | AA15: =Assumptions!AA104 -> 48.250172 | AB15: =Assumptions!AB104 -> 48.870142 | AC15: =Assumptions!AC104 -> 41.960283 | AD15: =Assumptions!AD104 -> 48.295346 | AE15: =SUM(AA15:AD15) -> 187.37594 | AF15: =Assumptions!AF104 -> 44.205938 | AG15: =Assumptions!AG104 -> 52.774254 | AH15: =Assumptions!AH104 -> 50.988406 | AI15: =Assumptions!AI104 -> 55.017441 | AJ15: =SUM(AF15:AI15) -> 202.98604 | AK15: =Assumptions!AK104 -> 47.630966 | AL15: =Assumptions!AL104 -> 56.485405 | AM15: =Assumptions!AM104 -> 54.551857 | AN15: =Assumptions!AN104 -> 58.694537 | AO15: =SUM(AK15:AN15) -> 217.36276
A16: National advertising fund expense | B16: 16.987 | C16: 17.89 | D16: 17.618 | E16: 17.599 | F16: 70.094 | G16: 19.792 | H16: 20.112 | I16: 19.72 | J16: 19.385 | K16: =SUM(G16:J16) -> 79.009 | L16: 21.944 | M16: 22.777 | N16: 21.429 | O16: =Assumptions!O108 -> 20.35425 | P16: =SUM(L16:O16) -> 86.50425 | Q16: =Assumptions!Q108 -> 27.43 | R16: =Assumptions!R108 -> 28.47125 | S16: =Assumptions!S108 -> 26.78625 | T16: =Assumptions!T108 -> 25.442812 | U16: =SUM(Q16:T16) -> 108.13031 | V16: =Assumptions!V108 -> 29.3501 | W16: =Assumptions!W108 -> 30.464237 | X16: =Assumptions!X108 -> 28.661288 | Y16: =Assumptions!Y108 -> 27.223809 | Z16: =SUM(V16:Y16) -> 115.69943 | AA16: =Assumptions!AA108 -> 30.817605 | AB16: =Assumptions!AB108 -> 31.987449 | AC16: =Assumptions!AC108 -> 30.094352 | AD16: =Assumptions!AD108 -> 28.585 | AE16: =SUM(AA16:AD16) -> 121.48441 | AF16: =Assumptions!AF108 -> 32.358485 | AG16: =Assumptions!AG108 -> 33.586822 | AH16: =Assumptions!AH108 -> 31.599069 | AI16: =Assumptions!AI108 -> 30.01425 | AJ16: =SUM(AF16:AI16) -> 127.55863 | AK16: =Assumptions!AK108 -> 33.97641 | AL16: =Assumptions!AL108 -> 35.266163 | AM16: =Assumptions!AM108 -> 33.179023 | AN16: =Assumptions!AN108 -> 31.514962 | AO16: =SUM(AK16:AN16) -> 133.93656
A17: Depreciation and amortization | B17: 36.01 | C17: 36.767 | D17: 37.477 | E17: 39.159 | F17: 149.413 | G17: 39.38 | H17: 39.817 | I17: 41.033 | J17: 40.116 | K17: =SUM(G17:J17) -> 160.346 | L17: 38.281 | M17: 38.429 | N17: 39.108 | O17: =-Assumptions!O122-Assumptions!O137 -> 39.123781 | P17: =SUM(L17:O17) -> 154.94178 | Q17: =-Assumptions!Q122-Assumptions!Q137 -> 35.633367 | R17: =-Assumptions!R122-Assumptions!R137 -> 35.966672 | S17: =-Assumptions!S122-Assumptions!S137 -> 36.943464 | T17: =-Assumptions!T122-Assumptions!T137 -> 38.155528 | U17: =SUM(Q17:T17) -> 146.69903 | V17: =-Assumptions!V122-Assumptions!V137 -> 37.793067 | W17: =-Assumptions!W122-Assumptions!W137 -> 38.250358 | X17: =-Assumptions!X122-Assumptions!X137 -> 35.958162 | Y17: =-Assumptions!Y122-Assumptions!Y137 -> 39.650888 | Z17: =SUM(V17:Y17) -> 151.65247 | AA17: =-Assumptions!AA122-Assumptions!AA137 -> 40.006207 | AB17: =-Assumptions!AB122-Assumptions!AB137 -> 40.541347 | AC17: =-Assumptions!AC122-Assumptions!AC137 -> 38.098447 | AD17: =-Assumptions!AD122-Assumptions!AD137 -> 42.10975 | AE17: =SUM(AA17:AD17) -> 160.75575 | AF17: =-Assumptions!AF122-Assumptions!AF137 -> 41.786972 | AG17: =-Assumptions!AG122-Assumptions!AG137 -> 42.3786 | AH17: =-Assumptions!AH122-Assumptions!AH137 -> 39.735371 | AI17: =-Assumptions!AI122-Assumptions!AI137 -> 44.060158 | AJ17: =SUM(AF17:AI17) -> 167.9611 | AK17: =-Assumptions!AK122-Assumptions!AK137 -> 46.006641 | AL17: =-Assumptions!AL122-Assumptions!AL137 -> 46.628034 | AM17: =-Assumptions!AM122-Assumptions!AM137 -> 43.7483 | AN17: =-Assumptions!AN122-Assumptions!AN137 -> 48.385276 | AO17: =SUM(AK17:AN17) -> 184.76825
A18: Other (gain) loss | B18: 3.936 | C18: 3.825 | D18: -0.056 | E18: 2.674 | F18: 10.379 | G18: 0.484 | H18: -0.066 | I18: 0.28 | J18: 0.628 | K18: =SUM(G18:J18) -> 1.326 | L18: -1.237 | M18: 4.9 | N18: -5.732 | O18: =Assumptions!O111 -> 0 | P18: =SUM(L18:O18) -> -2.069 | Q18: =Assumptions!Q111 -> 0 | R18: =Assumptions!R111 -> 0 | S18: =Assumptions!S111 -> 0 | T18: =Assumptions!T111 -> 0 | U18: =SUM(Q18:T18) -> 0 | V18: =Assumptions!V111 -> 0 | W18: =Assumptions!W111 -> 0 | X18: =Assumptions!X111 -> 0 | Y18: =Assumptions!Y111 -> 0 | Z18: =SUM(V18:Y18) -> 0 | AA18: =Assumptions!AA111 -> 0 | AB18: =Assumptions!AB111 -> 0 | AC18: =Assumptions!AC111 -> 0 | AD18: =Assumptions!AD111 -> 0 | AE18: =SUM(AA18:AD18) -> 0 | AF18: =Assumptions!AF111 -> 0 | AG18: =Assumptions!AG111 -> 0 | AH18: =Assumptions!AH111 -> 0 | AI18: =Assumptions!AI111 -> 0 | AJ18: =SUM(AF18:AI18) -> 0 | AK18: =Assumptions!AK111 -> 0 | AL18: =Assumptions!AL111 -> 0 | AM18: =Assumptions!AM111 -> 0 | AN18: =Assumptions!AN111 -> 0 | AO18: =SUM(AK18:AN18) -> 0
A19: Total operating costs and expenses | B19: =SUM(B12:B18) -> 170.069 | C19: =SUM(C12:C18) -> 209.461 | D19: =SUM(D12:D18) -> 205.2 | E19: =SUM(E12:E18) -> 213.73 | F19: =SUM(F12:F18) -> 798.46 | G19: =SUM(G12:G18) -> 182.195 | H19: =SUM(H12:H18) -> 213.562 | I19: =SUM(I12:I18) -> 210.995 | ... AO19: =SUM(AO12:AO18) -> 1362.5597
A20: Income from operations | B20: =B11-B19 -> 35.352 | C20: =C11-C19 -> 59.006 | D20: =D11-D19 -> 54.773 | E20: =E11-E19 -> 53.722 | F20: =F11-F19 -> 272.865 | G20: =G11-G19 -> 65.822 | H20: =H11-H19 -> 87.379 | I20: =I11-I19 -> 81.251 | ... AO20: =AO11-AO19 -> 727.46688
A21: Other income (expense), net:
A22: Interest income | B22: 3.931 | C22: 4.163 | D22: 4.245 | E22: 5.402 | F22: 17.741 | G22: 5.461 | H22: 5.616 | I22: 5.61 | J22: 6.428 | K22: =SUM(G22:J22) -> 23.115 | L22: 5.812 | M22: 5.69 | N22: 5.936 | O22: =Assumptions!O152 -> 4.3729962 | P22: =SUM(L22:O22) -> 21.810996 | Q22: =Assumptions!Q152 -> 4.3997895 | R22: =Assumptions!R152 -> 5.5531461 | S22: =Assumptions!S152 -> 6.0778966 | T22: =Assumptions!T152 -> 6.3955222 | U22: =SUM(Q22:T22) -> 22.426354 | V22: =Assumptions!V152 -> 6.8113158 | W22: =Assumptions!W152 -> 8.1209775 | X22: =Assumptions!X152 -> 8.6953001 | Y22: =Assumptions!Y152 -> 9.1922914 | Z22: =SUM(V22:Y22) -> 32.819885 | AA22: =Assumptions!AA152 -> 9.7195021 | AB22: =Assumptions!AB152 -> 11.221024 | AC22: =Assumptions!AC152 -> 11.882822 | AD22: =Assumptions!AD152 -> 12.468632 | AE22: =SUM(AA22:AD22) -> 45.29198 | AF22: =Assumptions!AF152 -> 13.069652 | AG22: =Assumptions!AG152 -> 14.846825 | AH22: =Assumptions!AH152 -> 15.636341 | AI22: =Assumptions!AI152 -> 16.311401 | AJ22: =SUM(AF22:AI22) -> 59.86422 | AK22: =Assumptions!AK152 -> 17.009142 | AL22: =Assumptions!AL152 -> 18.965588 | AM22: =Assumptions!AM152 -> 19.845009 | AN22: =Assumptions!AN152 -> 20.60315 | AO22: =SUM(AK22:AN22) -> 76.42289
A23: Interest expense | B23: -21.599 | C23: -21.468 | D23: -21.704 | E23: -21.805 | F23: -86.576 | G23: -21.433 | H23: -24.533 | I23: -26.603 | J23: -27.468 | K23: =SUM(G23:J23) -> -100.037 | L23: -26.197 | M23: -26.181 | N23: -26.342 | O23: =-Assumptions!O151 -> -27.743262 | P23: =SUM(L23:O23) -> -106.46326 | Q23: =-Assumptions!Q151 -> -26.362049 | R23: =-Assumptions!R151 -> -26.362049 | S23: =-Assumptions!S151 -> -26.362049 | T23: =-Assumptions!T151 -> -26.362049 | U23: =SUM(Q23:T23) -> -105.4482 | V23: =-Assumptions!V151 -> -26.334104 | W23: =-Assumptions!W151 -> -26.278213 | X23: =-Assumptions!X151 -> -26.222322 | Y23: =-Assumptions!Y151 -> -26.166432 | Z23: =SUM(V23:Y23) -> -105.00107 | AA23: =-Assumptions!AA151 -> -26.110541 | AB23: =-Assumptions!AB151 -> -26.054651 | AC23: =-Assumptions!AC151 -> -25.99876 | AD23: =-Assumptions!AD151 -> -25.942869 | AE23: =SUM(AA23:AD23) -> -104.10682 | AF23: =-Assumptions!AF151 -> -25.914924 | AG23: =-Assumptions!AG151 -> -25.914924 | AH23: =-Assumptions!AH151 -> -25.914924 | AI23: =-Assumptions!AI151 -> -25.914924 | AJ23: =SUM(AF23:AI23) -> -103.6597 | AK23: =-Assumptions!AK151 -> -25.914924 | AL23: =-Assumptions!AL151 -> -25.914924 | AM23: =-Assumptions!AM151 -> -25.914924 | AN23: =-Assumptions!AN151 -> -25.914924 | AO23: =SUM(AK23:AN23) -> -103.6597
A24: Other income (expense), net | B24: 0.113 | C24: 0.37 | D24: 0.148 | E24: 2.881 | F24: 3.512 | G24: 0.647 | H24: 1.043 | I24: -0.558 | J24: -1.68 | K24: =SUM(G24:J24) -> -0.548 | L24: 0.283 | M24: 1.942 | N24: 1.067 | O24: =N24 -> 1.067 | P24: =SUM(L24:O24) -> 4.359 | Q24: =O24 -> 1.067 | R24: =Q24 -> 1.067 | S24: =R24 -> 1.067 | T24: =S24 -> 1.067 | U24: =SUM(Q24:T24) -> 4.268 | V24: =Q24 -> 1.067 | W24: =V24 -> 1.067 | X24: =W24 -> 1.067 | Y24: =X24 -> 1.067 | Z24: =SUM(V24:Y24) -> 4.268 | AA24: =Y24 -> 1.067 | AB24: =AA24 -> 1.067 | AC24: =AB24 -> 1.067 | AD24: =AC24 -> 1.067 | AE24: =SUM(AA24:AD24) -> 4.268 | AF24: =AD24 -> 1.067 | AG24: =AF24 -> 1.067 | AH24: =AG24 -> 1.067 | AI24: =AH24 -> 1.067 | AJ24: =SUM(AF24:AI24) -> 4.268 | AK24: =AI24 -> 1.067 | AL24: =AK24 -> 1.067 | AM24: =AL24 -> 1.067 | AN24: =AM24 -> 1.067 | AO24: =SUM(AK24:AN24) -> 4.268
A25: Total other expense, net | B25: =SUM(B22:B24) -> -17.555 | C25: =SUM(C22:C24) -> -16.935 | D25: =SUM(D22:D24) -> -17.311 | E25: =SUM(E22:E24) -> -13.522 | F25: =SUM(F22:F24) -> -65.323 | G25: =SUM(G22:G24) -> -15.325 | H25: =SUM(H22:H24) -> -17.874 | I25: =SUM(I22:I24) -> -21.551 | ... AO25: =SUM(AO22:AO24) -> -22.968806
A27: Income before income taxes | B27: =B20+B25 -> 17.797 | C27: =C20+C25 -> 42.071 | D27: =D20+D25 -> 37.462 | E27: =E20+E25 -> 40.2 | F27: =F20+F25 -> 207.542 | G27: =G20+G25 -> 50.497 | H27: =H20+H25 -> 69.505 | I27: =I20+I25 -> 59.7 | ... AO27: =AO20+AO25 -> 704.49808
A28: Provision for income taxes | B28: 9.567 | C28: 15.814 | D28: 13.474 | E28: 19.657 | F28: 58.512 | G28: 14.324 | H28: 18.977 | I28: 16.523 | J28: 18.619 | K28: =SUM(G28:J28) -> 68.443 | L28: 16.216 | M28: 24.93 | N28: 27.974 | O28: =O27*Assumptions!O157 -> 22.417978 | P28: =SUM(L28:O28) -> 91.537978 | Q28: =Q27*Assumptions!Q157 -> 22.060482 | R28: =R27*Assumptions!R157 -> 31.493889 | S28: =S27*Assumptions!S157 -> 29.745594 | T28: =T27*Assumptions!T157 -> 30.185606 | U28: =SUM(Q28:T28) -> 113.48557 | V28: =V27*Assumptions!V157 -> 27.679942 | W28: =W27*Assumptions!W157 -> 37.577661 | X28: =X27*Assumptions!X157 -> 36.454603 | Y28: =Y27*Assumptions!Y157 -> 36.25315 | Z28: =SUM(V28:Y28) -> 137.96536 | AA28: =AA27*Assumptions!AA157 -> 32.811275 | AB28: =AB27*Assumptions!AB157 -> 43.155928 | AC28: =AC27*Assumptions!AC157 -> 41.86671 | AD28: =AD27*Assumptions!AD157 -> 41.396635 | AE28: =SUM(AA28:AD28) -> 159.23055 | AF28: =AF27*Assumptions!AF157 -> 40.531998 | AG28: =AG27*Assumptions!AG157 -> 48.780423 | AH28: =AH27*Assumptions!AH157 -> 45.618332 | AI28: =AI27*Assumptions!AI157 -> 45.39943 | AJ28: =SUM(AF28:AI28) -> 180.33018 | AK28: =AK27*Assumptions!AK157 -> 45.009701 | AL28: =AL27*Assumptions!AL157 -> 53.400831 | AM28: =AM27*Assumptions!AM157 -> 49.99931 | AN28: =AN27*Assumptions!AN157 -> 49.554117 | AO28: =SUM(AK28:AN28) -> 197.96396
A29: Losses from equity-method investments, net of tax | B29: -0.265 | C29: -0.073 | D29: -0.242 | E29: -1.414 | F29: -1.994 | G29: -1.2 | H29: -1.216 | I29: -0.782 | J29: -0.844 | K29: =SUM(G29:J29) -> -4.042 | L29: -0.805 | M29: -0.628 | N29: -0.572 | O29: 0 | P29: =SUM(L29:O29) -> -2.005 | Q29: 0 | R29: 0 | S29: 0 | T29: 0 | U29: =SUM(Q29:T29) -> 0 | V29: 0 | W29: 0 | X29: 0 | Y29: 0 | Z29: =SUM(V29:Y29) -> 0 | AA29: 0 | AB29: 0 | AC29: 0 | AD29: 0 | AE29: =SUM(AA29:AD29) -> 0 | AF29: 0 | AG29: 0 | AH29: 0 | AI29: 0 | AJ29: =SUM(AF29:AI29) -> 0 | AK29: 0 | AL29: 0 | AM29: 0 | AN29: 0 | AO29: =SUM(AK29:AN29) -> 0
A30: Net income | B30: =B27-B28+B29 -> 7.965 | C30: =C27-C28+C29 -> 26.184 | D30: =D27-D28+D29 -> 23.746 | E30: =E27-E28+E29 -> 19.129 | F30: =F27-F28+F29 -> 147.036 | G30: =G27-G28+G29 -> 34.973 | H30: =H27-H28+H29 -> 49.312 | I30: =I27-I28+I29 -> 42.395 | ... AO30: =AO27-AO28+AO29 -> 506.53412
A32: Less net income attributable to non-controlling interests | B32: 2.064 | C32: 3.045 | D32: 2.19 | E32: 1.423 | F32: 8.722 | G32: 0.664 | H32: 0.672 | I32: 0.386 | J32: 0.479 | K32: =SUM(G32:J32) -> 2.201 | L32: 0.212 | M32: 0.276 | N32: 0.354 | O32: 0 | P32: =SUM(L32:O32) -> 0.842 | Q32: 0 | R32: 0 | S32: 0 | T32: 0 | U32: =SUM(Q32:T32) -> 0 | V32: 0 | W32: 0 | X32: 0 | Y32: 0 | Z32: =SUM(V32:Y32) -> 0 | AA32: 0 | AB32: 0 | AC32: 0 | AD32: 0 | AE32: =SUM(AA32:AD32) -> 0 | AF32: 0 | AG32: 0 | AH32: 0 | AI32: 0 | AJ32: =SUM(AF32:AI32) -> 0 | AK32: 0 | AL32: 0 | AM32: 0 | AN32: 0 | AO32: =SUM(AK32:AN32) -> 0
A33: Net income attributable to Planet Fitness, Inc. | B33: =B30-B32 -> 5.901 | C33: =C30-C32 -> 23.139 | D33: =D30-D32 -> 21.556 | E33: =E30-E32 -> 17.706 | F33: =SUM(B33:E33) -> 68.302 | G33: =G30-G32 -> 34.309 | H33: =H30-H32 -> 48.64 | I33: =I30-I32 -> 42.009 | J33: =J30-J32 -> 47.084 | K33: =SUM(G33:J33) -> 172.042 | L33: =L30-L32 -> 41.867 | M33: =M30-M32 -> 58.019 | N33: =N30-N32 -> 58.829 | O33: =O30-O32 -> 58.51335 | P33: =SUM(L33:O33) -> 217.22835 | Q33: =Q30-Q32 -> 56.446571 | R33: =R30-R32 -> 80.584008 | S33: =S30-S32 -> 76.110612 | T33: =T30-T32 -> 77.236479 | U33: =SUM(Q33:T33) -> 290.37767 | V33: =V30-V32 -> 70.82519 | W33: =W30-W32 -> 96.15067 | X33: =X30-X32 -> 93.277081 | Y33: =Y30-Y32 -> 92.761618 | Z33: =SUM(V33:Y33) -> 353.01456 | AA33: =AA30-AA32 -> 83.954829 | AB33: =AB30-AB32 -> 110.42389 | AC33: =AC30-AC32 -> 107.12514 | AD33: =AD30-AD32 -> 105.92235 | AE33: =SUM(AA33:AD33) -> 407.42621 | AF33: =AF30-AF32 -> 103.70999 | AG33: =AG30-AG32 -> 124.81539 | AH33: =AH30-AH32 -> 116.72449 | AI33: =AI30-AI32 -> 116.16438 | AJ33: =SUM(AF33:AI33) -> 461.41424 | AK33: =AK30-AK32 -> 115.16717 | AL33: =AL30-AL32 -> 136.63771 | AM33: =AM30-AM32 -> 127.93418 | AN33: =AN30-AN32 -> 126.79505 | AO33: =SUM(AK33:AN33) -> 506.53412
A34: Net income per share of Class A common stock:
A35: Basic | B35: =B33/B38 -> 0.069880631 | C35: =C33/C38 -> 0.27345246 | D35: =D33/D38 -> 0.25476894 | E35: =E33/E38 -> 0.206121 | F35: =F33/F38 -> 0.80453732 | G35: =G33/G38 -> 0.39476924 | H35: =H33/H38 -> 0.56031057 | I35: =I33/I38 -> 0.49673643 | ... AO35: =AO33/AO38 -> 6.0650421
A36: Diluted | B36: =B33/B39 -> 0.069597934 | C36: =C33/C39 -> 0.27251849 | D36: =D33/D39 -> 0.25394058 | E36: =E33/E39 -> 0.20542271 | F36: =F33/F39 -> 0.80180783 | G36: =G33/G39 -> 0.39335259 | H36: =H33/H39 -> 0.55936979 | I36: =I33/I39 -> 0.49581012 | ... AO36: =AO33/AO39 -> 6.0505527
A37: Weighted-average shares of Class A common stock outstanding:
A38: Basic | B38: 84.444 | C38: 84.618 | D38: 84.61 | E38: 85.901 | F38: 84.896 | G38: 86.909 | H38: 86.809 | I38: 84.57 | J38: 84.224 | K38: =AVERAGE(G38:J38) -> 85.628 | L38: 84.17 | M38: 83.861 | N38: 83.517 | O38: =N38 -> 83.517 | P38: =AVERAGE(L38:O38) -> 83.76625 | Q38: =N38 -> 83.517 | R38: =Q38 -> 83.517 | S38: =R38 -> 83.517 | T38: =S38 -> 83.517 | U38: =AVERAGE(Q38:T38) -> 83.517 | V38: =T38 -> 83.517 | W38: =V38 -> 83.517 | X38: =W38 -> 83.517 | Y38: =X38 -> 83.517 | Z38: =AVERAGE(V38:Y38) -> 83.517 | AA38: =V38 -> 83.517 | AB38: =AA38 -> 83.517 | AC38: =AB38 -> 83.517 | AD38: =AC38 -> 83.517 | AE38: =AVERAGE(AA38:AD38) -> 83.517 | AF38: =AA38 -> 83.517 | AG38: =AB38 -> 83.517 | AH38: =AC38 -> 83.517 | AI38: =AD38 -> 83.517 | AJ38: =AVERAGE(AF38:AI38) -> 83.517 | AK38: =AF38 -> 83.517 | AL38: =AG38 -> 83.517 | AM38: =AH38 -> 83.517 | AN38: =AI38 -> 83.517 | AO38: =AVERAGE(AK38:AN38) -> 83.517
A39: Diluted | B39: 84.787 | C39: 84.908 | D39: 84.886 | E39: 86.193 | F39: 85.185 | G39: 87.222 | H39: 86.955 | I39: 84.728 | J39: 84.442 | K39: =AVERAGE(G39:J39) -> 85.83675 | L39: 84.402 | M39: 84.065 | N39: 83.717 | O39: =N39-N38+O38 -> 83.717 | P39: =AVERAGE(L39:O39) -> 83.97525 | Q39: =O39-O38+Q38 -> 83.717 | R39: =Q39-Q38+R38 -> 83.717 | S39: =R39-R38+S38 -> 83.717 | T39: =S39-S38+T38 -> 83.717 | U39: =AVERAGE(Q39:T39) -> 83.717 | V39: =T39-T38+V38 -> 83.717 | W39: =V39-V38+W38 -> 83.717 | X39: =W39-W38+X38 -> 83.717 | Y39: =X39-X38+Y38 -> 83.717 | Z39: =AVERAGE(V39:Y39) -> 83.717 | AA39: =Y39-Y38+AA38 -> 83.717 | AB39: =AA39-AA38+AB38 -> 83.717 | AC39: =AB39-AB38+AC38 -> 83.717 | AD39: =AC39-AC38+AD38 -> 83.717 | AE39: =AVERAGE(AA39:AD39) -> 83.717 | AF39: =AD39-AD38+AF38 -> 83.717 | AG39: =AF39-AF38+AG38 -> 83.717 | AH39: =AG39-AG38+AH38 -> 83.717 | AI39: =AH39-AH38+AI38 -> 83.717 | AJ39: =AVERAGE(AF39:AI39) -> 83.717 | AK39: =AI39-AI38+AK38 -> 83.717 | AL39: =AK39-AK38+AL38 -> 83.717 | AM39: =AL39-AL38+AM38 -> 83.717 | AN39: =AM39-AM38+AN38 -> 83.717 | AO39: =AVERAGE(AK39:AN39) -> 83.717
A41: Non-GAAP measures
A42: Net Income (GAAP) | B42: =B30 -> 7.965 | C42: =C30 -> 26.184 | D42: =D30 -> 23.746 | E42: =E30 -> 19.129 | F42: =F30 -> 147.036 | G42: =G30 -> 34.973 | H42: =H30 -> 49.312 | I42: =I30 -> 42.395 | J42: =J30 -> 47.563 | K42: =SUM(G42:J42) -> 174.243 | L42: =L30 -> 42.079 | M42: =M30 -> 58.295 | N42: =N30 -> 59.183 | O42: =O30 -> 58.51335 | P42: =SUM(L42:O42) -> 218.07035 | Q42: =Q30 -> 56.446571 | R42: =R30 -> 80.584008 | S42: =S30 -> 76.110612 | T42: =T30 -> 77.236479 | U42: =SUM(Q42:T42) -> 290.37767 | V42: =V30 -> 70.82519 | W42: =W30 -> 96.15067 | X42: =X30 -> 93.277081 | Y42: =Y30 -> 92.761618 | Z42: =SUM(V42:Y42) -> 353.01456 | AA42: =AA30 -> 83.954829 | AB42: =AB30 -> 110.42389 | AC42: =AC30 -> 107.12514 | AD42: =AD30 -> 105.92235 | AE42: =SUM(AA42:AD42) -> 407.42621 | AF42: =AF30 -> 103.70999 | AG42: =AG30 -> 124.81539 | AH42: =AH30 -> 116.72449 | AI42: =AI30 -> 116.16438 | AJ42: =SUM(AF42:AI42) -> 461.41424 | AK42: =AK30 -> 115.16717 | AL42: =AL30 -> 136.63771 | AM42: =AM30 -> 127.93418 | AN42: =AN30 -> 126.79505 | AO42: =SUM(AK42:AN42) -> 506.53412
A43: Interest income | B43: =-B22 -> -3.931 | C43: =-C22 -> -4.163 | D43: =-D22 -> -4.245 | E43: =-E22 -> -5.402 | F43: =-F22 -> -17.741 | G43: =-G22 -> -5.461 | H43: =-H22 -> -5.616 | I43: =-I22 -> -5.61 | J43: =-J22 -> -6.428 | K43: =SUM(G43:J43) -> -23.115 | L43: =-L22 -> -5.812 | M43: =-M22 -> -5.69 | N43: =-N22 -> -5.936 | O43: =-O22 -> -4.3729962 | P43: =SUM(L43:O43) -> -21.810996 | Q43: =-Q22 -> -4.3997895 | R43: =-R22 -> -5.5531461 | S43: =-S22 -> -6.0778966 | T43: =-T22 -> -6.3955222 | U43: =SUM(Q43:T43) -> -22.426354 | V43: =-V22 -> -6.8113158 | W43: =-W22 -> -8.1209775 | X43: =-X22 -> -8.6953001 | Y43: =-Y22 -> -9.1922914 | Z43: =SUM(V43:Y43) -> -32.819885 | AA43: =-AA22 -> -9.7195021 | AB43: =-AB22 -> -11.221024 | AC43: =-AC22 -> -11.882822 | AD43: =-AD22 -> -12.468632 | AE43: =SUM(AA43:AD43) -> -45.29198 | AF43: =-AF22 -> -13.069652 | AG43: =-AG22 -> -14.846825 | AH43: =-AH22 -> -15.636341 | AI43: =-AI22 -> -16.311401 | AJ43: =SUM(AF43:AI43) -> -59.86422 | AK43: =-AK22 -> -17.009142 | AL43: =-AL22 -> -18.965588 | AM43: =-AM22 -> -19.845009 | AN43: =-AN22 -> -20.60315 | AO43: =SUM(AK43:AN43) -> -76.42289
A44: Interest expense | B44: =-B23 -> 21.599 | C44: =-C23 -> 21.468 | D44: =-D23 -> 21.704 | E44: =-E23 -> 21.805 | F44: =-F23 -> 86.576 | G44: =-G23 -> 21.433 | H44: =-H23 -> 24.533 | I44: =-I23 -> 26.603 | J44: =-J23 -> 27.468 | K44: =SUM(G44:J44) -> 100.037 | L44: =-L23 -> 26.197 | M44: =-M23 -> 26.181 | N44: =-N23 -> 26.342 | O44: =-O23 -> 27.743262 | P44: =SUM(L44:O44) -> 106.46326 | Q44: =-Q23 -> 26.362049 | R44: =-R23 -> 26.362049 | S44: =-S23 -> 26.362049 | T44: =-T23 -> 26.362049 | U44: =SUM(Q44:T44) -> 105.4482 | V44: =-V23 -> 26.334104 | W44: =-W23 -> 26.278213 | X44: =-X23 -> 26.222322 | Y44: =-Y23 -> 26.166432 | Z44: =SUM(V44:Y44) -> 105.00107 | AA44: =-AA23 -> 26.110541 | AB44: =-AB23 -> 26.054651 | AC44: =-AC23 -> 25.99876 | AD44: =-AD23 -> 25.942869 | AE44: =SUM(AA44:AD44) -> 104.10682 | AF44: =-AF23 -> 25.914924 | AG44: =-AG23 -> 25.914924 | AH44: =-AH23 -> 25.914924 | AI44: =-AI23 -> 25.914924 | AJ44: =SUM(AF44:AI44) -> 103.6597 | AK44: =-AK23 -> 25.914924 | AL44: =-AL23 -> 25.914924 | AM44: =-AM23 -> 25.914924 | AN44: =-AN23 -> 25.914924 | AO44: =SUM(AK44:AN44) -> 103.6597
A45: Provision for income taxes | B45: =B28 -> 9.567 | C45: =C28 -> 15.814 | D45: =D28 -> 13.474 | E45: =E28 -> 19.657 | F45: =F28 -> 58.512 | G45: =G28 -> 14.324 | H45: =H28 -> 18.977 | I45: =I28 -> 16.523 | J45: =J28 -> 18.619 | K45: =SUM(G45:J45) -> 68.443 | L45: =L28 -> 16.216 | M45: =M28 -> 24.93 | N45: =N28 -> 27.974 | O45: =O28 -> 22.417978 | P45: =SUM(L45:O45) -> 91.537978 | Q45: =Q28 -> 22.060482 | R45: =R28 -> 31.493889 | S45: =S28 -> 29.745594 | T45: =T28 -> 30.185606 | U45: =SUM(Q45:T45) -> 113.48557 | V45: =V28 -> 27.679942 | W45: =W28 -> 37.577661 | X45: =X28 -> 36.454603 | Y45: =Y28 -> 36.25315 | Z45: =SUM(V45:Y45) -> 137.96536 | AA45: =AA28 -> 32.811275 | AB45: =AB28 -> 43.155928 | AC45: =AC28 -> 41.86671 | AD45: =AD28 -> 41.396635 | AE45: =SUM(AA45:AD45) -> 159.23055 | AF45: =AF28 -> 40.531998 | AG45: =AG28 -> 48.780423 | AH45: =AH28 -> 45.618332 | AI45: =AI28 -> 45.39943 | AJ45: =SUM(AF45:AI45) -> 180.33018 | AK45: =AK28 -> 45.009701 | AL45: =AL28 -> 53.400831 | AM45: =AM28 -> 49.99931 | AN45: =AN28 -> 49.554117 | AO45: =SUM(AK45:AN45) -> 197.96396
B46: ='Cash Flow Statement'!B10 -> 36.01 | C46: ='Cash Flow Statement'!C10 -> 36.767 | D46: ='Cash Flow Statement'!D10 -> 37.477 | E46: ='Cash Flow Statement'!E10 -> 39.159 | F46: ='Cash Flow Statement'!F10 -> 149.413 | G46: ='Cash Flow Statement'!G10 -> 39.38 | H46: ='Cash Flow Statement'!H10 -> 39.817 | I46: ='Cash Flow Statement'!I10 -> 41.033 | J46: ='Cash Flow Statement'!J10 -> 40.116 | K46: =SUM(G46:J46) -> 160.346 | L46: ='Cash Flow Statement'!L10 -> 38.281 | M46: ='Cash Flow Statement'!M10 -> 38.429 | N46: ='Cash Flow Statement'!N10 -> 39.108 | O46: ='Cash Flow Statement'!O10 -> 39.123781 | P46: =SUM(L46:O46) -> 154.94178 | Q46: ='Cash Flow Statement'!Q10 -> 35.633367 | R46: ='Cash Flow Statement'!R10 -> 35.966672 | S46: ='Cash Flow Statement'!S10 -> 36.943464 | T46: ='Cash Flow Statement'!T10 -> 38.155528 | U46: =SUM(Q46:T46) -> 146.69903 | V46: ='Cash Flow Statement'!V10 -> 37.793067 | W46: ='Cash Flow Statement'!W10 -> 38.250358 | X46: ='Cash Flow Statement'!X10 -> 35.958162 | Y46: ='Cash Flow Statement'!Y10 -> 39.650888 | Z46: =SUM(V46:Y46) -> 151.65247 | AA46: ='Cash Flow Statement'!AA10 -> 40.006207 | AB46: ='Cash Flow Statement'!AB10 -> 40.541347 | AC46: ='Cash Flow Statement'!AC10 -> 38.098447 | AD46: ='Cash Flow Statement'!AD10 -> 42.10975 | AE46: =SUM(AA46:AD46) -> 160.75575 | AF46: ='Cash Flow Statement'!AF10 -> 41.786972 | AG46: ='Cash Flow Statement'!AG10 -> 42.3786 | AH46: ='Cash Flow Statement'!AH10 -> 39.735371 | AI46: ='Cash Flow Statement'!AI10 -> 44.060158 | AJ46: =SUM(AF46:AI46) -> 167.9611 | AK46: ='Cash Flow Statement'!AK10 -> 46.006641 | AL46: ='Cash Flow Statement'!AL10 -> 46.628034 | AM46: ='Cash Flow Statement'!AM10 -> 43.7483 | AN46: ='Cash Flow Statement'!AN10 -> 48.385276 | AO46: =SUM(AK46:AN46) -> 184.76825
B47: =SUM(B42:B46) -> 71.21 | C47: =SUM(C42:C46) -> 96.07 | D47: =SUM(D42:D46) -> 92.156 | E47: =SUM(E42:E46) -> 94.348 | F47: =SUM(F42:F46) -> 423.796 | G47: =SUM(G42:G46) -> 104.649 | H47: =SUM(H42:H46) -> 127.023 | I47: =SUM(I42:I46) -> 120.944 | ... AO47: =SUM(AO42:AO46) -> 916.50313
A48: Adjustments | B48: =SUM(B49:B71) -> 2.197 | C48: =SUM(C49:C71) -> 4.873 | D48: =SUM(D49:D71) -> 2.158 | E48: =SUM(E49:E71) -> 2.352 | F48: 11.58 | G48: =SUM(G49:G71) -> 1.662 | H48: =SUM(H49:H71) -> 0.48 | I48: =SUM(I49:I71) -> 2.127 | J48: =SUM(J49:J71) -> 3.487 | K48: =SUM(K49:K71) -> 7.756 | L48: =SUM(L49:L71) -> 0.044 | M48: =SUM(M49:M71) -> 5.464 | N48: =SUM(N49:N71) -> -5.905 | O48: =SUM(O49:O71) -> 0 | P48: =SUM(L48:O48) -> -0.397 | Q48: =SUM(Q49:Q71) -> 0 | R48: =SUM(R49:R71) -> 0 | S48: =SUM(S49:S71) -> 0 | T48: =SUM(T49:T71) -> 0 | U48: =SUM(Q48:T48) -> 0 | V48: =SUM(V49:V71) -> 0 | W48: =SUM(W49:W71) -> 0 | X48: =SUM(X49:X71) -> 0 | Y48: =SUM(Y49:Y71) -> 0 | Z48: =SUM(V48:Y48) -> 0 | AA48: =SUM(AA49:AA71) -> 0 | AB48: =SUM(AB49:AB71) -> 0 | AC48: =SUM(AC49:AC71) -> 0 | AD48: =SUM(AD49:AD71) -> 0 | AE48: =SUM(AA48:AD48) -> 0 | AF48: =SUM(AF49:AF71) -> 0 | AG48: =SUM(AG49:AG71) -> 0 | AH48: =SUM(AH49:AH71) -> 0 | AI48: =SUM(AI49:AI71) -> 0 | AJ48: =SUM(AF48:AI48) -> 0 | AK48: =SUM(AK49:AK71) -> 0 | AL48: =SUM(AL49:AL71) -> 0 | AM48: =SUM(AM49:AM71) -> 0 | AN48: =SUM(AN49:AN71) -> 0 | AO48: =SUM(AK48:AN48) -> 0
A49: Purchase accounting adjustments-revenue | B49: 0.086 | C49: 0.247 | D49: 0.045 | E49: 0.137 | F49: =SUM(B49:E49) -> 0.515 | G49: 0.02 | H49: 0.042 | I49: 0.029 | J49: 0 | K49: =SUM(G49:J49) -> 0.091 | L49: 0 | M49: 0 | N49: 0 | O49: 0 | P49: =SUM(L49:O49) -> 0 | Q49: 0 | R49: 0 | S49: 0 | T49: 0 | U49: =SUM(Q49:T49) -> 0 | V49: 0 | W49: 0 | X49: 0 | Y49: 0 | Z49: =SUM(V49:Y49) -> 0 | AA49: 0 | AB49: 0 | AC49: 0 | AD49: 0 | AE49: =SUM(AA49:AD49) -> 0 | AF49: 0 | AG49: 0 | AH49: 0 | AI49: 0 | AJ49: =SUM(AF49:AI49) -> 0 | AK49: 0 | AL49: 0 | AM49: 0 | AN49: 0 | AO49: =SUM(AK49:AN49) -> 0
A50: Purchase accounting adjustments-rent | B50: 0.104 | C50: 0.184 | D50: 0.173 | E50: 0.177 | F50: =SUM(B50:E50) -> 0.638 | G50: 0.171 | H50: 0.171 | I50: 0.17 | J50: 0 | K50: =SUM(G50:J50) -> 0.512 | L50: 0 | M50: 0 | N50: 0 | O50: 0 | P50: =SUM(L50:O50) -> 0 | Q50: 0 | R50: 0 | S50: 0 | T50: 0 | U50: =SUM(Q50:T50) -> 0 | V50: 0 | W50: 0 | X50: 0 | Y50: 0 | Z50: =SUM(V50:Y50) -> 0 | AA50: 0 | AB50: 0 | AC50: 0 | AD50: 0 | AE50: =SUM(AA50:AD50) -> 0 | AF50: 0 | AG50: 0 | AH50: 0 | AI50: 0 | AJ50: =SUM(AF50:AI50) -> 0 | AK50: 0 | AL50: 0 | AM50: 0 | AN50: 0 | AO50: =SUM(AK50:AN50) -> 0
A51: Management fees | B51: 0 | C51: 0 | D51: 0 | E51: 0 | F51: =SUM(B51:E51) -> 0 | G51: 0 | H51: 0 | I51: 0 | J51: 0 | K51: =SUM(G51:J51) -> 0 | L51: 0 | M51: 0 | N51: 0 | O51: 0 | P51: =SUM(L51:O51) -> 0 | Q51: 0 | R51: 0 | S51: 0 | T51: 0 | U51: =SUM(Q51:T51) -> 0 | V51: 0 | W51: 0 | X51: 0 | Y51: 0 | Z51: =SUM(V51:Y51) -> 0 | AA51: 0 | AB51: 0 | AC51: 0 | AD51: 0 | AE51: =SUM(AA51:AD51) -> 0 | AF51: 0 | AG51: 0 | AH51: 0 | AI51: 0 | AJ51: =SUM(AF51:AI51) -> 0 | AK51: 0 | AL51: 0 | AM51: 0 | AN51: 0 | AO51: =SUM(AK51:AN51) -> 0
A52: IT system upgrade costs | B52: 0 | C52: 0 | D52: 0 | E52: 0 | F52: =SUM(B52:E52) -> 0 | G52: 0 | H52: 0 | I52: 0 | J52: 0 | K52: =SUM(G52:J52) -> 0 | L52: 0 | M52: 0 | N52: 0 | O52: 0 | P52: =SUM(L52:O52) -> 0 | Q52: 0 | R52: 0 | S52: 0 | T52: 0 | U52: =SUM(Q52:T52) -> 0 | V52: 0 | W52: 0 | X52: 0 | Y52: 0 | Z52: =SUM(V52:Y52) -> 0 | AA52: 0 | AB52: 0 | AC52: 0 | AD52: 0 | AE52: =SUM(AA52:AD52) -> 0 | AF52: 0 | AG52: 0 | AH52: 0 | AI52: 0 | AJ52: =SUM(AF52:AI52) -> 0 | AK52: 0 | AL52: 0 | AM52: 0 | AN52: 0 | AO52: =SUM(AK52:AN52) -> 0
A53: IPO-related compensation expense | B53: 0 | C53: 0 | D53: 0 | E53: 0 | F53: =SUM(B53:E53) -> 0 | G53: 0 | H53: 0 | I53: 0 | J53: 0 | K53: =SUM(G53:J53) -> 0 | L53: 0 | M53: 0 | N53: 0 | O53: 0 | P53: =SUM(L53:O53) -> 0 | Q53: 0 | R53: 0 | S53: 0 | T53: 0 | U53: =SUM(Q53:T53) -> 0 | V53: 0 | W53: 0 | X53: 0 | Y53: 0 | Z53: =SUM(V53:Y53) -> 0 | AA53: 0 | AB53: 0 | AC53: 0 | AD53: 0 | AE53: =SUM(AA53:AD53) -> 0 | AF53: 0 | AG53: 0 | AH53: 0 | AI53: 0 | AJ53: =SUM(AF53:AI53) -> 0 | AK53: 0 | AL53: 0 | AM53: 0 | AN53: 0 | AO53: =SUM(AK53:AN53) -> 0
A54: Loss on reacquired franchise rights | B54: 0 | C54: 0.11 | D54: 0 | E54: 0 | F54: =SUM(B54:E54) -> 0.11 | G54: 0 | H54: 0 | I54: 0 | J54: 0 | K54: =SUM(G54:J54) -> 0 | L54: 0 | M54: 0 | N54: 0 | O54: 0 | P54: =SUM(L54:O54) -> 0 | Q54: 0 | R54: 0 | S54: 0 | T54: 0 | U54: =SUM(Q54:T54) -> 0 | V54: 0 | W54: 0 | X54: 0 | Y54: 0 | Z54: =SUM(V54:Y54) -> 0 | AA54: 0 | AB54: 0 | AC54: 0 | AD54: 0 | AE54: =SUM(AA54:AD54) -> 0 | AF54: 0 | AG54: 0 | AH54: 0 | AI54: 0 | AJ54: =SUM(AF54:AI54) -> 0 | AK54: 0 | AL54: 0 | AM54: 0 | AN54: 0 | AO54: =SUM(AK54:AN54) -> 0
A55: Gain on settlement of preexisting contract with acquiree | B55: 0 | C55: 0 | D55: 0 | E55: 0 | F55: =SUM(B55:E55) -> 0 | G55: 0 | H55: 0 | I55: 0 | J55: 0 | K55: =SUM(G55:J55) -> 0 | L55: 0 | M55: 0 | N55: 0 | O55: 0 | P55: =SUM(L55:O55) -> 0 | Q55: 0 | R55: 0 | S55: 0 | T55: 0 | U55: =SUM(Q55:T55) -> 0 | V55: 0 | W55: 0 | X55: 0 | Y55: 0 | Z55: =SUM(V55:Y55) -> 0 | AA55: 0 | AB55: 0 | AC55: 0 | AD55: 0 | AE55: =SUM(AA55:AD55) -> 0 | AF55: 0 | AG55: 0 | AH55: 0 | AI55: 0 | AJ55: =SUM(AF55:AI55) -> 0 | AK55: 0 | AL55: 0 | AM55: 0 | AN55: 0 | AO55: =SUM(AK55:AN55) -> 0
A56: Transaction fees and acquisition-related costs | B56: 0.394 | C56: 0 | D56: 0 | E56: 0 | F56: =SUM(B56:E56) -> 0.394 | G56: 0 | H56: 0 | I56: 0 | J56: 0 | K56: =SUM(G56:J56) -> 0 | L56: 0 | M56: 0 | N56: 0 | O56: 0 | P56: =SUM(L56:O56) -> 0 | Q56: 0 | R56: 0 | S56: 0 | T56: 0 | U56: =SUM(Q56:T56) -> 0 | V56: 0 | W56: 0 | X56: 0 | Y56: 0 | Z56: =SUM(V56:Y56) -> 0 | AA56: 0 | AB56: 0 | AC56: 0 | AD56: 0 | AE56: =SUM(AA56:AD56) -> 0 | AF56: 0 | AG56: 0 | AH56: 0 | AI56: 0 | AJ56: =SUM(AF56:AI56) -> 0 | AK56: 0 | AL56: 0 | AM56: 0 | AN56: 0 | AO56: =SUM(AK56:AN56) -> 0
A57: Stock offering-related costs | B57: 0 | C57: 0 | D57: 0 | E57: 0 | F57: =SUM(B57:E57) -> 0 | G57: 0 | H57: 0 | I57: 0 | J57: 0 | K57: =SUM(G57:J57) -> 0 | L57: 0 | M57: 0 | N57: 0 | O57: 0 | P57: =SUM(L57:O57) -> 0 | Q57: 0 | R57: 0 | S57: 0 | T57: 0 | U57: =SUM(Q57:T57) -> 0 | V57: 0 | W57: 0 | X57: 0 | Y57: 0 | Z57: =SUM(V57:Y57) -> 0 | AA57: 0 | AB57: 0 | AC57: 0 | AD57: 0 | AE57: =SUM(AA57:AD57) -> 0 | AF57: 0 | AG57: 0 | AH57: 0 | AI57: 0 | AJ57: =SUM(AF57:AI57) -> 0 | AK57: 0 | AL57: 0 | AM57: 0 | AN57: 0 | AO57: =SUM(AK57:AN57) -> 0
A58: Severance costs | B58: 0 | C58: 1.22 | D58: 0 | E58: 0 | F58: =SUM(B58:E58) -> 1.22 | G58: 1.602 | H58: 0 | I58: 0 | J58: 0 | K58: =SUM(G58:J58) -> 1.602 | L58: 0.597 | M58: 0.052 | N58: 0 | O58: 0 | P58: =SUM(L58:O58) -> 0.649 | Q58: 0 | R58: 0 | S58: 0 | T58: 0 | U58: =SUM(Q58:T58) -> 0 | V58: 0 | W58: 0 | X58: 0 | Y58: 0 | Z58: =SUM(V58:Y58) -> 0 | AA58: 0 | AB58: 0 | AC58: 0 | AD58: 0 | AE58: =SUM(AA58:AD58) -> 0 | AF58: 0 | AG58: 0 | AH58: 0 | AI58: 0 | AJ58: =SUM(AF58:AI58) -> 0 | AK58: 0 | AL58: 0 | AM58: 0 | AN58: 0 | AO58: =SUM(AK58:AN58) -> 0
A59: Executive transition costs | B59: 0 | C59: 0 | D59: 2.502 | E59: 1.226 | F59: =SUM(B59:E59) -> 3.728 | G59: 0.283 | H59: 1.348 | I59: 1.342 | J59: 1.227 | K59: =SUM(G59:J59) -> 4.2 | L59: 1.041 | M59: 1.406 | N59: 0.408 | O59: 0 | P59: =SUM(L59:O59) -> 2.855 | Q59: 0 | R59: 0 | S59: 0 | T59: 0 | U59: =SUM(Q59:T59) -> 0 | V59: 0 | W59: 0 | X59: 0 | Y59: 0 | Z59: =SUM(V59:Y59) -> 0 | AA59: 0 | AB59: 0 | AC59: 0 | AD59: 0 | AE59: =SUM(AA59:AD59) -> 0 | AF59: 0 | AG59: 0 | AH59: 0 | AI59: 0 | AJ59: =SUM(AF59:AI59) -> 0 | AK59: 0 | AL59: 0 | AM59: 0 | AN59: 0 | AO59: =SUM(AK59:AN59) -> 0
A60: Legal matters | B60: 3.3 | C60: 2.95 | D60: 0 | E60: 0 | F60: =SUM(B60:E60) -> 6.25 | G60: 0 | H60: 0 | I60: 0 | J60: 0 | K60: =SUM(G60:J60) -> 0 | L60: 0 | M60: 0 | N60: 0 | O60: 0 | P60: =SUM(L60:O60) -> 0 | Q60: 0 | R60: 0 | S60: 0 | T60: 0 | U60: =SUM(Q60:T60) -> 0 | V60: 0 | W60: 0 | X60: 0 | Y60: 0 | Z60: =SUM(V60:Y60) -> 0 | AA60: 0 | AB60: 0 | AC60: 0 | AD60: 0 | AE60: =SUM(AA60:AD60) -> 0 | AF60: 0 | AG60: 0 | AH60: 0 | AI60: 0 | AJ60: =SUM(AF60:AI60) -> 0 | AK60: 0 | AL60: 0 | AM60: 0 | AN60: 0 | AO60: =SUM(AK60:AN60) -> 0
... A71: Other | B71: -1.459 | C71: 0.818 | D71: 0.05 | E71: 0.176 | F71: =SUM(B71:E71) -> -0.415 | G71: -0.228 | H71: 0.121 | I71: 0.032 | J71: 0.211 | K71: =SUM(G71:J71) -> 0.136 | L71: 0.155 | M71: 0.176 | N71: 0.212 | O71: 0 | P71: =SUM(L71:O71) -> 0.543 | Q71: 0 | R71: 0 | S71: 0 | T71: 0 | U71: =SUM(Q71:T71) -> 0 | V71: 0 | W71: 0 | X71: 0 | Y71: 0 | Z71: =SUM(V71:Y71) -> 0 | AA71: 0 | AB71: 0 | AC71: 0 | AD71: 0 | AE71: =SUM(AA71:AD71) -> 0 | AF71: 0 | AG71: 0 | AH71: 0 | AI71: 0 | AJ71: =SUM(AF71:AI71) -> 0 | AK71: 0 | AL71: 0 | AM71: 0 | AN71: 0 | AO71: =SUM(AK71:AN71) -> 0
A72: Adjusted EBITDA | B72: =B47+B48 -> 73.407 | C72: =C47+C48 -> 100.943 | D72: =D47+D48 -> 94.314 | E72: =E47+E48 -> 96.7 | F72: =F47+F48 -> 435.376 | G72: =G47+G48 -> 106.311 | H72: =H47+H48 -> 127.503 | I72: =I47+I48 -> 123.071 | ... AO72: =AO47+AO48 -> 916.50313
A73: YoY % Change | B73: =IFERROR(B72/#REF!-1,"na") -> na | C73: =IFERROR(C72/#REF!-1,"na") -> na | D73: =IFERROR(D72/#REF!-1,"na") -> na | E73: =IFERROR(E72/#REF!-1,"na") -> na | F73: =IFERROR(F72/#REF!-1,"na") -> na | G73: =IFERROR(G72/B72-1,"na") -> 0.44824063 | H73: =IFERROR(H72/C72-1,"na") -> 0.26311879 | I73: =IFERROR(I72/D72-1,"na") -> 0.30490701 | J73: =IFERROR(J72/E72-1,"na") -> 0.35289555 | K73: =IFERROR(K72/F72-1,"na") -> 0.12020415 | L73: =IFERROR(L72/G72-1,"na") -> 0.10059166 | M73: =IFERROR(M72/H72-1,"na") -> 0.15769041 | N73: =IFERROR(N72/I72-1,"na") -> 0.14377879 | ... AO73: =IFERROR(AO72/AJ72-1,"na") -> 0.073816121
A74: % Margin | F74: =IFERROR(F72/F11,"na") -> 0.40639022 | K74: =IFERROR(K72/K11,"na") -> 0.41273503 | L74: =IFERROR(L72/L11,"na") -> 0.42291677 | M74: =IFERROR(M72/M11,"na") -> 0.43302462 | N74: =IFERROR(N72/N11,"na") -> 0.42611815 | O74: =IFERROR(O72/O11,"na") -> 0.39715774 | P74: =IFERROR(P72/P11,"na") -> 0.41925048 | Q74: =IFERROR(Q72/Q11,"na") -> 0.42849178 | R74: =IFERROR(R72/R11,"na") -> 0.43563236 | ... U74: =IFERROR(U72/U11,"na") -> 0.42468001 | Z74: =IFERROR(Z72/Z11,"na") -> 0.43292197 | AE74: =IFERROR(AE72/AE11,"na") -> 0.43555182 | AJ74: =IFERROR(AJ72/AJ11,"na") -> 0.43729167 | AO74: =IFERROR(AO72/AO11,"na") -> 0.43851267
A75: Net Income (GAAP) | B75: =B30 -> 7.965 | C75: =C30 -> 26.184 | D75: =D30 -> 23.746 | E75: =E30 -> 19.129 | F75: =F30 -> 147.036 | G75: =G30 -> 34.973 | H75: =H30 -> 49.312 | I75: =I30 -> 42.395 | J75: =J30 -> 47.563 | K75: =SUM(G75:J75) -> 174.243 | L75: =L30 -> 42.079 | M75: =M30 -> 58.295 | N75: =N30 -> 59.183 | O75: =O30 -> 58.51335 | P75: =SUM(L75:O75) -> 218.07035 | Q75: =Q30 -> 56.446571 | R75: =R30 -> 80.584008 | S75: =S30 -> 76.110612 | T75: =T30 -> 77.236479 | U75: =SUM(Q75:T75) -> 290.37767 | V75: =V30 -> 70.82519 | W75: =W30 -> 96.15067 | X75: =X30 -> 93.277081 | Y75: =Y30 -> 92.761618 | Z75: =SUM(V75:Y75) -> 353.01456 | AA75: =AA30 -> 83.954829 | AB75: =AB30 -> 110.42389 | AC75: =AC30 -> 107.12514 | AD75: =AD30 -> 105.92235 | AE75: =SUM(AA75:AD75) -> 407.42621 | AF75: =AF30 -> 103.70999 | AG75: =AG30 -> 124.81539 | AH75: =AH30 -> 116.72449 | AI75: =AI30 -> 116.16438 | AJ75: =SUM(AF75:AI75) -> 461.41424 | AK75: =AK30 -> 115.16717 | AL75: =AL30 -> 136.63771 | AM75: =AM30 -> 127.93418 | AN75: =AN30 -> 126.79505 | AO75: =SUM(AK75:AN75) -> 506.53412
A76: Provision for income taxes | B76: =B28 -> 9.567 | C76: =C28 -> 15.814 | D76: =D28 -> 13.474 | E76: =E28 -> 19.657 | F76: =F28 -> 58.512 | G76: =G28 -> 14.324 | H76: =H28 -> 18.977 | I76: =I28 -> 16.523 | J76: =J28 -> 18.619 | K76: =SUM(G76:J76) -> 68.443 | L76: =L28 -> 16.216 | M76: =M28 -> 24.93 | N76: =N28 -> 27.974 | O76: =O28 -> 22.417978 | P76: =SUM(L76:O76) -> 91.537978 | Q76: =Q28 -> 22.060482 | R76: =R28 -> 31.493889 | S76: =S28 -> 29.745594 | T76: =T28 -> 30.185606 | U76: =SUM(Q76:T76) -> 113.48557 | V76: =V28 -> 27.679942 | W76: =W28 -> 37.577661 | X76: =X28 -> 36.454603 | Y76: =Y28 -> 36.25315 | Z76: =SUM(V76:Y76) -> 137.96536 | AA76: =AA28 -> 32.811275 | AB76: =AB28 -> 43.155928 | AC76: =AC28 -> 41.86671 | AD76: =AD28 -> 41.396635 | AE76: =SUM(AA76:AD76) -> 159.23055 | AF76: =AF28 -> 40.531998 | AG76: =AG28 -> 48.780423 | AH76: =AH28 -> 45.618332 | AI76: =AI28 -> 45.39943 | AJ76: =SUM(AF76:AI76) -> 180.33018 | AK76: =AK28 -> 45.009701 | AL76: =AL28 -> 53.400831 | AM76: =AM28 -> 49.99931 | AN76: =AN28 -> 49.554117 | AO76: =SUM(AK76:AN76) -> 197.96396
A77: Adjustments | B77: =SUM(B78:B102) -> 14.774 | C77: =SUM(C78:C102) -> 17.827 | D77: =SUM(D78:D102) -> 15.112 | E77: =SUM(E78:E102) -> 15.307 | F77: =SUM(F78:F102) -> 63.02 | G77: =SUM(G78:G102) -> 14.419 | H77: =SUM(H78:H102) -> 15.523 | I77: =SUM(I78:I102) -> 14.884 | J77: =SUM(J78:J102) -> 14.405 | K77: =SUM(G77:J77) -> 59.231 | L77: =SUM(L78:L102) -> 9.222 | M77: =SUM(M78:M102) -> 14.642 | N77: =SUM(N78:N102) -> 3.273 | O77: =SUM(O78:O102) -> 10.918 | P77: =SUM(L77:O77) -> 38.055 | Q77: =SUM(Q78:Q102) -> 9.178 | R77: =SUM(R78:R102) -> 9.178 | S77: =SUM(S78:S102) -> 9.178 | T77: =SUM(T78:T102) -> 10.918 | U77: =SUM(Q77:T77) -> 38.452 | V77: =SUM(V78:V102) -> 10 | W77: =SUM(W78:W102) -> 11 | X77: =SUM(X78:X102) -> 10 | Y77: =SUM(Y78:Y102) -> 10.918 | Z77: =SUM(V77:Y77) -> 41.918 | AA77: =SUM(AA78:AA102) -> 10 | AB77: =SUM(AB78:AB102) -> 11 | AC77: =SUM(AC78:AC102) -> 10 | AD77: =SUM(AD78:AD102) -> 10.918 | AE77: =SUM(AA77:AD77) -> 41.918 | AF77: =SUM(AF78:AF102) -> 10 | AG77: =SUM(AG78:AG102) -> 11 | AH77: =SUM(AH78:AH102) -> 10 | AI77: =SUM(AI78:AI102) -> 10.918 | AJ77: =SUM(AF77:AI77) -> 41.918 | AK77: =SUM(AK78:AK102) -> 10 | AL77: =SUM(AL78:AL102) -> 11 | AM77: =SUM(AM78:AM102) -> 10 | AN77: =SUM(AN78:AN102) -> 10.918 | AO77: =SUM(AK77:AN77) -> 41.918
A78: Purchase accounting adjustments-revenue | B78: =B49 -> 0.086 | C78: =C49 -> 0.247 | D78: =D49 -> 0.045 | E78: =E49 -> 0.137 | F78: =SUM(B78:E78) -> 0.515 | G78: =G49 -> 0.02 | H78: =H49 -> 0.042 | I78: =I49 -> 0.029 | J78: =J49 -> 0 | K78: =SUM(G78:J78) -> 0.091 | L78: =L49 -> 0 | M78: =M49 -> 0 | N78: =N49 -> 0 | O78: =O49 -> 0 | P78: =SUM(L78:O78) -> 0 | Q78: =Q49 -> 0 | R78: =R49 -> 0 | S78: =S49 -> 0 | T78: =T49 -> 0 | U78: =SUM(Q78:T78) -> 0 | V78: =V49 -> 0 | W78: =W49 -> 0 | X78: =X49 -> 0 | Y78: =Y49 -> 0 | Z78: =SUM(V78:Y78) -> 0 | AA78: =AA49 -> 0 | AB78: =AB49 -> 0 | AC78: =AC49 -> 0 | AD78: =AD49 -> 0 | AE78: =SUM(AA78:AD78) -> 0 | AF78: =AF49 -> 0 | AG78: =AG49 -> 0 | AH78: =AH49 -> 0 | AI78: =AI49 -> 0 | AJ78: =SUM(AF78:AI78) -> 0 | AK78: =AK49 -> 0 | AL78: =AL49 -> 0 | AM78: =AM49 -> 0 | AN78: =AN49 -> 0 | AO78: =SUM(AK78:AN78) -> 0
A79: Purchase accounting adjustments-rent | B79: =B50 -> 0.104 | C79: =C50 -> 0.184 | D79: =D50 -> 0.173 | E79: =E50 -> 0.177 | F79: =SUM(B79:E79) -> 0.638 | G79: =G50 -> 0.171 | H79: =H50 -> 0.171 | I79: =I50 -> 0.17 | J79: =J50 -> 0 | K79: =SUM(G79:J79) -> 0.512 | L79: =L50 -> 0 | M79: =M50 -> 0 | N79: =N50 -> 0 | O79: =O50 -> 0 | P79: =SUM(L79:O79) -> 0 | Q79: =Q50 -> 0 | R79: =R50 -> 0 | S79: =S50 -> 0 | T79: =T50 -> 0 | U79: =SUM(Q79:T79) -> 0 | V79: =V50 -> 0 | W79: =W50 -> 0 | X79: =X50 -> 0 | Y79: =Y50 -> 0 | Z79: =SUM(V79:Y79) -> 0 | AA79: =AA50 -> 0 | AB79: =AB50 -> 0 | AC79: =AC50 -> 0 | AD79: =AD50 -> 0 | AE79: =SUM(AA79:AD79) -> 0 | AF79: =AF50 -> 0 | AG79: =AG50 -> 0 | AH79: =AH50 -> 0 | AI79: =AI50 -> 0 | AJ79: =SUM(AF79:AI79) -> 0 | AK79: =AK50 -> 0 | AL79: =AL50 -> 0 | AM79: =AM50 -> 0 | AN79: =AN50 -> 0 | AO79: =SUM(AK79:AN79) -> 0
A80: Loss on reacquired franchise rights | B80: =B54 -> 0 | C80: =C54 -> 0.11 | D80: =D54 -> 0 | E80: =E54 -> 0 | F80: =SUM(B80:E80) -> 0.11 | G80: =G54 -> 0 | H80: =H54 -> 0 | I80: =I54 -> 0 | J80: =J54 -> 0 | K80: =SUM(G80:J80) -> 0 | L80: =L54 -> 0 | M80: =M54 -> 0 | N80: =N54 -> 0 | O80: =O54 -> 0 | P80: =SUM(L80:O80) -> 0 | Q80: =Q54 -> 0 | R80: =R54 -> 0 | S80: =S54 -> 0 | T80: =T54 -> 0 | U80: =SUM(Q80:T80) -> 0 | V80: =V54 -> 0 | W80: =W54 -> 0 | X80: =X54 -> 0 | Y80: =Y54 -> 0 | Z80: =SUM(V80:Y80) -> 0 | AA80: =AA54 -> 0 | AB80: =AB54 -> 0 | AC80: =AC54 -> 0 | AD80: =AD54 -> 0 | AE80: =SUM(AA80:AD80) -> 0 | AF80: =AF54 -> 0 | AG80: =AG54 -> 0 | AH80: =AH54 -> 0 | AI80: =AI54 -> 0 | AJ80: =SUM(AF80:AI80) -> 0 | AK80: =AK54 -> 0 | AL80: =AL54 -> 0 | AM80: =AM54 -> 0 | AN80: =AN54 -> 0 | AO80: =SUM(AK80:AN80) -> 0
A81: Gain on settlement of preexisting contract with acquiree | B81: =B55 -> 0 | C81: =C55 -> 0 | D81: =D55 -> 0 | E81: =E55 -> 0 | F81: =SUM(B81:E81) -> 0 | G81: =G55 -> 0 | H81: =H55 -> 0 | I81: =I55 -> 0 | J81: =J55 -> 0 | K81: =SUM(G81:J81) -> 0 | L81: =L55 -> 0 | M81: =M55 -> 0 | N81: =N55 -> 0 | O81: =O55 -> 0 | P81: =SUM(L81:O81) -> 0 | Q81: =Q55 -> 0 | R81: =R55 -> 0 | S81: =S55 -> 0 | T81: =T55 -> 0 | U81: =SUM(Q81:T81) -> 0 | V81: =V55 -> 0 | W81: =W55 -> 0 | X81: =X55 -> 0 | Y81: =Y55 -> 0 | Z81: =SUM(V81:Y81) -> 0 | AA81: =AA55 -> 0 | AB81: =AB55 -> 0 | AC81: =AC55 -> 0 | AD81: =AD55 -> 0 | AE81: =SUM(AA81:AD81) -> 0 | AF81: =AF55 -> 0 | AG81: =AG55 -> 0 | AH81: =AH55 -> 0 | AI81: =AI55 -> 0 | AJ81: =SUM(AF81:AI81) -> 0 | AK81: =AK55 -> 0 | AL81: =AL55 -> 0 | AM81: =AM55 -> 0 | AN81: =AN55 -> 0 | AO81: =SUM(AK81:AN81) -> 0
A82: Transaction fees and acquisition-related costs | B82: =B56 -> 0.394 | C82: =C56 -> 0 | D82: =D56 -> 0 | E82: =E56 -> 0 | F82: =SUM(B82:E82) -> 0.394 | G82: =G56 -> 0 | H82: =H56 -> 0 | I82: =I56 -> 0 | J82: =J56 -> 0 | K82: =SUM(G82:J82) -> 0 | L82: =L56 -> 0 | M82: =M56 -> 0 | N82: =N56 -> 0 | O82: =O56 -> 0 | P82: =SUM(L82:O82) -> 0 | Q82: =Q56 -> 0 | R82: =R56 -> 0 | S82: =S56 -> 0 | T82: =T56 -> 0 | U82: =SUM(Q82:T82) -> 0 | V82: =V56 -> 0 | W82: =W56 -> 0 | X82: =X56 -> 0 | Y82: =Y56 -> 0 | Z82: =SUM(V82:Y82) -> 0 | AA82: =AA56 -> 0 | AB82: =AB56 -> 0 | AC82: =AC56 -> 0 | AD82: =AD56 -> 0 | AE82: =SUM(AA82:AD82) -> 0 | AF82: =AF56 -> 0 | AG82: =AG56 -> 0 | AH82: =AH56 -> 0 | AI82: =AI56 -> 0 | AJ82: =SUM(AF82:AI82) -> 0 | AK82: =AK56 -> 0 | AL82: =AL56 -> 0 | AM82: =AM56 -> 0 | AN82: =AN56 -> 0 | AO82: =SUM(AK82:AN82) -> 0
A83: Severance costs | B83: =B58 -> 0 | C83: =C58 -> 1.22 | D83: =D58 -> 0 | E83: =E58 -> 0 | F83: =SUM(B83:E83) -> 1.22 | G83: =G58 -> 1.602 | H83: =H58 -> 0 | I83: =I58 -> 0 | J83: =J58 -> 0 | K83: =SUM(G83:J83) -> 1.602 | L83: =L58 -> 0.597 | M83: =M58 -> 0.052 | N83: =N58 -> 0 | O83: =O58 -> 0 | P83: =SUM(L83:O83) -> 0.649 | Q83: =Q58 -> 0 | R83: =R58 -> 0 | S83: =S58 -> 0 | T83: =T58 -> 0 | U83: =SUM(Q83:T83) -> 0 | V83: =V58 -> 0 | W83: =W58 -> 0 | X83: =X58 -> 0 | Y83: =Y58 -> 0 | Z83: =SUM(V83:Y83) -> 0 | AA83: =AA58 -> 0 | AB83: =AB58 -> 0 | AC83: =AC58 -> 0 | AD83: =AD58 -> 0 | AE83: =SUM(AA83:AD83) -> 0 | AF83: =AF58 -> 0 | AG83: =AG58 -> 0 | AH83: =AH58 -> 0 | AI83: =AI58 -> 0 | AJ83: =SUM(AF83:AI83) -> 0 | AK83: =AK58 -> 0 | AL83: =AL58 -> 0 | AM83: =AM58 -> 0 | AN83: =AN58 -> 0 | AO83: =SUM(AK83:AN83) -> 0
A84: Executive transition costs | B84: =B59 -> 0 | C84: =C59 -> 0 | D84: =D59 -> 2.502 | E84: =E59 -> 1.226 | F84: =SUM(B84:E84) -> 3.728 | G84: =G59 -> 0.283 | H84: =H59 -> 1.348 | I84: =I59 -> 1.342 | J84: =J59 -> 1.227 | K84: =SUM(G84:J84) -> 4.2 | L84: =L59 -> 1.041 | M84: =M59 -> 1.406 | N84: =N59 -> 0.408 | O84: =O59 -> 0 | P84: =SUM(L84:O84) -> 2.855 | Q84: =Q59 -> 0 | R84: =R59 -> 0 | S84: =S59 -> 0 | T84: =T59 -> 0 | U84: =SUM(Q84:T84) -> 0 | V84: =V59 -> 0 | W84: =W59 -> 0 | X84: =X59 -> 0 | Y84: =Y59 -> 0 | Z84: =SUM(V84:Y84) -> 0 | AA84: =AA59 -> 0 | AB84: =AB59 -> 0 | AC84: =AC59 -> 0 | AD84: =AD59 -> 0 | AE84: =SUM(AA84:AD84) -> 0 | AF84: =AF59 -> 0 | AG84: =AG59 -> 0 | AH84: =AH59 -> 0 | AI84: =AI59 -> 0 | AJ84: =SUM(AF84:AI84) -> 0 | AK84: =AK59 -> 0 | AL84: =AL59 -> 0 | AM84: =AM59 -> 0 | AN84: =AN59 -> 0 | AO84: =SUM(AK84:AN84) -> 0
A85: Pre-opening costs | B85: =B63 -> 0 | C85: =C63 -> 0 | D85: =D63 -> 0 | E85: =E63 -> 0 | F85: =SUM(B85:E85) -> 0 | G85: =G63 -> 0 | H85: =H63 -> 0 | I85: =I63 -> 0 | J85: =J63 -> 0 | K85: =SUM(G85:J85) -> 0 | L85: =L63 -> 0 | M85: =M63 -> 0 | N85: =N63 -> 0 | O85: =O63 -> 0 | P85: =SUM(L85:O85) -> 0 | Q85: =Q63 -> 0 | R85: =R63 -> 0 | S85: =S63 -> 0 | T85: =T63 -> 0 | U85: =SUM(Q85:T85) -> 0 | V85: =V63 -> 0 | W85: =W63 -> 0 | X85: =X63 -> 0 | Y85: =Y63 -> 0 | Z85: =SUM(V85:Y85) -> 0 | AA85: =AA63 -> 0 | AB85: =AB63 -> 0 | AC85: =AC63 -> 0 | AD85: =AD63 -> 0 | AE85: =SUM(AA85:AD85) -> 0 | AF85: =AF63 -> 0 | AG85: =AG63 -> 0 | AH85: =AH63 -> 0 | AI85: =AI63 -> 0 | AJ85: =SUM(AF85:AI85) -> 0 | AK85: =AK63 -> 0 | AL85: =AL63 -> 0 | AM85: =AM63 -> 0 | AN85: =AN63 -> 0 | AO85: =SUM(AK85:AN85) -> 0
A86: Stock offering-related costs | B86: =B57 -> 0 | C86: =C57 -> 0 | D86: =D57 -> 0 | E86: =E57 -> 0 | F86: =SUM(B86:E86) -> 0 | G86: =G57 -> 0 | H86: =H57 -> 0 | I86: =I57 -> 0 | J86: =J57 -> 0 | K86: =SUM(G86:J86) -> 0 | L86: =L57 -> 0 | M86: =M57 -> 0 | N86: =N57 -> 0 | O86: =O57 -> 0 | P86: =SUM(L86:O86) -> 0 | Q86: =Q57 -> 0 | R86: =R57 -> 0 | S86: =S57 -> 0 | T86: =T57 -> 0 | U86: =SUM(Q86:T86) -> 0 | V86: =V57 -> 0 | W86: =W57 -> 0 | X86: =X57 -> 0 | Y86: =Y57 -> 0 | Z86: =SUM(V86:Y86) -> 0 | AA86: =AA57 -> 0 | AB86: =AB57 -> 0 | AC86: =AC57 -> 0 | AD86: =AD57 -> 0 | AE86: =SUM(AA86:AD86) -> 0 | AF86: =AF57 -> 0 | AG86: =AG57 -> 0 | AH86: =AH57 -> 0 | AI86: =AI57 -> 0 | AJ86: =SUM(AF86:AI86) -> 0 | AK86: =AK57 -> 0 | AL86: =AL57 -> 0 | AM86: =AM57 -> 0 | AN86: =AN57 -> 0 | AO86: =SUM(AK86:AN86) -> 0
A87: Equipment discount | B87: =B64 -> 0 | C87: =C64 -> 0 | D87: =D64 -> 0 | E87: =E64 -> 0 | F87: =SUM(B87:E87) -> 0 | G87: =G64 -> 0 | H87: =H64 -> 0 | I87: =I64 -> 0 | J87: =J64 -> 0 | K87: =SUM(G87:J87) -> 0 | L87: =L64 -> 0 | M87: =M64 -> 0 | N87: =N64 -> 0 | O87: =O64 -> 0 | P87: =SUM(L87:O87) -> 0 | Q87: =Q64 -> 0 | R87: =R64 -> 0 | S87: =S64 -> 0 | T87: =T64 -> 0 | U87: =SUM(Q87:T87) -> 0 | V87: =V64 -> 0 | W87: =W64 -> 0 | X87: =X64 -> 0 | Y87: =Y64 -> 0 | Z87: =SUM(V87:Y87) -> 0 | AA87: =AA64 -> 0 | AB87: =AB64 -> 0 | AC87: =AC64 -> 0 | AD87: =AD64 -> 0 | AE87: =SUM(AA87:AD87) -> 0 | AF87: =AF64 -> 0 | AG87: =AG64 -> 0 | AH87: =AH64 -> 0 | AI87: =AI64 -> 0 | AJ87: =SUM(AF87:AI87) -> 0 | AK87: =AK64 -> 0 | AL87: =AL64 -> 0 | AM87: =AM64 -> 0 | AN87: =AN64 -> 0 | AO87: =SUM(AK87:AN87) -> 0
A88: Insurance recovery | B88: =B67 -> 0 | C88: =C67 -> 0 | D88: =D67 -> 0 | E88: =E67 -> 0 | F88: =SUM(B88:E88) -> 0 | G88: =G67 -> 0 | H88: =H67 -> 0 | I88: =I67 -> 0 | J88: =J67 -> 0 | K88: =SUM(G88:J88) -> 0 | L88: =L67 -> -1.636 | M88: =M67 -> 0 | N88: =N67 -> 0 | O88: =O67 -> 0 | P88: =SUM(L88:O88) -> -1.636 | Q88: =Q67 -> 0 | R88: =R67 -> 0 | S88: =S67 -> 0 | T88: =T67 -> 0 | U88: =SUM(Q88:T88) -> 0 | V88: =V67 -> 0 | W88: =W67 -> 0 | X88: =X67 -> 0 | Y88: =Y67 -> 0 | Z88: =SUM(V88:Y88) -> 0 | AA88: =AA67 -> 0 | AB88: =AB67 -> 0 | AC88: =AC67 -> 0 | AD88: =AD67 -> 0 | AE88: =SUM(AA88:AD88) -> 0 | AF88: =AF67 -> 0 | AG88: =AG67 -> 0 | AH88: =AH67 -> 0 | AI88: =AI67 -> 0 | AJ88: =SUM(AF88:AI88) -> 0 | AK88: =AK67 -> 0 | AL88: =AL67 -> 0 | AM88: =AM67 -> 0 | AN88: =AN67 -> 0 | AO88: =SUM(AK88:AN88) -> 0
A89: Legal matters | B89: =B60 -> 3.3 | C89: =C60 -> 2.95 | D89: =D60 -> 0 | E89: =E60 -> 0 | F89: =SUM(B89:E89) -> 6.25 | G89: =G60 -> 0 | H89: =H60 -> 0 | I89: =I60 -> 0 | J89: =J60 -> 0 | K89: =SUM(G89:J89) -> 0 | L89: =L60 -> 0 | M89: =M60 -> 0 | N89: =N60 -> 0 | O89: =O60 -> 0 | P89: =SUM(L89:O89) -> 0 | Q89: =Q60 -> 0 | R89: =R60 -> 0 | S89: =S60 -> 0 | T89: =T60 -> 0 | U89: =SUM(Q89:T89) -> 0 | V89: =V60 -> 0 | W89: =W60 -> 0 | X89: =X60 -> 0 | Y89: =Y60 -> 0 | Z89: =SUM(V89:Y89) -> 0 | AA89: =AA60 -> 0 | AB89: =AB60 -> 0 | AC89: =AC60 -> 0 | AD89: =AD60 -> 0 | AE89: =SUM(AA89:AD89) -> 0 | AF89: =AF60 -> 0 | AG89: =AG60 -> 0 | AH89: =AH60 -> 0 | AI89: =AI60 -> 0 | AJ89: =SUM(AF89:AI89) -> 0 | AK89: =AK60 -> 0 | AL89: =AL60 -> 0 | AM89: =AM60 -> 0 | AN89: =AN60 -> 0 | AO89: =SUM(AK89:AN89) -> 0
A90: Loss (gain) on adjustment of allowance for credit losses on held-to-maturity investment | B90: =B61 -> 0.255 | C90: =C61 -> -0.16 | D90: =D61 -> -0.101 | E90: =E61 -> 2.738 | F90: =SUM(B90:E90) -> 2.732 | G90: =G61 -> 0.475 | H90: =H61 -> 0.082 | I90: =I61 -> 0.292 | J90: =J61 -> 0.297 | K90: =SUM(G90:J90) -> 1.146 | L90: =L61 -> 0.292 | M90: =M61 -> 4.311 | N90: =N61 -> 0.486 | O90: =O61 -> 0 | P90: =SUM(L90:O90) -> 5.089 | Q90: =Q61 -> 0 | R90: =R61 -> 0 | S90: =S61 -> 0 | T90: =T61 -> 0 | U90: =SUM(Q90:T90) -> 0 | V90: =V61 -> 0 | W90: =W61 -> 0 | X90: =X61 -> 0 | Y90: =Y61 -> 0 | Z90: =SUM(V90:Y90) -> 0 | AA90: =AA61 -> 0 | AB90: =AB61 -> 0 | AC90: =AC61 -> 0 | AD90: =AD61 -> 0 | AE90: =SUM(AA90:AD90) -> 0 | AF90: =AF61 -> 0 | AG90: =AG61 -> 0 | AH90: =AH61 -> 0 | AI90: =AI61 -> 0 | AJ90: =SUM(AF90:AI90) -> 0 | AK90: =AK61 -> 0 | AL90: =AL61 -> 0 | AM90: =AM61 -> 0 | AN90: =AN61 -> 0 | AO90: =SUM(AK90:AN90) -> 0
A91: Dividend income on held-to-maturity investment | B91: =B62 -> -0.483 | C91: =C62 -> -0.496 | D91: =D62 -> -0.511 | E91: =E62 -> -0.576 | F91: =SUM(B91:E91) -> -2.066 | G91: =G62 -> -0.528 | H91: =H62 -> -0.537 | I91: =I62 -> -0.553 | J91: =J62 -> -0.562 | K91: =SUM(G91:J91) -> -2.18 | L91: =L62 -> -0.561 | M91: =M62 -> -0.578 | N91: =N62 -> -0.594 | O91: =O62 -> 0 | P91: =SUM(L91:O91) -> -1.733 | Q91: =Q62 -> 0 | R91: =R62 -> 0 | S91: =S62 -> 0 | T91: =T62 -> 0 | U91: =SUM(Q91:T91) -> 0 | V91: =V62 -> 0 | W91: =W62 -> 0 | X91: =X62 -> 0 | Y91: =Y62 -> 0 | Z91: =SUM(V91:Y91) -> 0 | AA91: =AA62 -> 0 | AB91: =AB62 -> 0 | AC91: =AC62 -> 0 | AD91: =AD62 -> 0 | AE91: =SUM(AA91:AD91) -> 0 | AF91: =AF62 -> 0 | AG91: =AG62 -> 0 | AH91: =AH62 -> 0 | AI91: =AI62 -> 0 | AJ91: =SUM(AF91:AI91) -> 0 | AK91: =AK62 -> 0 | AL91: =AL62 -> 0 | AM91: =AM62 -> 0 | AN91: =AN62 -> 0 | AO91: =SUM(AK91:AN91) -> 0
A92: Loss (gain) on remeasurement of tax benefit arrangement | B92: =B68 -> 0 | C92: =C68 -> 0 | D92: =D68 -> 0 | E92: =E68 -> -1.964 | F92: =F68 -> -1.964 | G92: =G68 -> -0.362 | H92: =H68 -> -0.987 | I92: =I68 -> 0.575 | J92: =J68 -> 2.074 | K92: =SUM(G92:J92) -> 1.3 | L92: =L68 -> -0.084 | M92: =M68 -> -1.21 | N92: =N68 -> -0.475 | O92: =O68 -> 0 | P92: =SUM(L92:O92) -> -1.769 | Q92: =Q68 -> 0 | R92: =R68 -> 0 | S92: =S68 -> 0 | T92: =T68 -> 0 | U92: =SUM(Q92:T92) -> 0 | V92: =V68 -> 0 | W92: =W68 -> 0 | X92: =X68 -> 0 | Y92: =Y68 -> 0 | Z92: =SUM(V92:Y92) -> 0 | AA92: =AA68 -> 0 | AB92: =AB68 -> 0 | AC92: =AC68 -> 0 | AD92: =AD68 -> 0 | AE92: =SUM(AA92:AD92) -> 0 | AF92: =AF68 -> 0 | AG92: =AG68 -> 0 | AH92: =AH68 -> 0 | AI92: =AI68 -> 0 | AJ92: =SUM(AF92:AI92) -> 0 | AK92: =AK68 -> 0 | AL92: =AL68 -> 0 | AM92: =AM68 -> 0 | AN92: =AN68 -> 0 | AO92: =SUM(AK92:AN92) -> 0
A93: Amortization of basis difference of equity-method investments | B93: =B70 -> 0 | C93: =C70 -> 0 | D93: =D70 -> 0 | E93: =E70 -> 0.438 | F93: =SUM(B93:E93) -> 0.438 | G93: =G70 -> 0.229 | H93: =H70 -> 0.24 | I93: =I70 -> 0.24 | J93: =J70 -> 0.24 | K93: =SUM(G93:J93) -> 0.949 | L93: =L70 -> 0.24 | M93: =M70 -> 0.24 | N93: =N70 -> 0.24 | O93: =O70 -> 0 | P93: =SUM(L93:O93) -> 0.72 | Q93: =Q70 -> 0 | R93: =R70 -> 0 | S93: =S70 -> 0 | T93: =T70 -> 0 | U93: =SUM(Q93:T93) -> 0 | V93: =V70 -> 0 | W93: =W70 -> 0 | X93: =X70 -> 0 | Y93: =Y70 -> 0 | Z93: =SUM(V93:Y93) -> 0 | AA93: =AA70 -> 0 | AB93: =AB70 -> 0 | AC93: =AC70 -> 0 | AD93: =AD70 -> 0 | AE93: =SUM(AA93:AD93) -> 0 | AF93: =AF70 -> 0 | AG93: =AG70 -> 0 | AH93: =AH70 -> 0 | AI93: =AI70 -> 0 | AJ93: =SUM(AF93:AI93) -> 0 | AK93: =AK70 -> 0 | AL93: =AL70 -> 0 | AM93: =AM70 -> 0 | AN93: =AN70 -> 0 | AO93: =SUM(AK93:AN93) -> 0
A94: Early lease termination costs | B94: =B65 -> 0 | C94: =C65 -> 0 | D94: =D65 -> 0 | E94: =E65 -> 0 | F94: =SUM(B94:E94) -> 0 | G94: =G65 -> 0 | H94: =H65 -> 0 | I94: =I65 -> 0 | J94: =J65 -> 0 | K94: =SUM(G94:J94) -> 0 | L94: =L65 -> 0 | M94: =M65 -> 1.067 | N94: =N65 -> 0.261 | O94: =O65 -> 0 | P94: =SUM(L94:O94) -> 1.328 | Q94: =Q65 -> 0 | R94: =R65 -> 0 | S94: =S65 -> 0 | T94: =T65 -> 0 | U94: =SUM(Q94:T94) -> 0 | V94: =V65 -> 0 | W94: =W65 -> 0 | X94: =X65 -> 0 | Y94: =Y65 -> 0 | Z94: =SUM(V94:Y94) -> 0 | AA94: =AA65 -> 0 | AB94: =AB65 -> 0 | AC94: =AC65 -> 0 | AD94: =AD65 -> 0 | AE94: =SUM(AA94:AD94) -> 0 | AF94: =AF65 -> 0 | AG94: =AG65 -> 0 | AH94: =AH65 -> 0 | AI94: =AI65 -> 0 | AJ94: =SUM(AF94:AI94) -> 0 | AK94: =AK65 -> 0 | AL94: =AL65 -> 0 | AM94: =AM65 -> 0 | AN94: =AN65 -> 0 | AO94: =SUM(AK94:AN94) -> 0
A95: Indemnification receivable | B95: =B66 -> 0 | C95: =C66 -> 0 | D95: =D66 -> 0 | E95: =E66 -> 0 | F95: =SUM(B95:E95) -> 0 | G95: =G66 -> 0 | H95: =H66 -> 0 | I95: =I66 -> 0 | J95: =J66 -> 0 | K95: =SUM(G95:J95) -> 0 | L95: =L66 -> 0 | M95: =M66 -> 0 | N95: =N66 -> 0 | O95: =O66 -> 0 | P95: =SUM(L95:O95) -> 0 | Q95: =Q66 -> 0 | R95: =R66 -> 0 | S95: =S66 -> 0 | T95: =T66 -> 0 | U95: =SUM(Q95:T95) -> 0 | V95: =V66 -> 0 | W95: =W66 -> 0 | X95: =X66 -> 0 | Y95: =Y66 -> 0 | Z95: =SUM(V95:Y95) -> 0 | AA95: =AA66 -> 0 | AB95: =AB66 -> 0 | AC95: =AC66 -> 0 | AD95: =AD66 -> 0 | AE95: =SUM(AA95:AD95) -> 0 | AF95: =AF66 -> 0 | AG95: =AG66 -> 0 | AH95: =AH66 -> 0 | AI95: =AI66 -> 0 | AJ95: =SUM(AF95:AI95) -> 0 | AK95: =AK66 -> 0 | AL95: =AL66 -> 0 | AM95: =AM66 -> 0 | AN95: =AN66 -> 0 | AO95: =SUM(AK95:AN95) -> 0
A96: =A51 -> Management fees | B96: =B51 -> 0 | C96: =C51 -> 0 | D96: =D51 -> 0 | E96: =E51 -> 0 | F96: =SUM(B96:E96) -> 0 | G96: =G51 -> 0 | H96: =H51 -> 0 | I96: =I51 -> 0 | J96: =J51 -> 0 | K96: =SUM(G96:J96) -> 0 | L96: =L51 -> 0 | M96: =M51 -> 0 | N96: =N51 -> 0 | O96: =O51 -> 0 | P96: =SUM(L96:O96) -> 0 | Q96: =Q51 -> 0 | R96: =R51 -> 0 | S96: =S51 -> 0 | T96: =T51 -> 0 | U96: =SUM(Q96:T96) -> 0 | V96: =V51 -> 0 | W96: =W51 -> 0 | X96: =X51 -> 0 | Y96: =Y51 -> 0 | Z96: =SUM(V96:Y96) -> 0 | AA96: =AA51 -> 0 | AB96: =AB51 -> 0 | AC96: =AC51 -> 0 | AD96: =AD51 -> 0 | AE96: =SUM(AA96:AD96) -> 0 | AF96: =AF51 -> 0 | AG96: =AG51 -> 0 | AH96: =AH51 -> 0 | AI96: =AI51 -> 0 | AJ96: =SUM(AF96:AI96) -> 0 | AK96: =AK51 -> 0 | AL96: =AL51 -> 0 | AM96: =AM51 -> 0 | AN96: =AN51 -> 0 | AO96: =SUM(AK96:AN96) -> 0
A97: =A52 -> IT system upgrade costs | B97: =B52 -> 0 | C97: =C52 -> 0 | D97: =D52 -> 0 | E97: =E52 -> 0 | F97: =SUM(B97:E97) -> 0 | G97: =G52 -> 0 | H97: =H52 -> 0 | I97: =I52 -> 0 | J97: =J52 -> 0 | K97: =SUM(G97:J97) -> 0 | L97: =L52 -> 0 | M97: =M52 -> 0 | N97: =N52 -> 0 | O97: =O52 -> 0 | P97: =SUM(L97:O97) -> 0 | Q97: =Q52 -> 0 | R97: =R52 -> 0 | S97: =S52 -> 0 | T97: =T52 -> 0 | U97: =SUM(Q97:T97) -> 0 | V97: =V52 -> 0 | W97: =W52 -> 0 | X97: =X52 -> 0 | Y97: =Y52 -> 0 | Z97: =SUM(V97:Y97) -> 0 | AA97: =AA52 -> 0 | AB97: =AB52 -> 0 | AC97: =AC52 -> 0 | AD97: =AD52 -> 0 | AE97: =SUM(AA97:AD97) -> 0 | AF97: =AF52 -> 0 | AG97: =AG52 -> 0 | AH97: =AH52 -> 0 | AI97: =AI52 -> 0 | AJ97: =SUM(AF97:AI97) -> 0 | AK97: =AK52 -> 0 | AL97: =AL52 -> 0 | AM97: =AM52 -> 0 | AN97: =AN52 -> 0 | AO97: =SUM(AK97:AN97) -> 0
A98: =A53 -> IPO-related compensation expense | B98: =B53 -> 0 | C98: =C53 -> 0 | D98: =D53 -> 0 | E98: =E53 -> 0 | F98: =SUM(B98:E98) -> 0 | G98: =G53 -> 0 | H98: =H53 -> 0 | I98: =I53 -> 0 | J98: =J53 -> 0 | K98: =K53 -> 0 | L98: =L53 -> 0 | M98: =M53 -> 0 | N98: =N53 -> 0 | O98: =O53 -> 0 | P98: =SUM(L98:O98) -> 0 | Q98: =Q53 -> 0 | R98: =R53 -> 0 | S98: =S53 -> 0 | T98: =T53 -> 0 | U98: =SUM(Q98:T98) -> 0 | V98: =V53 -> 0 | W98: =W53 -> 0 | X98: =X53 -> 0 | Y98: =Y53 -> 0 | Z98: =SUM(V98:Y98) -> 0 | AA98: =AA53 -> 0 | AB98: =AB53 -> 0 | AC98: =AC53 -> 0 | AD98: =AD53 -> 0 | AE98: =SUM(AA98:AD98) -> 0 | AF98: =AF53 -> 0 | AG98: =AG53 -> 0 | AH98: =AH53 -> 0 | AI98: =AI53 -> 0 | AJ98: =SUM(AF98:AI98) -> 0 | AK98: =AK53 -> 0 | AL98: =AL53 -> 0 | AM98: =AM53 -> 0 | AN98: =AN53 -> 0 | AO98: =SUM(AK98:AN98) -> 0
A99: Gain on sale of corporate-owned stores | B99: =B69 -> 0 | C99: =C69 -> 0 | D99: =D69 -> 0 | E99: =E69 -> 0 | F99: =SUM(B99:E99) -> 0 | G99: =G69 -> 0 | H99: =H69 -> 0 | I99: =I69 -> 0 | J99: =J69 -> 0 | K99: =K69 -> 0 | L99: =L69 -> 0 | M99: =M69 -> 0 | N99: =N69 -> -6.443 | O99: =O69 -> 0 | P99: =SUM(L99:O99) -> -6.443 | Q99: =Q69 -> 0 | R99: =R69 -> 0 | S99: =S69 -> 0 | T99: =T69 -> 0 | U99: =SUM(Q99:T99) -> 0 | V99: =V69 -> 0 | W99: =W69 -> 0 | X99: =X69 -> 0 | Y99: =Y69 -> 0 | Z99: =SUM(V99:Y99) -> 0 | AA99: =AA69 -> 0 | AB99: =AB69 -> 0 | AC99: =AC69 -> 0 | AD99: =AD69 -> 0 | AE99: =SUM(AA99:AD99) -> 0 | AF99: =AF69 -> 0 | AG99: =AG69 -> 0 | AH99: =AH69 -> 0 | AI99: =AI69 -> 0 | AJ99: =SUM(AF99:AI99) -> 0 | AK99: =AK69 -> 0 | AL99: =AL69 -> 0 | AM99: =AM69 -> 0 | AN99: =AN69 -> 0 | AO99: =SUM(AK99:AN99) -> 0
A100: Loss on extinguishment of debt | B100: 0 | C100: 0 | D100: 0 | E100: 0 | F100: =SUM(B100:E100) -> 0 | G100: 0 | H100: 2.285 | I100: 0 | J100: 0 | K100: =SUM(G100:J100) -> 2.285 | L100: 0 | M100: 0 | N100: 0 | O100: 0 | P100: =SUM(L100:O100) -> 0 | Q100: 0 | R100: 0 | S100: 0 | T100: 0 | U100: =SUM(Q100:T100) -> 0 | V100: 0 | W100: 0 | X100: 0 | Y100: 0 | Z100: =SUM(V100:Y100) -> 0 | AA100: 0 | AB100: 0 | AC100: 0 | AD100: 0 | AE100: =SUM(AA100:AD100) -> 0 | AF100: 0 | AG100: 0 | AH100: 0 | AI100: 0 | AJ100: =SUM(AF100:AI100) -> 0 | AK100: 0 | AL100: 0 | AM100: 0 | AN100: 0 | AO100: =SUM(AK100:AN100) -> 0
A101: Other | B101: =B71 -> -1.459 | C101: =C71 -> 0.818 | D101: =D71 -> 0.05 | E101: =E71 -> 0.176 | F101: =SUM(B101:E101) -> -0.415 | G101: =G71 -> -0.228 | H101: =H71 -> 0.121 | I101: =I71 -> 0.032 | J101: =J71 -> 0.211 | K101: =SUM(G101:J101) -> 0.136 | L101: =L71 -> 0.155 | M101: =M71 -> 0.176 | N101: =N71 -> 0.212 | O101: =O71 -> 0 | P101: =SUM(L101:O101) -> 0.543 | Q101: =Q71 -> 0 | R101: =R71 -> 0 | S101: =S71 -> 0 | T101: =T71 -> 0 | U101: =SUM(Q101:T101) -> 0 | V101: =V71 -> 0 | W101: =W71 -> 0 | X101: =X71 -> 0 | Y101: =Y71 -> 0 | Z101: =SUM(V101:Y101) -> 0 | AA101: =AA71 -> 0 | AB101: =AB71 -> 0 | AC101: =AC71 -> 0 | AD101: =AD71 -> 0 | AE101: =SUM(AA101:AD101) -> 0 | AF101: =AF71 -> 0 | AG101: =AG71 -> 0 | AH101: =AH71 -> 0 | AI101: =AI71 -> 0 | AJ101: =SUM(AF101:AI101) -> 0 | AK101: =AK71 -> 0 | AL101: =AL71 -> 0 | AM101: =AM71 -> 0 | AN101: =AN71 -> 0 | AO101: =SUM(AK101:AN101) -> 0
A102: Purchase accounting amortization | B102: 12.577 | C102: 12.954 | D102: 12.954 | E102: 12.955 | F102: =SUM(B102:E102) -> 51.44 | G102: 12.757 | H102: 12.758 | I102: 12.757 | J102: 10.918 | K102: =SUM(G102:J102) -> 49.19 | L102: 9.178 | M102: 9.178 | N102: 9.178 | O102: =J102 -> 10.918 | P102: =SUM(L102:O102) -> 38.452 | Q102: =L102 -> 9.178 | R102: =M102 -> 9.178 | S102: =N102 -> 9.178 | T102: =O102 -> 10.918 | U102: =SUM(Q102:T102) -> 38.452 | V102: 10 | W102: 11 | X102: 10 | Y102: =T102 -> 10.918 | Z102: =SUM(V102:Y102) -> 41.918 | AA102: =V102 -> 10 | AB102: =W102 -> 11 | AC102: =X102 -> 10 | AD102: =Y102 -> 10.918 | AE102: =SUM(AA102:AD102) -> 41.918 | AF102: =AA102 -> 10 | AG102: =AB102 -> 11 | AH102: =AC102 -> 10 | AI102: =AD102 -> 10.918 | AJ102: =SUM(AF102:AI102) -> 41.918 | AK102: =AF102 -> 10 | AL102: =AG102 -> 11 | AM102: =AH102 -> 10 | AN102: =AI102 -> 10.918 | AO102: =SUM(AK102:AN102) -> 41.918
A103: Adjusted income before income taxes | B103: =SUM(B75:B77) -> 32.306 | C103: =SUM(C75:C77) -> 59.825 | D103: =SUM(D75:D77) -> 52.332 | E103: =SUM(E75:E77) -> 54.093 | F103: =SUM(F75:F77) -> 268.568 | G103: =SUM(G75:G77) -> 63.716 | H103: =SUM(H75:H77) -> 83.812 | I103: =SUM(I75:I77) -> 73.802 | ... AO103: =SUM(AO75:AO77) -> 746.41608
A104: Adjusted income taxes | B104: 12.719 | C104: 20.156 | D104: 18.107 | E104: 18.577 | F104: 69.559 | G104: 16.439 | H104: 21.645 | I104: 19.06 | J104: 20.863 | K104: 78.163 | L104: 17.487 | M104: 25.299 | N104: 23.421 | O104: =O103*Assumptions!O159 -> 23.7886 | P104: =SUM(L104:O104) -> 89.9956 | Q104: =Q103*Assumptions!Q159 -> 22.535059 | R104: =R103*Assumptions!R159 -> 31.162766 | S104: =S103*Assumptions!S159 -> 29.563791 | T104: =T103*Assumptions!T159 -> 30.413402 | U104: =SUM(Q104:T104) -> 113.67502 | V104: =V103*Assumptions!V159 -> 27.451798 | W104: =W103*Assumptions!W159 -> 36.616268 | X104: =X103*Assumptions!X159 -> 35.352116 | Y104: =Y103*Assumptions!Y159 -> 35.40299 | Z104: =SUM(V104:Y104) -> 134.82317 | AA104: =AA103*Assumptions!AA159 -> 32.071824 | AB104: =AB103*Assumptions!AB159 -> 41.638694 | AC104: =AC103*Assumptions!AC159 -> 40.224938 | AD104: =AD103*Assumptions!AD159 -> 40.033958 | AE104: =SUM(AA104:AD104) -> 153.96941 | AF104: =AF103*Assumptions!AF159 -> 39.023223 | AG104: =AG103*Assumptions!AG159 -> 46.70274 | AH104: =AH103*Assumptions!AH159 -> 43.602733 | AI104: =AI103*Assumptions!AI159 -> 43.637897 | AJ104: =SUM(AF104:AI104) -> 172.96659 | AK104: =AK103*Assumptions!AK159 -> 43.054749 | AL104: =AL103*Assumptions!AL159 -> 50.862752 | AM104: =AM103*Assumptions!AM159 -> 47.547172 | AN104: =AN103*Assumptions!AN159 -> 47.378594 | AO104: =SUM(AK104:AN104) -> 188.84327 | AU104: =SUM(K104)-SUM(G104,H104,I104,J104) -> 0.156
A105: Adjusted Net Income | B105: =B103-B104 -> 19.587 | C105: =C103-C104 -> 39.669 | D105: =D103-D104 -> 34.225 | E105: =E103-E104 -> 35.516 | F105: =F103-F104 -> 199.009 | G105: =G103-G104 -> 47.277 | H105: =H103-H104 -> 62.167 | I105: =I103-I104 -> 54.742 | ... AO105: =AO103-AO104 -> 557.57281
A106: YoY % Change | B106: =IFERROR(B105/#REF!-1,"na") -> na | C106: =IFERROR(C105/#REF!-1,"na") -> na | D106: =IFERROR(D105/#REF!-1,"na") -> na | E106: =IFERROR(E105/#REF!-1,"na") -> na | F106: =IFERROR(F105/#REF!-1,"na") -> na | G106: =IFERROR(G105/B105-1,"na") -> 1.4136928 | H106: =IFERROR(H105/C105-1,"na") -> 0.56714311 | I106: =IFERROR(I105/D105-1,"na") -> 0.59947407 | J106: =IFERROR(J105/E105-1,"na") -> 0.68160829 | K106: =IFERROR(K105/F105-1,"na") -> 0.12434111 | L106: =IFERROR(L105/G105-1,"na") -> 0.058231275 | M106: =IFERROR(M105/H105-1,"na") -> 0.16730741 | N106: =IFERROR(N105/I105-1,"na") -> 0.22408754 | ... AO106: =IFERROR(AO105/AJ105-1,"na") -> 0.091790409
A107: Adjusted weighted-average shares outstanding, diluted | B107: 89.794 | C107: 89.092 | D107: 88.42 | E107: 88.441 | F107: 88.92 | G107: 88.399 | H107: 87.685 | I107: 85.26 | J107: 84.845 | K107: 86.537 | L107: 84.744 | M107: 84.398 | N107: 84.033 | O107: =N107 -> 84.033 | P107: =AVERAGE(L107:O107) -> 84.302 | Q107: =N107 -> 84.033 | R107: =Q107 -> 84.033 | S107: =R107 -> 84.033 | T107: =S107 -> 84.033 | U107: =AVERAGE(Q107:T107) -> 84.033 | V107: =Q107 -> 84.033 | W107: =R107 -> 84.033 | X107: =S107 -> 84.033 | Y107: =T107 -> 84.033 | Z107: =AVERAGE(V107:Y107) -> 84.033 | AA107: =V107 -> 84.033 | AB107: =W107 -> 84.033 | AC107: =X107 -> 84.033 | AD107: =Y107 -> 84.033 | AE107: =AVERAGE(AA107:AD107) -> 84.033 | AF107: =AA107 -> 84.033 | AG107: =AB107 -> 84.033 | AH107: =AC107 -> 84.033 | AI107: =AD107 -> 84.033 | AJ107: =AVERAGE(AF107:AI107) -> 84.033 | AK107: =AF107 -> 84.033 | AL107: =AG107 -> 84.033 | AM107: =AH107 -> 84.033 | AN107: =AI107 -> 84.033 | AO107: =AVERAGE(AK107:AN107) -> 84.033
A108: Adjusted EPS | B108: =B105/B107 -> 0.21813261 | C108: =C105/C107 -> 0.44525883 | D108: =D105/D107 -> 0.38707306 | E108: =E105/E107 -> 0.40157845 | F108: =F105/F107 -> 2.2380679 | G108: =G105/G107 -> 0.53481374 | H108: =H105/H107 -> 0.70898101 | I108: =I105/I107 -> 0.64205958 | ... AO108: =AO105/AO107 -> 6.6351649
A109: YoY % Change | B109: =IFERROR(B108/#REF!-1,"na") -> na | C109: =IFERROR(C108/#REF!-1,"na") -> na | D109: =IFERROR(D108/#REF!-1,"na") -> na | E109: =IFERROR(E108/#REF!-1,"na") -> na | F109: =IFERROR(F108/#REF!-1,"na") -> na | G109: =IFERROR(G108/B108-1,"na") -> 1.4517826 | H109: =IFERROR(H108/C108-1,"na") -> 0.5922896 | I109: =IFERROR(I108/D108-1,"na") -> 0.65875554 | J109: =IFERROR(J108/E108-1,"na") -> 0.75288018 | K109: =IFERROR(K108/F108-1,"na") -> 0.15530249 | L109: =IFERROR(L108/G108-1,"na") -> 0.10387268 | M109: =IFERROR(M108/H108-1,"na") -> 0.21276986 | N109: =IFERROR(N108/I108-1,"na") -> 0.24196094 | ... AO109: =IFERROR(AO108/AJ108-1,"na") -> 0.091790409
A111: Revenue Breakdown
A112: Franchise segment revenue - U.S. | B112: 90.288 | C112: 96.337 | D112: 95.209 | E112: =F112-SUM(B112:D112) -> 94.693 | F112: 376.527 | G112: 100.528 | H112: 104.541 | I112: 98.902 | J112: =J114-J113 -> 105.022 | K112: =SUM(G112:J112) -> 408.993
A113: Franchise segment revenue - International | B113: 2.394 | C113: 2.505 | D113: 2.956 | E113: =F113-SUM(B113:D113) -> 3.547 | F113: 11.402 | G113: 3.492 | H113: 3.249 | I113: 3.513 | J113: 4 | K113: =SUM(G113:J113) -> 14.254
A114: Franchise segment total | B114: =SUM(B112:B113) -> 92.682 | C114: =SUM(C112:C113) -> 98.842 | D114: =SUM(D112:D113) -> 98.165 | E114: =SUM(E112:E113) -> 98.24 | F114: =SUM(F112:F113) -> 387.929 | G114: =SUM(G112:G113) -> 104.02 | H114: =SUM(H112:H113) -> 107.79 | I114: =SUM(I112:I113) -> 102.415 | J114: =K114-I114-H114-G114 -> 109.022 | K114: 423.247 | L114: 115.18 | M114: 119.658 | N114: 113.675
A117: Corporate-owned stores segment total | B117: =SUM(B115:B116) -> 0 | C117: =SUM(C115:C116) -> 0 | D117: =SUM(D115:D116) -> 0 | E117: =SUM(E115:E116) -> 0 | F117: =SUM(F115:F116) -> 0 | G117: =SUM(G115:G116) -> 0 | H117: =SUM(H115:H116) -> 0 | I117: =SUM(I115:I116) -> 0 | J117: =K117-I117-H117-G117 -> 502.287 | K117: 502.287 | L117: 133.669 | M117: 138.989 | N117: 137.833
...

Sheet Assumptions
A2: Planet Fitness Inc
A3: Assumptions
A4: (All values in $mn except EPS and stores)
B5: 2023A | F5: 2023A | G5: 2024A | K5: 2024A | L5: 2025E | P5: 2025 | Q5: =P5+1 -> 2026 | U5: =Q5 -> 2026 | V5: =U5+1 -> 2027 | Z5: =V5 -> 2027 | AA5: =Z5+1 -> 2028 | AE5: =AA5 -> 2028 | AF5: =AE5+1 -> 2029 | AJ5: =AF5 -> 2029 | AK5: =AJ5+1 -> 2030 | AO5: =AK5 -> 2030
B6: 1QA | C6: 2QA | D6: 3QA | E6: 4QA | F6: FY | G6: 1QA | H6: 2QA | I6: 3QA | J6: 4QA | K6: FY | L6: 1QA | M6: 2QA | N6: 3QA | O6: 4QE | P6: FY | Q6: 1QE | R6: 2QE | S6: 3QE | T6: 4QE | U6: FY | V6: 1QE | W6: 2QE | X6: 3QE | Y6: 4QE | Z6: FY | AA6: 1QE | AB6: 2QE | AC6: 3QE | AD6: 4QE | AE6: FY | AF6: 1QE | AG6: 2QE | AH6: 3QE | AI6: 4QE | AJ6: FY | AK6: 1QE | AL6: 2QE | AM6: 3QE | AN6: 4QE | AO6: FY
A8: Revenue Breakdown: | T8: =U10-U8 -> 44.435497 | U8: 528.25594
A10: Franchise segment total | B10: 92.682 | C10: 98.842 | D10: 98.165 | E10: 98.24 | F10: =SUM(B10:E10) -> 387.929 | G10: 104.02 | H10: 107.79 | I10: 102.415 | J10: 109.022 | K10: =SUM(G10:J10) -> 423.247 | L10: ='Income Statement'!L114 -> 115.18 | M10: ='Income Statement'!M114 -> 119.658 | N10: ='Income Statement'!N114 -> 113.675 | O10: =O61*AVERAGE(O52,O58) -> 119.70554 | P10: =SUM(L10:O10) -> 468.21854 | Q10: =Q61*AVERAGE(Q52,Q58) -> 141.16781 | R10: =R61*AVERAGE(R52,R58) -> 146.8498 | S10: =S61*AVERAGE(S52,S58) -> 138.76409 | T10: =T61*AVERAGE(T52,T58) -> 145.90974 | U10: =SUM(Q10:T10) -> 572.69144 | V10: =V61*AVERAGE(V52,V58) -> 158.80701 | W10: =W61*AVERAGE(W52,W58) -> 165.38773 | X10: =X61*AVERAGE(X52,X58) -> 154.80182 | Y10: =Y61*AVERAGE(Y52,Y58) -> 162.60189 | Z10: =SUM(V10:Y10) -> 641.59844 | AA10: =AA61*AVERAGE(AA52,AA58) -> 175.92554 | AB10: =AB61*AVERAGE(AB52,AB58) -> 183.11879 | AC10: =AC61*AVERAGE(AC52,AC58) -> 171.30563 | AD10: =AD61*AVERAGE(AD52,AD58) -> 179.73848 | AE10: =SUM(AA10:AD10) -> 710.08845 | AF10: =AF61*AVERAGE(AF52,AF58) -> 192.342 | AG10: =AG61*AVERAGE(AG52,AG58) -> 199.95215 | AH10: =AH61*AVERAGE(AH52,AH58) -> 186.7566 | AI10: =AI61*AVERAGE(AI52,AI58) -> 195.58029 | AJ10: =SUM(AF10:AI10) -> 774.63104 | AK10: =AK61*AVERAGE(AK52,AK58) -> 209.04859 | AL10: =AL61*AVERAGE(AL52,AL58) -> 217.24156 | AM10: =AM61*AVERAGE(AM52,AM58) -> 202.8331 | AN10: =AN61*AVERAGE(AN52,AN58) -> 212.24747 | AO10: =SUM(AK10:AN10) -> 841.37072
A11: YoY % Change | G11: =IFERROR(G10/B10-1,"na") -> 0.12233228 | H11: =IFERROR(H10/C10-1,"na") -> 0.090528318 | I11: =IFERROR(I10/D10-1,"na") -> 0.043294453 | J11: =IFERROR(J10/E10-1,"na") -> 0.10975163 | K11: =IFERROR(K10/F10-1,"na") -> 0.091042433 | L11: =IFERROR(L10/G10-1,"na") -> 0.10728706 | M11: =IFERROR(M10/H10-1,"na") -> 0.11010298 | N11: =IFERROR(N10/I10-1,"na") -> 0.10994483 | ... AO11: =IFERROR(AO10/AJ10-1,"na") -> 0.086156731
A12: As % of Total Revenue | B12: =B10/B$22 -> 0.41706379 | C12: =C10/C$22 -> 0.34504282 | D12: =D10/D$22 -> 0.35368275 | E12: =E10/E$22 -> 0.34459656 | F12: =F10/F$22 -> 0.36210173 | G12: =G10/G$22 -> 0.41940673 | H12: =H10/H$22 -> 0.35817652 | I12: =I10/I$22 -> 0.35044107 | ... AO12: =AO10/AO$22 -> 0.4025646
A14: Corporate-owned stores segment total | B14: 105.882 | C14: 113.759 | D14: 113.245 | E14: 116.41 | F14: =SUM(B14:E14) -> 449.296 | G14: 122.378 | H14: 125.466 | I14: 128.132 | J14: 126.311 | K14: =SUM(G14:J14) -> 502.287 | L14: 133.669 | M14: ='Income Statement'!M117 -> 138.989 | N14: ='Income Statement'!N117 -> 137.833 | O14: =O75*AVERAGE(O66,O72) -> 136.30695 | P14: =SUM(L14:O14) -> 546.79795 | Q14: =Q75*AVERAGE(Q66,Q72) -> 146.14797 | R14: =R75*AVERAGE(R66,R72) -> 151.12276 | S14: =S75*AVERAGE(S66,S72) -> 151.39635 | T14: =T75*AVERAGE(T66,T72) -> 151.14316 | U14: =SUM(Q14:T14) -> 599.81025 | V14: =V75*AVERAGE(V66,V72) -> 161.94077 | W14: =W75*AVERAGE(W66,W72) -> 168.48763 | X14: =X75*AVERAGE(X66,X72) -> 169.47154 | Y14: =Y75*AVERAGE(Y66,Y72) -> 169.46958 | Z14: =SUM(V14:Y14) -> 669.36952 | AA14: =AA75*AVERAGE(AA66,AA72) -> 179.60022 | AB14: =AB75*AVERAGE(AB66,AB72) -> 186.72059 | AC14: =AC75*AVERAGE(AC66,AC72) -> 187.61465 | AD14: =AD75*AVERAGE(AD66,AD72) -> 187.32937 | AE14: =SUM(AA14:AD14) -> 741.26483 | AF14: =AF75*AVERAGE(AF66,AF72) -> 198.29744 | AG14: =AG75*AVERAGE(AG66,AG72) -> 205.73328 | AH14: =AH75*AVERAGE(AH66,AH72) -> 205.95842 | AI14: =AI75*AVERAGE(AI66,AI72) -> 204.54822 | AJ14: =SUM(AF14:AI14) -> 814.53737 | AK14: =AK75*AVERAGE(AK66,AK72) -> 213.66338 | AL14: =AL75*AVERAGE(AL66,AL72) -> 221.58403 | AM14: =AM75*AVERAGE(AM66,AM72) -> 221.70691 | AN14: =AN75*AVERAGE(AN66,AN72) -> 220.01561 | AO14: =SUM(AK14:AN14) -> 876.96993
A15: YoY % Change | G15: =IFERROR(G14/B14-1,"na") -> 0.15579607 | H15: =IFERROR(H14/C14-1,"na") -> 0.10291054 | I15: =IFERROR(I14/D14-1,"na") -> 0.13145834 | J15: =IFERROR(J14/E14-1,"na") -> 0.085052831 | K15: =IFERROR(K14/F14-1,"na") -> 0.11794229 | L15: =IFERROR(L14/G14-1,"na") -> 0.092263315 | M15: =IFERROR(M14/H14-1,"na") -> 0.10778219 | N15: =IFERROR(N14/I14-1,"na") -> 0.075710986 | ... AO15: =IFERROR(AO14/AJ14-1,"na") -> 0.076647877
A16: As % of Total Revenue | B16: =B14/B$22 -> 0.47646304 | C16: =C14/C$22 -> 0.39711586 | D16: =D14/D$22 -> 0.4080151 | E16: =E14/E$22 -> 0.40833149 | F16: =F14/F$22 -> 0.41938308 | G16: =G14/G$22 -> 0.49342585 | H16: =H14/H$22 -> 0.41691229 | I16: =I14/I$22 -> 0.43843885 | ... AO16: =AO14/AO$22 -> 0.4195975
A18: Equipment segment total | B18: 23.661 | C18: 73.862 | D18: 66.141 | E18: 70.437 | F18: =SUM(B18:E18) -> 234.101 | G18: 21.619 | H18: 67.685 | I18: 61.699 | J18: 105.117 | K18: =SUM(G18:J18) -> 256.12 | L18: 27.813 | M18: ='Income Statement'!M120 -> 82.232 | N18: ='Income Statement'!N120 -> 78.837 | O18: =J18*(1+O19) -> 105.117 | P18: =SUM(L18:O18) -> 293.999 | Q18: =L18*(1+Q19) -> 30.31617 | R18: =M18*(1+R19) -> 89.63288 | S18: =N18*(1+S19) -> 85.93233 | T18: =O18*(1+T19) -> 113.52636 | U18: =SUM(Q18:T18) -> 319.40774 | V18: =Q18*(1+V19) -> 32.286721 | W18: =R18*(1+W19) -> 95.459017 | X18: =S18*(1+X19) -> 91.517931 | Y18: =T18*(1+Y19) -> 120.90557 | Z18: =SUM(V18:Y18) -> 340.16924 | AA18: =V18*(1+AA19) -> 33.57819 | AB18: =W18*(1+AB19) -> 99.277378 | AC18: =X18*(1+AC19) -> 95.178649 | AD18: =Y18*(1+AD19) -> 125.7418 | AE18: =SUM(AA18:AD18) -> 353.77601 | AF18: =AA18*(1+AF19) -> 34.417645 | AG18: =AB18*(1+AG19) -> 101.75931 | AH18: =AC18*(1+AH19) -> 97.558115 | AI18: =AD18*(1+AI19) -> 128.88534 | AJ18: =SUM(AF18:AI18) -> 362.62041 | AK18: =AF18*(1+AK19) -> 35.278086 | AL18: =AG18*(1+AL19) -> 104.3033 | AM18: =AH18*(1+AM19) -> 99.997068 | AN18: =AI18*(1+AN19) -> 132.10747 | AO18: =SUM(AK18:AN18) -> 371.68592
A19: YoY % Change | F19: =IFERROR(F18/#REF!-1,"na") -> na | G19: =IFERROR(G18/B18-1,"na") -> -0.086302354 | H19: =IFERROR(H18/C18-1,"na") -> -0.08362893 | I19: =IFERROR(I18/D18-1,"na") -> -0.067159553 | J19: =IFERROR(J18/E18-1,"na") -> 0.49235487 | K19: =IFERROR(K18/F18-1,"na") -> 0.094057693 | L19: =IFERROR(L18/G18-1,"na") -> 0.28650724 | M19: =IFERROR(M18/H18-1,"na") -> 0.21492207 | N19: =IFERROR(N18/I18-1,"na") -> 0.27776787 | O19: 0 | P19: =IFERROR(P18/K18-1,"na") -> 0.14789552 | Q19: 0.09 | R19: 0.09 | S19: 0.09 | T19: 0.08 | U19: =IFERROR(U18/P18-1,"na") -> 0.08642458 | V19: 0.065 | W19: 0.065 | X19: 0.065 | Y19: 0.065 | Z19: =IFERROR(Z18/U18-1,"na") -> 0.065 | AA19: 0.04 | AB19: 0.04 | AC19: 0.04 | AD19: 0.04 | AE19: =IFERROR(AE18/Z18-1,"na") -> 0.04 | AF19: 0.025 | AG19: 0.025 | AH19: 0.025 | AI19: 0.025 | AJ19: =IFERROR(AJ18/AE18-1,"na") -> 0.025 | AK19: 0.025 | AL19: 0.025 | AM19: 0.025 | AN19: 0.025 | AO19: =IFERROR(AO18/AJ18-1,"na") -> 0.025
A20: As % of Total Revenue | B20: =B18/B$22 -> 0.10647317 | C20: =C18/C$22 -> 0.25784133 | D20: =D18/D$22 -> 0.23830215 | E20: =E18/E$22 -> 0.24707195 | F20: =F18/F$22 -> 0.21851519 | G20: =G18/G$22 -> 0.087167412 | H20: =H18/H$22 -> 0.2249112 | I20: =I18/I$22 -> 0.21112008 | ... AO20: =AO18/AO$22 -> 0.17783789
A22: Total Revenue | B22: =B10+B14+B18 -> 222.225 | C22: =C10+C14+C18 -> 286.463 | D22: =D10+D14+D18 -> 277.551 | E22: =E10+E14+E18 -> 285.087 | F22: =F10+F14+F18 -> 1071.326 | G22: =G10+G14+G18 -> 248.017 | H22: =H10+H14+H18 -> 300.941 | I22: =I10+I14+I18 -> 292.246 | ... AO22: =AO10+AO14+AO18 -> 2090.0266
A23: YoY % Change | F23: 0.12560406 | G23: =IFERROR(G22/B22-1,"na") -> 0.11606255 | H23: =IFERROR(H22/C22-1,"na") -> 0.050540558 | I23: =IFERROR(I22/D22-1,"na") -> 0.052945224 | J23: =IFERROR(J22/E22-1,"na") -> 0.19419686 | K23: =IFERROR(K22/F22-1,"na") -> 0.10298266 | L23: =IFERROR(L22/G22-1,"na") -> 0.11549612 | M23: =IFERROR(M22/H22-1,"na") -> 0.1327104 | N23: =IFERROR(N22/I22-1,"na") -> 0.1303662 | ... AO23: =IFERROR(AO22/AJ22-1,"na") -> 0.070826181
A25: Segment EBITDA Details:
A27: Franchise | B27: 64.735 | C27: 66.101 | D27: 67.583 | E27: 68.309 | F27: =SUM(B27:E27) -> 266.728 | G27: ='Income Statement'!G124 -> 76.138 | H27: ='Income Statement'!H124 -> 77.409 | I27: ='Income Statement'!I124 -> 72.758 | J27: ='Income Statement'!J124 -> 74.817 | K27: =SUM(G27:J27) -> 301.122 | L27: 84.865 | M27: ='Income Statement'!M124 -> 86.502 | N27: ='Income Statement'!N124 -> 82.367 | O27: =O30*'Income Statement'!O$47 -> 84.620971 | P27: =SUM(L27:O27) -> 338.35497 | Q27: =Q30*'Income Statement'!Q$47 -> 97.801173 | R27: =R30*'Income Statement'!R$47 -> 101.5734 | S27: =S30*'Income Statement'!S$47 -> 90.44247 | T27: =T30*'Income Statement'!T$47 -> 96.512234 | U27: =SUM(Q27:T27) -> 386.32928 | V27: =V30*'Income Statement'!V$47 -> 111.97043 | W27: =W30*'Income Statement'!W$47 -> 114.37581 | X27: =X30*'Income Statement'!X$47 -> 101.60779 | Y27: =Y30*'Income Statement'!Y$47 -> 108.228 | Z27: =SUM(V27:Y27) -> 436.18203 | AA27: =AA30*'Income Statement'!AA$47 -> 124.43237 | AB27: =AB30*'Income Statement'!AB$47 -> 125.69625 | AC27: =AC30*'Income Statement'!AC$47 -> 111.58427 | AD27: =AD30*'Income Statement'!AD$47 -> 118.29243 | AE27: =SUM(AA27:AD27) -> 480.00532 | AF27: =AF30*'Income Statement'!AF$47 -> 142.90779 | AG27: =AG30*'Income Statement'!AG$47 -> 136.57688 | AH27: =AH30*'Income Statement'!AH$47 -> 117.76809 | AI27: =AI30*'Income Statement'!AI$47 -> 125.47763 | AJ27: =SUM(AF27:AI27) -> 522.73039 | AK27: =AK30*'Income Statement'!AK$47 -> 154.55967 | AL27: =AL30*'Income Statement'!AL$47 -> 146.54657 | AM27: =AM30*'Income Statement'!AM$47 -> 126.30576 | AN27: =AN30*'Income Statement'!AN$47 -> 134.11695 | AO27: =SUM(AK27:AN27) -> 561.52895
A28: YoY % Change | B28: =IFERROR(B27/#REF!-1,"na") -> na | C28: =IFERROR(C27/#REF!-1,"na") -> na | D28: =IFERROR(D27/#REF!-1,"na") -> na | E28: =IFERROR(E27/#REF!-1,"na") -> na | F28: =IFERROR(F27/#REF!-1,"na") -> na | G28: =IFERROR(G27/B27-1,"na") -> 0.17614891 | H28: =IFERROR(H27/C27-1,"na") -> 0.17107154 | I28: =IFERROR(I27/D27-1,"na") -> 0.076572511 | J28: =IFERROR(J27/E27-1,"na") -> 0.095272951 | K28: =IFERROR(K27/F27-1,"na") -> 0.12894784 | L28: =IFERROR(L27/G27-1,"na") -> 0.11462082 | M28: =IFERROR(M27/H27-1,"na") -> 0.11746696 | N28: =IFERROR(N27/I27-1,"na") -> 0.13206795 | ... AO28: =IFERROR(AO27/AJ27-1,"na") -> 0.074222896
A29: Segment EBITDA Margin | B29: =B27/B$10 -> 0.69846356 | C29: =C27/C$10 -> 0.66875417 | D29: =D27/D$10 -> 0.6884633 | E29: =E27/E$10 -> 0.69532777 | F29: =F27/F$10 -> 0.68756912 | G29: =G27/G$10 -> 0.73195539 | H29: =H27/H$10 -> 0.7181464 | I29: =I27/I$10 -> 0.71042328 | ... AO29: =AO27/AO$10 -> 0.66739778
A30: As % of Total EBITDA | B30: =B27/B$47 -> 0.73550799 | C30: =C27/C$47 -> 0.57949783 | D30: =D27/D$47 -> 0.61588022 | E30: =E27/E$47 -> 0.60999982 | F30: =F27/F$47 -> 0.62937829 | G30: =G27/G$47 -> 0.71618177 | H30: =H27/H$47 -> 0.60940932 | I30: =I27/I$47 -> 0.6015842 | ... N30: =N27/N$47 -> 0.56157659 | O30: 0.59 | P30: =P27/P$47 -> 0.61652999 | Q30: =L30-0.7/100 -> 0.71858374 | R30: =M30-0.7/100 -> 0.60154761 | S30: =N30-0.7/100 -> 0.55457659 | T30: =O30-0.7/100 -> 0.583 | U30: =U27/U$47 -> 0.60975216 | V30: =Q30 -> 0.71858374 | W30: =R30 -> 0.60154761 | X30: =S30 -> 0.55457659 | Y30: =T30 -> 0.583 | Z30: =Z27/Z$47 -> 0.61020389 | AA30: =V30 -> 0.71858374 | AB30: =W30 -> 0.60154761 | AC30: =X30 -> 0.55457659 | AD30: =Y30 -> 0.583 | AE30: =AE27/AE$47 -> 0.61051721 | AF30: =AA30 -> 0.71858374 | AG30: =AB30 -> 0.60154761 | AH30: =AC30 -> 0.55457659 | AI30: =AD30 -> 0.583 | AJ30: =AJ27/AJ$47 -> 0.61245434 | AK30: =AF30 -> 0.71858374 | AL30: =AG30 -> 0.60154761 | AM30: =AH30 -> 0.55457659 | AN30: =AI30 -> 0.583 | AO30: =AO27/AO$47 -> 0.61268634
A32: Corporate-owned stores | B32: 33.53 | C32: 48.705 | D32: 44.264 | E32: 45.019 | F32: =SUM(B32:E32) -> 171.518 | G32: ='Income Statement'!G125 -> 42.398 | H32: ='Income Statement'!H125 -> 49.296 | I32: ='Income Statement'!I125 -> 50.107 | J32: ='Income Statement'!J125 -> 46.95 | K32: =SUM(G32:J32) -> 188.751 | L32: 45.849 | M32: ='Income Statement'!M125 -> 56.598 | N32: ='Income Statement'!N125 -> 53.737 | O32: =O35*'Income Statement'!O$47 -> 52.881476 | P32: =SUM(L32:O32) -> 209.06548 | Q32: =Q35*'Income Statement'!Q$47 -> 52.399867 | R32: =R35*'Income Statement'!R$47 -> 66.050562 | S32: =S35*'Income Statement'!S$47 -> 58.608707 | T32: =T35*'Income Statement'!T$47 -> 59.877939 | U32: =SUM(Q32:T32) -> 236.93707 | V32: =V35*'Income Statement'!V$47 -> 59.991464 | W32: =W35*'Income Statement'!W$47 -> 74.375637 | X32: =X35*'Income Statement'!X$47 -> 65.844077 | Y32: =Y35*'Income Statement'!Y$47 -> 67.146613 | Z32: =SUM(V32:Y32) -> 267.35779 | AA32: =AA35*'Income Statement'!AA$47 -> 66.668316 | AB32: =AB35*'Income Statement'!AB$47 -> 81.73703 | AC32: =AC35*'Income Statement'!AC$47 -> 72.309056 | AD32: =AD35*'Income Statement'!AD$47 -> 73.39077 | AE32: =SUM(AA32:AD32) -> 294.10517 | AF32: =AF35*'Income Statement'!AF$47 -> 76.567069 | AG32: =AG35*'Income Statement'!AG$47 -> 88.812419 | AH32: =AH35*'Income Statement'!AH$47 -> 76.316312 | AI32: =AI35*'Income Statement'!AI$47 -> 77.848593 | AJ32: =SUM(AF32:AI32) -> 319.54439 | AK32: =AK35*'Income Statement'!AK$47 -> 82.809909 | AL32: =AL35*'Income Statement'!AL$47 -> 95.295453 | AM32: =AM35*'Income Statement'!AM$47 -> 81.848909 | AN32: =AN35*'Income Statement'!AN$47 -> 83.208584 | AO32: =SUM(AK32:AN32) -> 343.16285
A33: YoY % Change | B33: =IFERROR(B32/#REF!-1,"na") -> na | C33: =IFERROR(C32/#REF!-1,"na") -> na | D33: =IFERROR(D32/#REF!-1,"na") -> na | E33: =IFERROR(E32/#REF!-1,"na") -> na | F33: =IFERROR(F32/#REF!-1,"na") -> na | G33: =IFERROR(G32/B32-1,"na") -> 0.26447957 | H33: =IFERROR(H32/C32-1,"na") -> 0.012134278 | I33: =IFERROR(I32/D32-1,"na") -> 0.13200343 | J33: =IFERROR(J32/E32-1,"na") -> 0.042893001 | K33: =IFERROR(K32/F32-1,"na") -> 0.10047342 | L33: =IFERROR(L32/G32-1,"na") -> 0.081395349 | M33: =IFERROR(M32/H32-1,"na") -> 0.14812561 | N33: =IFERROR(N32/I32-1,"na") -> 0.072444968 | ... AO33: =IFERROR(AO32/AJ32-1,"na") -> 0.073912926
A34: Segment EBITDA Margin | B34: =B32/B$14 -> 0.31667328 | C34: =C32/C$14 -> 0.42814195 | D34: =D32/D$14 -> 0.39086935 | E34: =E32/E$14 -> 0.38672794 | F34: =F32/F$14 -> 0.38174834 | G34: =G32/G$14 -> 0.34645116 | H34: =H32/H$14 -> 0.39290326 | I34: =I32/I$14 -> 0.39105766 | ... L34: =L32/L$14 -> 0.34300399 | M34: =M32/M$10 -> 0.47299804 | N34: =N32/N$10 -> 0.47272487 | O34: =O32/O$14 -> 0.38795876 | P34: =P32/P$14 -> 0.38234502 | Q34: =Q32/Q$14 -> 0.35853981 | R34: =R32/R$14 -> 0.4370656 | S34: =S32/S$14 -> 0.38712099 | T34: =T32/T$14 -> 0.39616703 | U34: =U32/U$14 -> 0.39502005 | V34: =V32/V$14 -> 0.37045311 | ... AO34: =AO32/AO$14 -> 0.39130515
A35: As % of Total EBITDA | B35: =B32/B$47 -> 0.38096212 | C35: =C32/C$47 -> 0.42698964 | D35: =D32/D$47 -> 0.40337544 | E35: =E32/E$47 -> 0.40201997 | F35: =F32/F$47 -> 0.40471831 | G35: =G32/G$47 -> 0.39881104 | H35: =H32/H$47 -> 0.3880872 | I35: =I32/I$47 -> 0.41429918 | ... N35: =N32/N$47 -> 0.36637781 | O35: =J35 -> 0.36870376 | P35: =P32/P$47 -> 0.38094648 | Q35: =L35-0.7/100 -> 0.38500246 | R35: =M35-0.7/100 -> 0.39117088 | S35: =N35-0.7/100 -> 0.35937781 | T35: =O35-0.7/100 -> 0.36170376 | U35: =U32/U$47 -> 0.37396309 | V35: =Q35 -> 0.38500246 | W35: =R35 -> 0.39117088 | X35: =S35 -> 0.35937781 | Y35: =T35 -> 0.36170376 | Z35: =Z32/Z$47 -> 0.3740245 | AA35: =V35 -> 0.38500246 | AB35: =W35 -> 0.39117088 | AC35: =X35 -> 0.35937781 | AD35: =Y35 -> 0.36170376 | AE35: =AE32/AE$47 -> 0.37407141 | AF35: =AA35 -> 0.38500246 | AG35: =AB35 -> 0.39117088 | AH35: =AC35 -> 0.35937781 | AI35: =AD35 -> 0.36170376 | AJ35: =AJ32/AJ$47 -> 0.37439252 | AK35: =AF35 -> 0.38500246 | AL35: =AG35 -> 0.39117088 | AM35: =AH35 -> 0.35937781 | AN35: =AI35 -> 0.36170376 | AO35: =AO32/AO$47 -> 0.37442627
A37: Equipment | B37: 5.571 | C37: 17.129 | D37: 16.434 | E37: 16.913 | F37: =SUM(B37:E37) -> 56.047 | G37: ='Income Statement'!G126 -> 4.798 | H37: ='Income Statement'!H126 -> 18.575 | I37: ='Income Statement'!I126 -> 18.487 | J37: ='Income Statement'!J126 -> 29.918 | K37: =SUM(G37:J37) -> 71.778 | L37: 7.442 | M37: ='Income Statement'!M126 -> 26.435 | N37: ='Income Statement'!N126 -> 23.724 | O37: =O40*'Income Statement'!O$47 -> 33.697721 | P37: =SUM(L37:O37) -> 91.298721 | Q37: =Q40*'Income Statement'!Q$47 -> 7.7072289 | R37: =R40*'Income Statement'!R$47 -> 30.220056 | S37: =S40*'Income Statement'!S$47 -> 25.237183 | T37: =T40*'Income Statement'!T$47 -> 37.735705 | U37: =SUM(Q37:T37) -> 100.90017 | V37: =V40*'Income Statement'!V$47 -> 8.8238382 | W37: =W40*'Income Statement'!W$47 -> 34.02902 | X37: =X40*'Income Statement'!X$47 -> 28.352768 | Y37: =Y40*'Income Statement'!Y$47 -> 42.3165 | Z37: =SUM(V37:Y37) -> 113.52213 | AA37: =AA40*'Income Statement'!AA$47 -> 9.8059023 | AB37: =AB40*'Income Statement'!AB$47 -> 37.397071 | AC37: =AC40*'Income Statement'!AC$47 -> 31.136618 | AD37: =AD40*'Income Statement'!AD$47 -> 46.251632 | AE37: =SUM(AA37:AD37) -> 124.59122 | AF37: =AF40*'Income Statement'!AF$47 -> 11.261859 | AG37: =AG40*'Income Statement'!AG$47 -> 40.634268 | AH37: =AH40*'Income Statement'!AH$47 -> 32.862161 | AI37: =AI40*'Income Statement'!AI$47 -> 49.060999 | AJ37: =SUM(AF37:AI37) -> 133.81929 | AK37: =AK40*'Income Statement'!AK$47 -> 12.180087 | AL37: =AL40*'Income Statement'!AL$47 -> 43.600445 | AM37: =AM40*'Income Statement'!AM$47 -> 35.244523 | AN37: =AN40*'Income Statement'!AN$47 -> 52.438922 | AO37: =SUM(AK37:AN37) -> 143.46398
A38: YoY % Change | B38: =IFERROR(B37/#REF!-1,"na") -> na | C38: =IFERROR(C37/#REF!-1,"na") -> na | D38: =IFERROR(D37/#REF!-1,"na") -> na | E38: =IFERROR(E37/#REF!-1,"na") -> na | F38: =IFERROR(F37/#REF!-1,"na") -> na | G38: =IFERROR(G37/B37-1,"na") -> -0.13875426 | H38: =IFERROR(H37/C37-1,"na") -> 0.084418238 | I38: =IFERROR(I37/D37-1,"na") -> 0.12492394 | J38: =IFERROR(J37/E37-1,"na") -> 0.76893514 | K38: =IFERROR(K37/F37-1,"na") -> 0.28067515 | L38: =IFERROR(L37/G37-1,"na") -> 0.55106294 | M38: =IFERROR(M37/H37-1,"na") -> 0.42314939 | N38: =IFERROR(N37/I37-1,"na") -> 0.28328014 | ... AO38: =IFERROR(AO37/AJ37-1,"na") -> 0.072072485
A39: Segment EBITDA Margin | B39: =B37/B$18 -> 0.23545074 | C39: =C37/C$18 -> 0.23190545 | D39: =D37/D$18 -> 0.24846918 | E39: =E37/E$18 -> 0.24011528 | F39: =F37/F$18 -> 0.23941376 | G39: =G37/G$18 -> 0.22193441 | H39: =H37/H$18 -> 0.27443304 | I39: =I37/I$18 -> 0.29963208 | ... L39: =L37/L$18 -> 0.26757272 | M39: =M37/M$10 -> 0.22092129 | N39: =N37/N$10 -> 0.20870024 | O39: =O37/O$18 -> 0.32057346 | P39: =P37/P$18 -> 0.31054092 | Q39: =Q37/Q$18 -> 0.25422832 | R39: =R37/R$18 -> 0.33715368 | S39: =S37/S$18 -> 0.29368671 | T39: =T37/T$18 -> 0.33239597 | U39: =U37/U$18 -> 0.31589771 | V39: =V37/V$18 -> 0.2732962 | ... AO39: =AO37/AO$18 -> 0.38598173
A40: As % of Total EBITDA | B40: =B37/B$47 -> 0.063296748 | C40: =C37/C$47 -> 0.15016745 | D40: =D37/D$47 -> 0.14976215 | E40: =E37/E$47 -> 0.1510332 | F40: =F37/F$47 -> 0.13224995 | G40: =G37/G$47 -> 0.045131736 | H40: =H37/H$47 -> 0.14623336 | I40: =I37/I$47 -> 0.15285587 | ... N40: =N37/N$47 -> 0.16174977 | O40: =J40 -> 0.2349495 | P40: =P37/P$47 -> 0.16635901 | Q40: =L40-0.7/100 -> 0.056628047 | R40: =M40-0.7/100 -> 0.17897207 | S40: =N40-0.7/100 -> 0.15474977 | T40: =O40-0.7/100 -> 0.2279495 | U40: =U37/U$47 -> 0.159253 | V40: =Q40 -> 0.056628047 | W40: =R40 -> 0.17897207 | X40: =S40 -> 0.15474977 | Y40: =T40 -> 0.2279495 | Z40: =Z37/Z$47 -> 0.15881361 | AA40: =V40 -> 0.056628047 | AB40: =W40 -> 0.17897207 | AC40: =X40 -> 0.15474977 | AD40: =Y40 -> 0.2279495 | AE40: =AE37/AE$47 -> 0.15846717 | AF40: =AA40 -> 0.056628047 | AG40: =AB40 -> 0.17897207 | AH40: =AC40 -> 0.15474977 | AI40: =AD40 -> 0.2279495 | AJ40: =AJ37/AJ$47 -> 0.15678867 | AK40: =AF40 -> 0.056628047 | AL40: =AG40 -> 0.17897207 | AM40: =AH40 -> 0.15474977 | AN40: =AI40 -> 0.2279495 | AO40: =AO37/AO$47 -> 0.15653408
A42: Corporate and other | B42: -15.822 | C42: -17.869 | D42: -18.547 | E42: -18.259 | F42: =SUM(B42:E42) -> -70.497 | G42: ='Income Statement'!G127 -> -17.023 | H42: ='Income Statement'!H127 -> -18.257 | I42: ='Income Statement'!I127 -> -20.408 | J42: ='Income Statement'!J127 -> -18.253 | K42: =SUM(G42:J42) -> -73.941 | L42: -21.151 | M42: ='Income Statement'!M127 -> -21.926 | N42: ='Income Statement'!N127 -> -19.062 | O42: =O47-O27-O32-O37 -> -27.774793 | P42: =SUM(L42:O42) -> -89.913793 | Q42: =Q47-Q27-Q32-Q37 -> -21.805589 | R42: =R47-R27-R32-R37 -> -28.990548 | S42: =S47-S27-S32-S37 -> -11.204538 | T42: =T47-T27-T32-T37 -> -28.581737 | U42: =SUM(Q42:T42) -> -90.582412 | V42: =V47-V27-V32-V37 -> -24.964743 | W42: =W47-W27-W32-W37 -> -32.644544 | X42: =X47-X27-X32-X37 -> -12.587762 | Y42: =Y47-Y27-Y32-Y37 -> -32.051318 | Z42: =SUM(V42:Y42) -> -102.24837 | AA42: =AA47-AA27-AA32-AA37 -> -27.743236 | AB42: =AB47-AB27-AB32-AB37 -> -35.875565 | AC42: =AC47-AC27-AC32-AC37 -> -13.823707 | AD42: =AD47-AD27-AD32-AD37 -> -35.031862 | AE42: =SUM(AA42:AD42) -> -112.47437 | AF42: =AF47-AF27-AF32-AF37 -> -31.862486 | AG42: =AG47-AG27-AG32-AG37 -> -38.981056 | AH42: =AH47-AH27-AH32-AH37 -> -14.589795 | AI42: =AI47-AI27-AI32-AI37 -> -37.159729 | AJ42: =SUM(AF42:AI42) -> -122.59307 | AK42: =AK47-AK27-AK32-AK37 -> -34.46037 | AL42: =AL47-AL27-AL32-AL37 -> -41.826554 | AM42: =AM47-AM27-AM32-AM37 -> -15.647491 | AN42: =AN47-AN27-AN32-AN37 -> -39.718232 | AO42: =SUM(AK42:AN42) -> -131.65265
A43: YoY % Change | B43: =IFERROR(B42/#REF!-1,"na") -> na | C43: =IFERROR(C42/#REF!-1,"na") -> na | D43: =IFERROR(D42/#REF!-1,"na") -> na | E43: =IFERROR(E42/#REF!-1,"na") -> na | F43: =IFERROR(F42/#REF!-1,"na") -> na | G43: =IFERROR(G42/B42-1,"na") -> 0.075906965 | H43: =IFERROR(H42/C42-1,"na") -> 0.021713582 | I43: =IFERROR(I42/D42-1,"na") -> 0.10033968 | J43: =IFERROR(J42/E42-1,"na") -> -0.00032860507 | K43: =IFERROR(K42/F42-1,"na") -> 0.048853143 | L43: =IFERROR(L42/G42-1,"na") -> 0.24249545 | M43: =IFERROR(M42/H42-1,"na") -> 0.20096401 | N43: =IFERROR(N42/I42-1,"na") -> -0.065954528 | ... AO43: =IFERROR(AO42/AJ42-1,"na") -> 0.073899612
A44: Segment EBITDA Margin | B44: =B42/B$22 -> -0.07119811 | C44: =C42/C$22 -> -0.062378038 | D44: =D42/D$22 -> -0.066823755 | E44: =E42/E$22 -> -0.064047115 | F44: =F42/F$22 -> -0.0658035 | G44: =G42/G$22 -> -0.068636424 | H44: =H42/H$22 -> -0.060666376 | I44: =I42/I$22 -> -0.06983158 | ... AO44: =AO42/AO$22 -> -0.062990896
A45: As % of Total EBITDA | B45: =B42/B$47 -> -0.17976686 | C45: =C42/C$47 -> -0.15665492 | D45: =D42/D$47 -> -0.16901781 | E45: =E42/E$47 -> -0.16305299 | F45: =F42/F$47 -> -0.16634654 | G45: =G42/G$47 -> -0.16012454 | H45: =H42/H$47 -> -0.14372988 | I45: =I42/I$47 -> -0.16873925 | ... AO45: =AO42/AO$47 -> -0.1436467
A47: Total Segment EBITDA | B47: =B27+B32+B37+B42 -> 88.014 | C47: =C27+C32+C37+C42 -> 114.066 | D47: =D27+D32+D37+D42 -> 109.734 | E47: =E27+E32+E37+E42 -> 111.982 | F47: =F27+F32+F37+F42 -> 423.796 | G47: =G27+G32+G37+G42 -> 106.311 | H47: =H27+H32+H37+H42 -> 127.023 | I47: =I27+I32+I37+I42 -> 120.944 | J47: ='Income Statement'!J47 -> 127.338 | K47: =K27+K32+K37+K42 -> 487.71 | L47: ='Income Statement'!L47 -> 116.961 | M47: ='Income Statement'!M47 -> 142.145 | N47: ='Income Statement'!N47 -> 146.671 | O47: ='Income Statement'!O47 -> 143.42538 | P47: =P27+P32+P37+P42 -> 548.80538 | Q47: ='Income Statement'!Q47 -> 136.10268 | R47: ='Income Statement'!R47 -> 168.85347 | S47: ='Income Statement'!S47 -> 163.08382 | T47: ='Income Statement'!T47 -> 165.54414 | U47: =U27+U32+U37+U42 -> 633.58411 | V47: ='Income Statement'!V47 -> 155.82099 | W47: ='Income Statement'!W47 -> 190.13592 | X47: ='Income Statement'!X47 -> 183.21687 | Y47: ='Income Statement'!Y47 -> 185.6398 | Z47: =Z27+Z32+Z37+Z42 -> 714.81358 | AA47: ='Income Statement'!AA47 -> 173.16335 | AB47: ='Income Statement'!AB47 -> 208.95479 | AC47: ='Income Statement'!AC47 -> 201.20623 | AD47: ='Income Statement'!AD47 -> 202.90297 | AE47: =AE27+AE32+AE37+AE42 -> 786.22735 | AF47: ='Income Statement'!AF47 -> 198.87423 | AG47: ='Income Statement'!AG47 -> 227.04251 | AH47: ='Income Statement'!AH47 -> 212.35677 | AI47: ='Income Statement'!AI47 -> 215.22749 | AJ47: =AJ27+AJ32+AJ37+AJ42 -> 853.501 | AK47: ='Income Statement'!AK47 -> 215.0893 | AL47: ='Income Statement'!AL47 -> 243.61592 | AM47: ='Income Statement'!AM47 -> 227.7517 | AN47: ='Income Statement'!AN47 -> 230.04622 | AO47: =AO27+AO32+AO37+AO42 -> 916.50313
A50: KPIs:
A51: Franchisee-owned stores:
A52: Stores operated at beginning of period | B52: ='Income Statement'!B132 -> 2176 | C52: ='Income Statement'!C132 -> 2211 | D52: ='Income Statement'!D132 -> 2230 | E52: ='Income Statement'!E132 -> 2254 | F52: ='Income Statement'!F132 -> 2176 | G52: ='Income Statement'!G132 -> 2319 | H52: ='Income Statement'!H132 -> 2341 | I52: ='Income Statement'!I132 -> 2358 | J52: ='Income Statement'!J132 -> 2369 | K52: =F58 -> 2319 | L52: ='Income Statement'!L132 -> 2445 | M52: ='Income Statement'!M132 -> 2461 | N52: ='Income Statement'!N132 -> 2479 | O52: =N58 -> 2514 | P52: =K58 -> 2445 | Q52: =P58 -> 2593 | R52: =Q58 -> 2613 | S52: =R58 -> 2636 | T52: =S58 -> 2664 | U52: =P58 -> 2593 | V52: =U58 -> 2749 | W52: =V58 -> 2776 | X52: =W58 -> 2801 | Y52: =X58 -> 2830 | Z52: =U58 -> 2749 | AA52: =Z58 -> 2915 | AB52: =AA58 -> 2942 | AC52: =AB58 -> 2967 | AD52: =AC58 -> 2996 | AE52: =Z58 -> 2915 | AF52: =AE58 -> 3081 | AG52: =AF58 -> 3106 | AH52: =AG58 -> 3128 | AI52: =AH58 -> 3153 | AJ52: =AE58 -> 3081 | AK52: =AJ58 -> 3236 | AL52: =AK58 -> 3261 | AM52: =AL58 -> 3283 | AN52: =AM58 -> 3308 | AO52: =AJ58 -> 3236
A53: YoY % Change | B53: =IFERROR(B52/#REF!-1,"na") -> na | C53: =IFERROR(C52/#REF!-1,"na") -> na | D53: =IFERROR(D52/#REF!-1,"na") -> na | E53: =IFERROR(E52/#REF!-1,"na") -> na | F53: =IFERROR(F52/#REF!-1,"na") -> na | G53: =IFERROR(G52/B52-1,"na") -> 0.065716912 | H53: =IFERROR(H52/C52-1,"na") -> 0.058796924 | I53: =IFERROR(I52/D52-1,"na") -> 0.057399103 | J53: =IFERROR(J52/E52-1,"na") -> 0.051020408 | K53: =IFERROR(K52/F52-1,"na") -> 0.065716912 | L53: =IFERROR(L52/G52-1,"na") -> 0.054333765 | M53: =IFERROR(M52/H52-1,"na") -> 0.051260145 | N53: =IFERROR(N52/I52-1,"na") -> 0.051314673 | ... AO53: =IFERROR(AO52/AJ52-1,"na") -> 0.050308341
A54: New stores opened | B54: ='Income Statement'!B133 -> 35 | C54: ='Income Statement'!C133 -> 23 | D54: ='Income Statement'!D133 -> 24 | E54: ='Income Statement'!E133 -> 65 | F54: ='Income Statement'!F133 -> 147 | G54: ='Income Statement'!G133 -> 23 | H54: ='Income Statement'!H133 -> 17 | I54: ='Income Statement'!I133 -> 12 | J54: ='Income Statement'!J133 -> 77 | K54: =SUM(G54:J54) -> 129 | L54: ='Income Statement'!L133 -> 16 | M54: ='Income Statement'!M133 -> 20 | N54: ='Income Statement'!N133 -> 29 | O54: 79 | P54: =SUM(L54:O54) -> 144 | Q54: 20 | R54: 23 | S54: 28 | T54: 85 | U54: =SUM(Q54:T54) -> 156 | V54: 27 | W54: 25 | X54: 29 | Y54: 85 | Z54: =SUM(V54:Y54) -> 166 | AA54: 27 | AB54: 25 | AC54: 29 | AD54: 85 | AE54: =SUM(AA54:AD54) -> 166 | AF54: 25 | AG54: 22 | AH54: 25 | AI54: 83 | AJ54: =SUM(AF54:AI54) -> 155 | AK54: 25 | AL54: 22 | AM54: 25 | AN54: 83 | AO54: =SUM(AK54:AN54) -> 155
A55: YoY % Change | B55: =IFERROR(B54/#REF!-1,"na") -> na | C55: =IFERROR(C54/#REF!-1,"na") -> na | D55: =IFERROR(D54/#REF!-1,"na") -> na | E55: =IFERROR(E54/#REF!-1,"na") -> na | F55: =IFERROR(F54/#REF!-1,"na") -> na | G55: =IFERROR(G54/B54-1,"na") -> -0.34285714 | H55: =IFERROR(H54/C54-1,"na") -> -0.26086957 | I55: =IFERROR(I54/D54-1,"na") -> -0.5 | J55: =IFERROR(J54/E54-1,"na") -> 0.18461538 | K55: =IFERROR(K54/F54-1,"na") -> -0.12244898 | L55: =IFERROR(L54/G54-1,"na") -> -0.30434783 | M55: =IFERROR(M54/H54-1,"na") -> 0.17647059 | N55: =IFERROR(N54/I54-1,"na") -> 1.4166667 | ... AO55: =IFERROR(AO54/AJ54-1,"na") -> 0
A56: Stores Sold / Acquired | B56: ='Income Statement'!B135+'Income Statement'!B134 -> 0 | C56: ='Income Statement'!C135+'Income Statement'!C134 -> -4 | D56: ='Income Statement'!D135+'Income Statement'!D134 -> 0 | E56: ='Income Statement'!E135+'Income Statement'!E134 -> 0 | F56: ='Income Statement'!F135+'Income Statement'!F134 -> -4 | G56: ='Income Statement'!G135+'Income Statement'!G134 -> -1 | H56: ='Income Statement'!H135+'Income Statement'!H134 -> 0 | I56: ='Income Statement'!I135+'Income Statement'!I134 -> -1 | J56: ='Income Statement'!J135+'Income Statement'!J134 -> -1 | K56: =SUM(G56:J56) -> -3 | L56: ='Income Statement'!L135+'Income Statement'!L134 -> 0 | M56: ='Income Statement'!M135+'Income Statement'!M134 -> -2 | N56: ='Income Statement'!N135+'Income Statement'!N134 -> 6 | O56: 0 | P56: =SUM(L56:O56) -> 4 | Q56: 0 | R56: 0 | S56: 0 | T56: 0 | U56: =SUM(Q56:T56) -> 0 | V56: 0 | W56: 0 | X56: 0 | Y56: 0 | Z56: =SUM(V56:Y56) -> 0 | AA56: 0 | AB56: 0 | AC56: 0 | AD56: 0 | AE56: =SUM(AA56:AD56) -> 0 | AF56: 0 | AG56: 0 | AH56: 0 | AI56: 0 | AJ56: =SUM(AF56:AI56) -> 0 | AK56: 0 | AL56: 0 | AM56: 0 | AN56: 0 | AO56: =SUM(AK56:AN56) -> 0
A57: YoY % Change | B57: =IFERROR(B56/#REF!-1,"na") -> na | C57: =IFERROR(C56/#REF!-1,"na") -> na | D57: =IFERROR(D56/#REF!-1,"na") -> na | E57: =IFERROR(E56/#REF!-1,"na") -> na | F57: =IFERROR(F56/#REF!-1,"na") -> na | G57: =IFERROR(G56/B56-1,"na") -> na | H57: =IFERROR(H56/C56-1,"na") -> -1 | I57: =IFERROR(I56/D56-1,"na") -> na | J57: =IFERROR(J56/E56-1,"na") -> na | K57: =IFERROR(K56/F56-1,"na") -> -0.25 | L57: =IFERROR(L56/G56-1,"na") -> -1 | M57: =IFERROR(M56/H56-1,"na") -> na | N57: =IFERROR(N56/I56-1,"na") -> -7 | ... AO57: =IFERROR(AO56/AJ56-1,"na") -> na
A58: Stores operated at end of period | B58: =B52+B54+B56 -> 2211 | C58: =C52+C54+C56 -> 2230 | D58: =D52+D54+D56 -> 2254 | E58: =E52+E54+E56 -> 2319 | F58: =F52+F54+F56 -> 2319 | G58: =G52+G54+G56 -> 2341 | H58: =H52+H54+H56 -> 2358 | I58: =I52+I54+I56 -> 2369 | ... AO58: =AO52+AO54+AO56 -> 3391
A59: YoY % Change | B59: =IFERROR(B58/#REF!-1,"na") -> na | C59: =IFERROR(C58/#REF!-1,"na") -> na | D59: =IFERROR(D58/#REF!-1,"na") -> na | E59: =IFERROR(E58/#REF!-1,"na") -> na | F59: =IFERROR(F58/#REF!-1,"na") -> na | G59: =IFERROR(G58/B58-1,"na") -> 0.058796924 | H59: =IFERROR(H58/C58-1,"na") -> 0.057399103 | I59: =IFERROR(I58/D58-1,"na") -> 0.051020408 | J59: =IFERROR(J58/E58-1,"na") -> 0.054333765 | K59: =IFERROR(K58/F58-1,"na") -> 0.054333765 | L59: =IFERROR(L58/G58-1,"na") -> 0.051260145 | M59: =IFERROR(M58/H58-1,"na") -> 0.051314673 | N59: =IFERROR(N58/I58-1,"na") -> 0.06120726 | ... AO59: =IFERROR(AO58/AJ58-1,"na") -> 0.04789864
A60: Same Store Sales | B60: 0.097 | C60: 0.086 | D60: 0.082 | E60: =(F60*4)-D60-C60-B60 -> 0.075 | F60: 0.085 | G60: 0.063 | H60: 0.043 | I60: 0.045 | J60: =(K60*4)-I60-H60-G60 -> 0.057 | K60: 0.052 | L60: 0.062 | M60: 0.083 | N60: 0.071 | O60: 0.045 | P60: =AVERAGE(L60:O60) -> 0.06525 | Q60: 0.06 | R60: 0.06 | S60: 0.06 | T60: 0.06 | U60: =AVERAGE(Q60:T60) -> 0.06 | V60: 0.05 | W60: 0.05 | X60: 0.05 | Y60: 0.05 | Z60: =AVERAGE(V60:Y60) -> 0.05 | AA60: 0.045 | AB60: 0.045 | AC60: 0.045 | AD60: 0.045 | AE60: =AVERAGE(AA60:AD60) -> 0.045 | AF60: 0.035 | AG60: 0.035 | AH60: 0.035 | AI60: 0.035 | AJ60: =AVERAGE(AF60:AI60) -> 0.035 | AK60: 0.035 | AL60: 0.035 | AM60: 0.035 | AN60: 0.035 | AO60: =AVERAGE(AK60:AN60) -> 0.035
A61: Average Revenue Per Store | B61: =B10/AVERAGE(B58,B52) -> 0.04225302 | C61: =C10/AVERAGE(C58,C52) -> 0.044513398 | D61: =D10/AVERAGE(D58,D52) -> 0.043784567 | E61: =E10/AVERAGE(E58,E52) -> 0.042965231 | F61: =F10/AVERAGE(F58,F52) -> 0.17260467 | G61: =G10/AVERAGE(G58,G52) -> 0.044643777 | H61: =H10/AVERAGE(H58,H52) -> 0.045877846 | I61: =I10/AVERAGE(I58,I52) -> 0.043331923 | ... N61: =N10/AVERAGE(N58,N52) -> 0.045533747 | O61: =J61*(1+O60+O63) -> 0.046879007 | P61: =P10/AVERAGE(P58,P52) -> 0.18587477 | Q61: =L61*(1+Q60+Q63) -> 0.054232735 | R61: =M61*(1+R60+R63) -> 0.055953437 | S61: =N61*(1+S60+S63) -> 0.052363809 | T61: =O61*(1+T60+T63) -> 0.053910858 | U61: =U10/AVERAGE(U58,U52) -> 0.21441087 | V61: =Q61*(1+V60+V63) -> 0.0574867 | W61: =R61*(1+W60+W63) -> 0.059310643 | X61: =S61*(1+X60+X63) -> 0.054982 | Y61: =T61*(1+Y60+Y63) -> 0.056606401 | Z61: =Z10/AVERAGE(Z58,Z52) -> 0.22655312 | AA61: =V61*(1+AA60+AA63) -> 0.060073601 | AB61: =W61*(1+AB60+AB63) -> 0.061979622 | AC61: =X61*(1+AC60+AC63) -> 0.05745619 | AD61: =Y61*(1+AD60+AD63) -> 0.059153689 | AE61: =AE10/AVERAGE(AE58,AE52) -> 0.23685405 | AF61: =AA61*(1+AF60+AF63) -> 0.062176177 | AG61: =AB61*(1+AG60+AG63) -> 0.064148909 | AH61: =AC61*(1+AH60+AH63) -> 0.059467156 | AI61: =AD61*(1+AI60+AI63) -> 0.061224068 | AJ61: =AJ10/AVERAGE(AJ58,AJ52) -> 0.24525282 | AK61: =AF61*(1+AK60+AK63) -> 0.064352343 | AL61: =AG61*(1+AL60+AL63) -> 0.066394121 | AM61: =AH61*(1+AM60+AM63) -> 0.061548507 | AN61: =AI61*(1+AN60+AN63) -> 0.063366911 | AO61: =AO10/AVERAGE(AO58,AO52) -> 0.25392205
A62: YoY % Change | B62: =IFERROR(B61/#REF!-1,"na") -> na | C62: =IFERROR(C61/#REF!-1,"na") -> na | D62: =IFERROR(D61/#REF!-1,"na") -> na | E62: =IFERROR(E61/#REF!-1,"na") -> na | F62: =IFERROR(F61/#REF!-1,"na") -> na | G62: =IFERROR(G61/B61-1,"na") -> 0.056581909 | H62: =IFERROR(H61/C61-1,"na") -> 0.030652535 | I62: =IFERROR(I61/D61-1,"na") -> -0.010337989 | J62: =IFERROR(J61/E61-1,"na") -> 0.054194889 | K62: =IFERROR(K61/F61-1,"na") -> 0.029436553 | L62: =IFERROR(L61/G61-1,"na") -> 0.051764717 | M62: =IFERROR(M61/H61-1,"na") -> 0.055946132 | N62: =IFERROR(N61/I61-1,"na") -> 0.050812983 | ... AO62: =IFERROR(AO61/AJ61-1,"na") -> 0.035348131
A63: Diff Btw SSS | G63: =G62-G60 -> -0.0064180913 | H63: =H62-H60 -> -0.012347465 | I63: =I62-I60 -> -0.055337989 | J63: =J62-J60 -> -0.0028051105 | K63: =AVERAGE(G63:J63) -> -0.019227164 | L63: =L62-L60 -> -0.010235283 | M63: =M62-M60 -> -0.027053868 | N63: =N62-N60 -> -0.020187017 | O63: -0.01 | P63: =AVERAGE(L63:O63) -> -0.016869042 | Q63: 0.095 | R63: 0.095 | S63: 0.09 | T63: 0.09 | U63: =AVERAGE(Q63:T63) -> 0.0925 | V63: 0.01 | W63: 0.01 | X63: 0 | Y63: 0 | Z63: =AVERAGE(V63:Y63) -> 0.005 | AA63: 0 | AB63: 0 | AC63: 0 | AD63: 0 | AE63: =AVERAGE(AA63:AD63) -> 0 | AF63: 0 | AG63: 0 | AH63: 0 | AI63: 0 | AJ63: =AVERAGE(AF63:AI63) -> 0 | AK63: 0 | AL63: 0 | AM63: 0 | AN63: 0 | AO63: =AVERAGE(AK63:AN63) -> 0
A65: Corporate-owned stores:
A66: Stores operated at beginning of period | B66: ='Income Statement'!B138 -> 212 | C66: ='Income Statement'!C138 -> 213 | D66: ='Income Statement'!D138 -> 220 | E66: ='Income Statement'!E138 -> 222 | F66: ='Income Statement'!F138 -> 234 | G66: ='Income Statement'!G138 -> 256 | H66: ='Income Statement'!H138 -> 258 | I66: ='Income Statement'!I138 -> 259 | J66: ='Income Statement'!J138 -> 268 | K66: =F72 -> 256 | L66: ='Income Statement'!L138 -> 277 | M66: ='Income Statement'!M138 -> 280 | N66: ='Income Statement'!N138 -> 283 | O66: =N72 -> 281 | P66: =K72 -> 277 | Q66: =P72 -> 290 | R66: =Q72 -> 290 | S66: =R72 -> 293 | T66: =S72 -> 297 | U66: =P72 -> 290 | V66: =U72 -> 306 | W66: =V72 -> 309 | X66: =W72 -> 313 | Y66: =X72 -> 319 | Z66: =U72 -> 306 | AA66: =Z72 -> 328 | AB66: =AA72 -> 331 | AC66: =AB72 -> 335 | AD66: =AC72 -> 341 | AE66: =Z72 -> 328 | AF66: =AE72 -> 350 | AG66: =AF72 -> 353 | AH66: =AG72 -> 356 | AI66: =AH72 -> 361 | AJ66: =AE72 -> 350 | AK66: =AJ72 -> 368 | AL66: =AK72 -> 371 | AM66: =AL72 -> 374 | AN66: =AM72 -> 379 | AO66: =AJ72 -> 368
A67: YoY % Change | B67: =IFERROR(B66/#REF!-1,"na") -> na | C67: =IFERROR(C66/#REF!-1,"na") -> na | D67: =IFERROR(D66/#REF!-1,"na") -> na | E67: =IFERROR(E66/#REF!-1,"na") -> na | F67: =IFERROR(F66/#REF!-1,"na") -> na | G67: =IFERROR(G66/B66-1,"na") -> 0.20754717 | H67: =IFERROR(H66/C66-1,"na") -> 0.21126761 | I67: =IFERROR(I66/D66-1,"na") -> 0.17727273 | J67: =IFERROR(J66/E66-1,"na") -> 0.20720721 | K67: =IFERROR(K66/F66-1,"na") -> 0.094017094 | L67: =IFERROR(L66/G66-1,"na") -> 0.08203125 | M67: =IFERROR(M66/H66-1,"na") -> 0.085271318 | N67: =IFERROR(N66/I66-1,"na") -> 0.092664093 | ... AO67: =IFERROR(AO66/AJ66-1,"na") -> 0.051428571
A68: New stores opened | B68: ='Income Statement'!B139 -> 1 | C68: ='Income Statement'!C139 -> 3 | D68: ='Income Statement'!D139 -> 2 | E68: ='Income Statement'!E139 -> 12 | F68: ='Income Statement'!F139 -> 18 | G68: ='Income Statement'!G139 -> 2 | H68: ='Income Statement'!H139 -> 1 | I68: ='Income Statement'!I139 -> 9 | J68: ='Income Statement'!J139 -> 9 | K68: =SUM(G68:J68) -> 21 | L68: ='Income Statement'!L139 -> 3 | M68: ='Income Statement'!M139 -> 3 | N68: ='Income Statement'!N139 -> 6 | O68: 9 | P68: =SUM(L68:O68) -> 21 | Q68: 0 | R68: 3 | S68: 4 | T68: 9 | U68: =SUM(Q68:T68) -> 16 | V68: 3 | W68: 4 | X68: 6 | Y68: 9 | Z68: =SUM(V68:Y68) -> 22 | AA68: 3 | AB68: 4 | AC68: 6 | AD68: 9 | AE68: =SUM(AA68:AD68) -> 22 | AF68: 3 | AG68: 3 | AH68: 5 | AI68: 7 | AJ68: =SUM(AF68:AI68) -> 18 | AK68: 3 | AL68: 3 | AM68: 5 | AN68: 7 | AO68: =SUM(AK68:AN68) -> 18
A69: YoY % Change | B69: =IFERROR(B68/#REF!-1,"na") -> na | C69: =IFERROR(C68/#REF!-1,"na") -> na | D69: =IFERROR(D68/#REF!-1,"na") -> na | E69: =IFERROR(E68/#REF!-1,"na") -> na | F69: =IFERROR(F68/#REF!-1,"na") -> na | G69: =IFERROR(G68/B68-1,"na") -> 1 | H69: =IFERROR(H68/C68-1,"na") -> -0.66666667 | I69: =IFERROR(I68/D68-1,"na") -> 3.5 | J69: =IFERROR(J68/E68-1,"na") -> -0.25 | K69: =IFERROR(K68/F68-1,"na") -> 0.16666667 | L69: =IFERROR(L68/G68-1,"na") -> 0.5 | M69: =IFERROR(M68/H68-1,"na") -> 2 | N69: =IFERROR(N68/I68-1,"na") -> -0.33333333 | ... AO69: =IFERROR(AO68/AJ68-1,"na") -> 0
A70: Stores sold/acquired | B70: ='Income Statement'!B140+'Income Statement'!B141 -> 0 | C70: ='Income Statement'!C140+'Income Statement'!C141 -> 4 | D70: ='Income Statement'!D140+'Income Statement'!D141 -> 0 | E70: ='Income Statement'!E140+'Income Statement'!E141 -> 0 | F70: ='Income Statement'!F140+'Income Statement'!F141 -> 4 | G70: ='Income Statement'!G140+'Income Statement'!G141 -> 0 | H70: ='Income Statement'!H140+'Income Statement'!H141 -> 0 | I70: ='Income Statement'!I140+'Income Statement'!I141 -> 0 | J70: ='Income Statement'!J140+'Income Statement'!J141 -> 0 | K70: =SUM(G70:J70) -> 0 | L70: ='Income Statement'!L140+'Income Statement'!L141 -> 0 | M70: ='Income Statement'!M140+'Income Statement'!M141 -> 0 | N70: ='Income Statement'!N140+'Income Statement'!N141 -> -8 | O70: 0 | P70: =SUM(L70:O70) -> -8 | Q70: 0 | R70: 0 | S70: 0 | T70: 0 | U70: =SUM(Q70:T70) -> 0 | V70: 0 | W70: 0 | X70: 0 | Y70: 0 | Z70: =SUM(V70:Y70) -> 0 | AA70: 0 | AB70: 0 | AC70: 0 | AD70: 0 | AE70: =SUM(AA70:AD70) -> 0 | AF70: 0 | AG70: 0 | AH70: 0 | AI70: 0 | AJ70: =SUM(AF70:AI70) -> 0 | AK70: 0 | AL70: 0 | AM70: 0 | AN70: 0 | AO70: =SUM(AK70:AN70) -> 0
A71: YoY % Change | B71: =IFERROR(B70/#REF!-1,"na") -> na | C71: =IFERROR(C70/#REF!-1,"na") -> na | D71: =IFERROR(D70/#REF!-1,"na") -> na | E71: =IFERROR(E70/#REF!-1,"na") -> na | F71: =IFERROR(F70/#REF!-1,"na") -> na | G71: =IFERROR(G70/B70-1,"na") -> na | H71: =IFERROR(H70/C70-1,"na") -> -1 | I71: =IFERROR(I70/D70-1,"na") -> na | J71: =IFERROR(J70/E70-1,"na") -> na | K71: =IFERROR(K70/F70-1,"na") -> -1 | L71: =IFERROR(L70/G70-1,"na") -> na | M71: =IFERROR(M70/H70-1,"na") -> na | N71: =IFERROR(N70/I70-1,"na") -> na | ... AO71: =IFERROR(AO70/AJ70-1,"na") -> na
A72: Stores operated at end of period | B72: =B66+B68+B70 -> 213 | C72: =C66+C68+C70 -> 220 | D72: =D66+D68+D70 -> 222 | E72: =E66+E68+E70 -> 234 | F72: =F66+F68+F70 -> 256 | G72: =G66+G68+G70 -> 258 | H72: =H66+H68+H70 -> 259 | I72: =I66+I68+I70 -> 268 | ... AO72: =AO66+AO68+AO70 -> 386
A73: YoY % Change | B73: =IFERROR(B72/#REF!-1,"na") -> na | C73: =IFERROR(C72/#REF!-1,"na") -> na | D73: =IFERROR(D72/#REF!-1,"na") -> na | E73: =IFERROR(E72/#REF!-1,"na") -> na | F73: =IFERROR(F72/#REF!-1,"na") -> na | G73: =IFERROR(G72/B72-1,"na") -> 0.21126761 | H73: =IFERROR(H72/C72-1,"na") -> 0.17727273 | I73: =IFERROR(I72/D72-1,"na") -> 0.20720721 | J73: =IFERROR(J72/E72-1,"na") -> 0.18376068 | K73: =IFERROR(K72/F72-1,"na") -> 0.08203125 | L73: =IFERROR(L72/G72-1,"na") -> 0.085271318 | M73: =IFERROR(M72/H72-1,"na") -> 0.092664093 | N73: =IFERROR(N72/I72-1,"na") -> 0.048507463 | ... AO73: =IFERROR(AO72/AJ72-1,"na") -> 0.048913043
A74: Same Store Sales | B74: 0.121 | C74: 0.102 | D74: 0.101 | E74: =(F74*4)-D74-C74-B74 -> 0.08 | F74: 0.101 | G74: 0.062 | H74: 0.04 | I74: 0.034 | J74: =(K74*4)-I74-H74-G74 -> 0.044 | K74: 0.045 | L74: 0.051 | M74: 0.07 | N74: 0.06 | O74: 0.04 | P74: =AVERAGE(L74:O74) -> 0.05525 | Q74: 0.05 | R74: 0.05 | S74: 0.05 | T74: 0.05 | U74: =AVERAGE(Q74:T74) -> 0.05 | V74: 0.045 | W74: 0.045 | X74: 0.045 | Y74: 0.045 | Z74: =AVERAGE(V74:Y74) -> 0.045 | AA74: 0.035 | AB74: 0.035 | AC74: 0.035 | AD74: 0.035 | AE74: =AVERAGE(AA74:AD74) -> 0.035 | AF74: 0.035 | AG74: 0.035 | AH74: 0.035 | AI74: 0.035 | AJ74: =AVERAGE(AF74:AI74) -> 0.035 | AK74: 0.025 | AL74: 0.025 | AM74: 0.025 | AN74: 0.025 | AO74: =AVERAGE(AK74:AN74) -> 0.025
A75: Average Revenue Per Store | B75: =B14/AVERAGE(B72,B66) -> 0.49826824 | C75: =C14/AVERAGE(C72,C66) -> 0.52544573 | D75: =D14/AVERAGE(D72,D66) -> 0.51242081 | E75: =E14/AVERAGE(E72,E66) -> 0.51057018 | F75: =F14/AVERAGE(F72,F66) -> 1.8338612 | G75: =G14/AVERAGE(G72,G66) -> 0.47617899 | H75: =H14/AVERAGE(H72,H66) -> 0.4853617 | I75: =I14/AVERAGE(I72,I66) -> 0.48626945 | ... N75: =N14/AVERAGE(N72,N66) -> 0.4887695 | O75: =J75*(1+O74+O77) -> 0.4774324 | P75: =P14/AVERAGE(P72,P66) -> 1.9287406 | Q75: =L75*(1+Q74+Q77) -> 0.50395853 | R75: =M75*(1+R74+R77) -> 0.51843144 | S75: =N75*(1+S74+S77) -> 0.51320798 | T75: =O75*(1+T74+T77) -> 0.50130402 | U75: =U14/AVERAGE(U72,U66) -> 2.0127861 | V75: =Q75*(1+V74+V77) -> 0.52663666 | W75: =R75*(1+W74+W77) -> 0.54176085 | X75: =S75*(1+X74+X77) -> 0.53630234 | Y75: =T75*(1+Y74+Y77) -> 0.5238627 | Z75: =Z14/AVERAGE(Z72,Z66) -> 2.1115758 | AA75: =V75*(1+AA74+AA77) -> 0.54506894 | AB75: =W75*(1+AB74+AB77) -> 0.56072248 | AC75: =X75*(1+AC74+AC77) -> 0.55507292 | AD75: =Y75*(1+AD74+AD77) -> 0.5421979 | AE75: =AE14/AVERAGE(AE72,AE66) -> 2.1866219 | AF75: =AA75*(1+AF74+AF77) -> 0.56414636 | AG75: =AB75*(1+AG74+AG77) -> 0.58034777 | AH75: =AC75*(1+AH74+AH77) -> 0.57450047 | AI75: =AD75*(1+AI74+AI77) -> 0.56117483 | AJ75: =AJ14/AVERAGE(AJ72,AJ66) -> 2.2689063 | AK75: =AF75*(1+AK74+AK77) -> 0.57825002 | AL75: =AG75*(1+AL74+AL77) -> 0.59485646 | AM75: =AH75*(1+AM74+AM77) -> 0.58886298 | AN75: =AI75*(1+AN74+AN77) -> 0.5752042 | AO75: =AO14/AVERAGE(AO72,AO66) -> 2.3261802
A76: YoY % Change | B76: =IFERROR(B75/#REF!-1,"na") -> na | C76: =IFERROR(C75/#REF!-1,"na") -> na | D76: =IFERROR(D75/#REF!-1,"na") -> na | E76: =IFERROR(E75/#REF!-1,"na") -> na | F76: =IFERROR(F75/#REF!-1,"na") -> na | G76: =IFERROR(G75/B75-1,"na") -> -0.044332039 | H76: =IFERROR(H75/C75-1,"na") -> -0.076285758 | I76: =IFERROR(I75/D75-1,"na") -> -0.051034939 | J76: =IFERROR(J75/E75-1,"na") -> -0.092139283 | K76: =IFERROR(K75/F75-1,"na") -> 0.027751826 | L76: =IFERROR(L75/G75-1,"na") -> 0.0079413718 | M76: =IFERROR(M75/H75-1,"na") -> 0.017270677 | N76: =IFERROR(N75/I75-1,"na") -> 0.0051412932 | ... AO76: =IFERROR(AO75/AJ75-1,"na") -> 0.025242938
A77: Diff Btw SSS | G77: =G76-G74 -> -0.10633204 | H77: =H76-H74 -> -0.11628576 | I77: =I76-I74 -> -0.085034939 | J77: =J76-J74 -> -0.13613928 | K77: =AVERAGE(G77:J77) -> -0.110948 | L77: =L76-L74 -> -0.043058628 | M77: =M76-M74 -> -0.052729323 | N77: =N76-N74 -> -0.054858707 | O77: -0.01 | P77: =AVERAGE(L77:O77) -> -0.040161664 | Q77: 0 | R77: =Q77 -> 0 | S77: =R77 -> 0 | T77: =S77 -> 0 | U77: =AVERAGE(Q77:T77) -> 0 | V77: =T77 -> 0 | W77: =V77 -> 0 | X77: =W77 -> 0 | Y77: =X77 -> 0 | Z77: =AVERAGE(V77:Y77) -> 0 | AA77: =Y77 -> 0 | AB77: =AA77 -> 0 | AC77: =AB77 -> 0 | AD77: =AC77 -> 0 | AE77: =AVERAGE(AA77:AD77) -> 0 | AF77: =AD77 -> 0 | AG77: =AF77 -> 0 | AH77: =AG77 -> 0 | AI77: =AH77 -> 0 | AJ77: =AVERAGE(AF77:AI77) -> 0 | AK77: =AI77 -> 0 | AL77: =AK77 -> 0 | AM77: =AL77 -> 0 | AN77: =AM77 -> 0 | AO77: =AVERAGE(AK77:AN77) -> 0
A79: Total stores:
A80: Stores operated at beginning of period | B80: ='Income Statement'!B144 -> 2410 | C80: ='Income Statement'!C144 -> 2446 | D80: ='Income Statement'!D144 -> 2472 | E80: ='Income Statement'!E144 -> 2498 | F80: ='Income Statement'!F144 -> 2410 | G80: ='Income Statement'!G144 -> 2575 | H80: ='Income Statement'!H144 -> 2599 | I80: ='Income Statement'!I144 -> 2617 | J80: ='Income Statement'!J144 -> 2637 | K80: =F86 -> 2575 | L80: =K86 -> 2722 | M80: ='Income Statement'!M144 -> 2741 | N80: ='Income Statement'!N144 -> 2762 | O80: =N86 -> 2795 | P80: =K86 -> 2722 | Q80: =P86 -> 2883 | R80: =Q86 -> 2903 | S80: =R86 -> 2929 | T80: =S86 -> 2961 | U80: =P86 -> 2883 | V80: =U86 -> 3055 | W80: =V86 -> 3085 | X80: =W86 -> 3114 | Y80: =X86 -> 3149 | Z80: =U86 -> 3055 | AA80: =Z86 -> 3243 | AB80: =AA86 -> 3273 | AC80: =AB86 -> 3302 | AD80: =AC86 -> 3337 | AE80: =Z86 -> 3243 | AF80: =AE86 -> 3431 | AG80: =AF86 -> 3459 | AH80: =AG86 -> 3484 | AI80: =AH86 -> 3514 | AJ80: =AE86 -> 3431 | AK80: =AJ86 -> 3604 | AL80: =AK86 -> 3632 | AM80: =AL86 -> 3657 | AN80: =AM86 -> 3687 | AO80: =AJ86 -> 3604
A81: YoY % Change | B81: =IFERROR(B80/#REF!-1,"na") -> na | C81: =IFERROR(C80/#REF!-1,"na") -> na | D81: =IFERROR(D80/#REF!-1,"na") -> na | E81: =IFERROR(E80/#REF!-1,"na") -> na | F81: =IFERROR(F80/#REF!-1,"na") -> na | G81: =IFERROR(G80/B80-1,"na") -> 0.06846473 | H81: =IFERROR(H80/C80-1,"na") -> 0.062551104 | I81: =IFERROR(I80/D80-1,"na") -> 0.058656958 | J81: =IFERROR(J80/E80-1,"na") -> 0.055644516 | K81: =IFERROR(K80/F80-1,"na") -> 0.06846473 | L81: =IFERROR(L80/G80-1,"na") -> 0.057087379 | M81: =IFERROR(M80/H80-1,"na") -> 0.054636399 | N81: =IFERROR(N80/I80-1,"na") -> 0.055406955 | ... AO81: =IFERROR(AO80/AJ80-1,"na") -> 0.050422617
A82: New stores opened | B82: ='Income Statement'!B145 -> 36 | C82: ='Income Statement'!C145 -> 26 | D82: ='Income Statement'!D145 -> 26 | E82: ='Income Statement'!E145 -> 77 | F82: ='Income Statement'!F145 -> 165 | G82: ='Income Statement'!G145 -> 25 | H82: ='Income Statement'!H145 -> 18 | I82: ='Income Statement'!I145 -> 21 | J82: ='Income Statement'!J145 -> 86 | K82: =SUM(G82:J82) -> 150 | L82: =L68+L54 -> 19 | M82: ='Income Statement'!M145 -> 23 | N82: ='Income Statement'!N145 -> 35 | O82: =O68+O54 -> 88 | P82: =SUM(L82:O82) -> 165 | Q82: =Q68+Q54 -> 20 | R82: =R68+R54 -> 26 | S82: =S68+S54 -> 32 | T82: =T68+T54 -> 94 | U82: =SUM(Q82:T82) -> 172 | V82: =V68+V54 -> 30 | W82: =W68+W54 -> 29 | X82: =X68+X54 -> 35 | Y82: =Y68+Y54 -> 94 | Z82: =SUM(V82:Y82) -> 188 | AA82: =AA68+AA54 -> 30 | AB82: =AB68+AB54 -> 29 | AC82: =AC68+AC54 -> 35 | AD82: =AD68+AD54 -> 94 | AE82: =SUM(AA82:AD82) -> 188 | AF82: =AF68+AF54 -> 28 | AG82: =AG68+AG54 -> 25 | AH82: =AH68+AH54 -> 30 | AI82: =AI68+AI54 -> 90 | AJ82: =SUM(AF82:AI82) -> 173 | AK82: =AK68+AK54 -> 28 | AL82: =AL68+AL54 -> 25 | AM82: =AM68+AM54 -> 30 | AN82: =AN68+AN54 -> 90 | AO82: =SUM(AK82:AN82) -> 173
A83: YoY % Change | B83: =IFERROR(B82/#REF!-1,"na") -> na | C83: =IFERROR(C82/#REF!-1,"na") -> na | D83: =IFERROR(D82/#REF!-1,"na") -> na | E83: =IFERROR(E82/#REF!-1,"na") -> na | F83: =IFERROR(F82/#REF!-1,"na") -> na | G83: =IFERROR(G82/B82-1,"na") -> -0.30555556 | H83: =IFERROR(H82/C82-1,"na") -> -0.30769231 | I83: =IFERROR(I82/D82-1,"na") -> -0.19230769 | J83: =IFERROR(J82/E82-1,"na") -> 0.11688312 | K83: =IFERROR(K82/F82-1,"na") -> -0.090909091 | L83: =IFERROR(L82/G82-1,"na") -> -0.24 | M83: =IFERROR(M82/H82-1,"na") -> 0.27777778 | N83: =IFERROR(N82/I82-1,"na") -> 0.66666667 | ... AO83: =IFERROR(AO82/AJ82-1,"na") -> 0 | AS83: =K86 -> 2722 | AU83: =Z86 -> 3243
A84: Stores debranded, sold, closed or consolidated | B84: ='Income Statement'!B146 -> 0 | C84: ='Income Statement'!C146 -> 0 | D84: ='Income Statement'!D146 -> 0 | E84: ='Income Statement'!E146 -> 0 | F84: ='Income Statement'!F146 -> 0 | G84: ='Income Statement'!G146 -> -1 | H84: ='Income Statement'!H146 -> 0 | I84: ='Income Statement'!I146 -> -1 | J84: ='Income Statement'!J146 -> -1 | K84: =SUM(G84:J84) -> -3 | L84: =L56+L70 -> 0 | M84: ='Income Statement'!M146 -> -2 | N84: ='Income Statement'!N146 -> -2 | O84: =O56+O70 -> 0 | P84: =SUM(L84:O84) -> -4 | Q84: =Q56+Q70 -> 0 | R84: =R56+R70 -> 0 | S84: =S56+S70 -> 0 | T84: =T56+T70 -> 0 | U84: =SUM(Q84:T84) -> 0 | V84: =V56+V70 -> 0 | W84: =W56+W70 -> 0 | X84: =X56+X70 -> 0 | Y84: =Y56+Y70 -> 0 | Z84: =SUM(V84:Y84) -> 0 | AA84: =AA56+AA70 -> 0 | AB84: =AB56+AB70 -> 0 | AC84: =AC56+AC70 -> 0 | AD84: =AD56+AD70 -> 0 | AE84: =SUM(AA84:AD84) -> 0 | AF84: =AF56+AF70 -> 0 | AG84: =AG56+AG70 -> 0 | AH84: =AH56+AH70 -> 0 | AI84: =AI56+AI70 -> 0 | AJ84: =SUM(AF84:AI84) -> 0 | AK84: =AK56+AK70 -> 0 | AL84: =AL56+AL70 -> 0 | AM84: =AM56+AM70 -> 0 | AN84: =AN56+AN70 -> 0 | AO84: =SUM(AK84:AN84) -> 0 | AU84: =AU83-AS83 -> 521
A85: YoY % Change | B85: =IFERROR(B84/#REF!-1,"na") -> na | C85: =IFERROR(C84/#REF!-1,"na") -> na | D85: =IFERROR(D84/#REF!-1,"na") -> na | E85: =IFERROR(E84/#REF!-1,"na") -> na | F85: =IFERROR(F84/#REF!-1,"na") -> na | G85: =IFERROR(G84/B84-1,"na") -> na | H85: =IFERROR(H84/C84-1,"na") -> na | I85: =IFERROR(I84/D84-1,"na") -> na | J85: =IFERROR(J84/E84-1,"na") -> na | K85: =IFERROR(K84/F84-1,"na") -> na | L85: =IFERROR(L84/G84-1,"na") -> -1 | M85: =IFERROR(M84/H84-1,"na") -> na | N85: =IFERROR(N84/I84-1,"na") -> 1 | ... AO85: =IFERROR(AO84/AJ84-1,"na") -> na
A86: Stores operated at end of period | B86: =B80+B82+B84 -> 2446 | C86: =C80+C82+C84 -> 2472 | D86: =D80+D82+D84 -> 2498 | E86: =E80+E82+E84 -> 2575 | F86: =F80+F82+F84 -> 2575 | G86: =G80+G82+G84 -> 2599 | H86: =H80+H82+H84 -> 2617 | I86: =I80+I82+I84 -> 2637 | ... AO86: =AO80+AO82+AO84 -> 3777
A87: YoY % Change | B87: =IFERROR(B86/#REF!-1,"na") -> na | C87: =IFERROR(C86/#REF!-1,"na") -> na | D87: =IFERROR(D86/#REF!-1,"na") -> na | E87: =IFERROR(E86/#REF!-1,"na") -> na | F87: =IFERROR(F86/#REF!-1,"na") -> na | G87: =IFERROR(G86/B86-1,"na") -> 0.062551104 | H87: =IFERROR(H86/C86-1,"na") -> 0.058656958 | I87: =IFERROR(I86/D86-1,"na") -> 0.055644516 | J87: =IFERROR(J86/E86-1,"na") -> 0.057087379 | K87: =IFERROR(K86/F86-1,"na") -> 0.057087379 | L87: =IFERROR(L86/G86-1,"na") -> 0.054636399 | M87: =IFERROR(M86/H86-1,"na") -> 0.055406955 | N87: =IFERROR(N86/I86-1,"na") -> 0.059916572 | ... AO87: =IFERROR(AO86/AJ86-1,"na") -> 0.04800222
A88: Same Store Sales | B88: 0.099 | C88: 0.087 | D88: 0.084 | E88: =(F88*4)-D88-C88-B88 -> 0.078 | F88: 0.087 | G88: 0.062 | H88: 0.042 | I88: 0.043 | J88: =(K88*4)-I88-H88-G88 -> 0.053 | K88: 0.05 | L88: 0.061 | M88: 0.082 | N88: 0.069 | O88: =(90%*O60)+(10%*O74) -> 0.0445 | P88: =AVERAGE(L88:O88) -> 0.064125 | Q88: =(90%*Q60)+(10%*Q74) -> 0.059 | R88: =(90%*R60)+(10%*R74) -> 0.059 | S88: =(90%*S60)+(10%*S74) -> 0.059 | T88: =(90%*T60)+(10%*T74) -> 0.059 | U88: =AVERAGE(Q88:T88) -> 0.059 | V88: =(90%*V60)+(10%*V74) -> 0.0495 | W88: =(90%*W60)+(10%*W74) -> 0.0495 | X88: =(90%*X60)+(10%*X74) -> 0.0495 | Y88: =(90%*Y60)+(10%*Y74) -> 0.0495 | Z88: =AVERAGE(V88:Y88) -> 0.0495 | AA88: =(90%*AA60)+(10%*AA74) -> 0.044 | AB88: =(90%*AB60)+(10%*AB74) -> 0.044 | AC88: =(90%*AC60)+(10%*AC74) -> 0.044 | AD88: =(90%*AD60)+(10%*AD74) -> 0.044 | AE88: =AVERAGE(AA88:AD88) -> 0.044 | AF88: =(90%*AF60)+(10%*AF74) -> 0.035 | AG88: =(90%*AG60)+(10%*AG74) -> 0.035 | AH88: =(90%*AH60)+(10%*AH74) -> 0.035 | AI88: =(90%*AI60)+(10%*AI74) -> 0.035 | AJ88: =AVERAGE(AF88:AI88) -> 0.035 | AK88: =(90%*AK60)+(10%*AK74) -> 0.034 | AL88: =(90%*AL60)+(10%*AL74) -> 0.034 | AM88: =(90%*AM60)+(10%*AM74) -> 0.034 | AN88: =(90%*AN60)+(10%*AN74) -> 0.034 | AO88: =AVERAGE(AK88:AN88) -> 0.034
A90: Income Statement
A92: Franchise | B92: ='Income Statement'!B8 -> 75.878 | C92: ='Income Statement'!C8 -> 80.846 | D92: ='Income Statement'!D8 -> 80.587 | E92: ='Income Statement'!E8 -> 80.604 | F92: ='Income Statement'!F8 -> 387.927 | G92: ='Income Statement'!G8 -> 104.02 | H92: ='Income Statement'!H8 -> 107.79 | I92: ='Income Statement'!I8 -> 102.415 | J92: ='Income Statement'!J8 -> 109.022 | K92: =SUM(G92:J92) -> 423.247 | L92: ='Income Statement'!L8 -> 115.18 | M92: ='Income Statement'!M8 -> 119.658 | N92: ='Income Statement'!N8 -> 113.675 | O92: =O$10*O93 -> 96.961491 | P92: =SUM(L92:O92) -> 445.47449 | Q92: =Q$10*Q93 -> 108.69921 | R92: =R$10*R93 -> 113.07434 | S92: =S$10*S93 -> 106.84835 | T92: =T$10*T93 -> 112.3505 | U92: =SUM(Q92:T92) -> 440.97241 | V92: =V$10*V93 -> 122.2814 | W92: =W$10*W93 -> 127.34855 | X92: =X$10*X93 -> 119.1974 | Y92: =Y$10*Y93 -> 125.20345 | Z92: =SUM(V92:Y92) -> 494.0308 | AA92: =AA$10*AA93 -> 135.46267 | AB92: =AB$10*AB93 -> 141.00147 | AC92: =AC$10*AC93 -> 131.90534 | AD92: =AD$10*AD93 -> 138.39863 | AE92: =SUM(AA92:AD92) -> 546.76811 | AF92: =AF$10*AF93 -> 148.10334 | AG92: =AG$10*AG93 -> 153.96316 | AH92: =AH$10*AH93 -> 143.80259 | AI92: =AI$10*AI93 -> 150.59682 | AJ92: =SUM(AF92:AI92) -> 596.4659 | AK92: =AK$10*AK93 -> 160.96741 | AL92: =AL$10*AL93 -> 167.276 | AM92: =AM$10*AM93 -> 156.18149 | AN92: =AN$10*AN93 -> 163.43055 | AO92: =SUM(AK92:AN92) -> 647.85546
A93: As % of Franchise Revenue | B93: =B92/B$10 -> 0.81869187 | C93: =C92/C$10 -> 0.81793165 | D93: =D92/D$10 -> 0.82093414 | E93: =E92/E$10 -> 0.82048046 | F93: =F92/F$10 -> 0.99999484 | G93: =G92/G$10 -> 1 | H93: =H92/H$10 -> 1 | I93: =I92/I$10 -> 1 | ... N93: =N92/N$10 -> 1 | O93: 0.81 | P93: =P92/P$10 -> 0.95142428 | Q93: 0.77 | R93: 0.77 | S93: 0.77 | T93: 0.77 | U93: =U92/U$10 -> 0.77 | V93: 0.77 | W93: 0.77 | X93: 0.77 | Y93: 0.77 | Z93: =Z92/Z$10 -> 0.77 | AA93: 0.77 | AB93: 0.77 | AC93: 0.77 | AD93: 0.77 | AE93: =AE92/AE$10 -> 0.77 | AF93: 0.77 | AG93: 0.77 | AH93: 0.77 | AI93: 0.77 | AJ93: =AJ92/AJ$10 -> 0.77 | AK93: 0.77 | AL93: 0.77 | AM93: 0.77 | AN93: 0.77 | AO93: =AO92/AO$10 -> 0.77
A94: YoY % Change | B94: =IFERROR(B92/#REF!-1,"na") -> na | C94: =IFERROR(C92/#REF!-1,"na") -> na | D94: =IFERROR(D92/#REF!-1,"na") -> na | E94: =IFERROR(E92/#REF!-1,"na") -> na | F94: =IFERROR(F92/#REF!-1,"na") -> na | G94: =IFERROR(G92/B92-1,"na") -> 0.37088484 | H94: =IFERROR(H92/C92-1,"na") -> 0.33327561 | I94: =IFERROR(I92/D92-1,"na") -> 0.27086255 | J94: =IFERROR(J92/E92-1,"na") -> 0.35256315 | K94: =IFERROR(K92/F92-1,"na") -> 0.091048058 | L94: =IFERROR(L92/G92-1,"na") -> 0.10728706 | M94: =IFERROR(M92/H92-1,"na") -> 0.11010298 | N94: =IFERROR(N92/I92-1,"na") -> 0.10994483 | ... AO94: =IFERROR(AO92/AJ92-1,"na") -> 0.086156731
A96: Cost of revenue | B96: ='Income Statement'!B13 -> 19.354 | C96: ='Income Statement'!C13 -> 59.457 | D96: ='Income Statement'!D13 -> 53.751 | E96: ='Income Statement'!E13 -> 57.465 | F96: ='Income Statement'!F13 -> 190.027 | G96: ='Income Statement'!G13 -> 18.993 | H96: ='Income Statement'!H13 -> 51.934 | I96: ='Income Statement'!I13 -> 45.701 | J96: ='Income Statement'!J13 -> 80.494 | K96: =SUM(G96:J96) -> 197.122 | L96: ='Income Statement'!L13 -> 22.485 | M96: ='Income Statement'!M13 -> 59.423 | N96: ='Income Statement'!N13 -> 58.155 | O96: =O$22*O97 -> 85.383339 | P96: =SUM(L96:O96) -> 225.44634 | Q96: =Q$22*Q97 -> 23.908937 | R96: =R$22*R97 -> 65.242854 | S96: =S$22*S97 -> 63.95203 | T96: =T$22*T97 -> 94.611475 | U96: =SUM(Q96:T96) -> 247.7153 | V96: =V$22*V97 -> 24.808601 | W96: =W$22*W97 -> 70.120115 | X96: =X$22*X97 -> 68.623537 | Y96: =Y$22*Y97 -> 102.11649 | Z96: =SUM(V96:Y96) -> 265.66874 | AA96: =AA$22*AA97 -> 27.34329 | AB96: =AB$22*AB97 -> 76.617488 | AC96: =AC$22*AC97 -> 74.945952 | AD96: =AD$22*AD97 -> 111.09612 | AE96: =SUM(AA96:AD96) -> 290.00285 | AF96: =AF$22*AF97 -> 29.869806 | AG96: =AG$22*AG97 -> 82.877324 | AH96: =AH$22*AH97 -> 80.916261 | AI96: =AI$22*AI97 -> 119.25778 | AJ96: =SUM(AF96:AI96) -> 312.92117 | AK96: =AK$22*AK97 -> 32.184086 | AL96: =AL$22*AL97 -> 88.705361 | AM96: =AM$22*AM97 -> 86.571294 | AN96: =AN$22*AN97 -> 127.22838 | AO96: =SUM(AK96:AN96) -> 334.68912
A97: As % of Total Revenue | B97: =B96/B$22 -> 0.087091911 | C97: =C96/C$22 -> 0.2075556 | D97: =D96/D$22 -> 0.19366171 | E97: =E96/E$22 -> 0.20157005 | F97: =F96/F$22 -> 0.17737551 | G97: =G96/G$22 -> 0.076579428 | H97: =H96/H$22 -> 0.17257203 | I97: =I96/I$22 -> 0.15637853 | ... N97: =N96/N$22 -> 0.17604323 | O97: =J97 -> 0.23643413 | P97: =P96/P$22 -> 0.17222587 | Q97: =L97-0.6% -> 0.075272455 | R97: =M97-0.6% -> 0.16832285 | S97: =N97-0.6% -> 0.17004323 | T97: =O97-0.6% -> 0.23043413 | U97: =U96/U$22 -> 0.1660391 | V97: =Q97-0.5% -> 0.070272455 | W97: =R97-0.5% -> 0.16332285 | X97: =S97-0.5% -> 0.16504323 | Y97: =T97-0.5% -> 0.22543413 | Z97: =Z96/Z$22 -> 0.16090046 | AA97: =V97 -> 0.070272455 | AB97: =W97 -> 0.16332285 | AC97: =X97 -> 0.16504323 | AD97: =Y97 -> 0.22543413 | AE97: =AE96/AE$22 -> 0.16065489 | AF97: =AA97 -> 0.070272455 | AG97: =AB97 -> 0.16332285 | AH97: =AC97 -> 0.16504323 | AI97: =AD97 -> 0.22543413 | AJ97: =AJ96/AJ$22 -> 0.16032532 | AK97: =AF97 -> 0.070272455 | AL97: =AG97 -> 0.16332285 | AM97: =AH97 -> 0.16504323 | AN97: =AI97 -> 0.22543413 | AO97: =AO96/AO$22 -> 0.1601363
A98: YoY % Change | B98: =IFERROR(B96/#REF!-1,"na") -> na | C98: =IFERROR(C96/#REF!-1,"na") -> na | D98: =IFERROR(D96/#REF!-1,"na") -> na | E98: =IFERROR(E96/#REF!-1,"na") -> na | F98: =IFERROR(F96/#REF!-1,"na") -> na | G98: =IFERROR(G96/B96-1,"na") -> -0.018652475 | H98: =IFERROR(H96/C96-1,"na") -> -0.12652842 | I98: =IFERROR(I96/D96-1,"na") -> -0.14976466 | J98: =IFERROR(J96/E96-1,"na") -> 0.40074828 | K98: =IFERROR(K96/F96-1,"na") -> 0.0373368 | L98: =IFERROR(L96/G96-1,"na") -> 0.18385721 | M98: =IFERROR(M96/H96-1,"na") -> 0.14420226 | N98: =IFERROR(N96/I96-1,"na") -> 0.27251045 | ... AO98: =IFERROR(AO96/AJ96-1,"na") -> 0.069563702
A100: Store operations | B100: ='Income Statement'!B14 -> 66.015 | C100: ='Income Statement'!C14 -> 58.876 | D100: ='Income Statement'!D14 -> 63.12 | E100: ='Income Statement'!E14 -> 65.608 | F100: ='Income Statement'!F14 -> 253.619 | G100: ='Income Statement'!G14 -> 74.353 | H100: ='Income Statement'!H14 -> 70.152 | I100: ='Income Statement'!I14 -> 71.614 | J100: ='Income Statement'!J14 -> 74.388 | K100: =SUM(G100:J100) -> 290.507 | L100: ='Income Statement'!L14 -> 81.68 | M100: ='Income Statement'!M14 -> 77.437 | N100: ='Income Statement'!N14 -> 79.792 | O100: =O$22*O101 -> 77.642842 | P100: =SUM(L100:O100) -> 316.55184 | Q100: =Q$22*Q101 -> 91.869927 | R100: =R$22*R101 -> 85.726147 | S100: =S$22*S101 -> 88.585427 | T100: =T$22*T101 -> 85.811065 | U100: =SUM(Q100:T100) -> 351.99257 | V100: =V$22*V101 -> 100.34437 | W100: =W$22*W101 -> 94.955275 | X100: =X$22*X101 -> 97.936071 | Y100: =Y$22*Y101 -> 94.672202 | Z100: =SUM(V100:Y100) -> 387.90792 | AA100: =AA$22*AA101 -> 110.59653 | AB100: =AB$22*AB101 -> 103.75389 | AC100: =AC$22*AC101 -> 106.95911 | AD100: =AD$22*AD101 -> 102.99722 | AE100: =SUM(AA100:AD100) -> 424.30674 | AF100: =AF$22*AF101 -> 120.81563 | AG100: =AG$22*AG101 -> 112.23084 | AH100: =AH$22*AH101 -> 115.47963 | AI100: =AI$22*AI101 -> 110.56389 | AJ100: =SUM(AF100:AI100) -> 459.09 | AK100: =AK$22*AK101 -> 130.1763 | AL100: =AL$22*AL101 -> 120.12305 | AM100: =AM$22*AM101 -> 123.55021 | AN100: =AN$22*AN101 -> 117.95344 | AO100: =SUM(AK100:AN100) -> 491.803
A101: As % of Total Revenue | B101: =B100/B$22 -> 0.29706379 | C101: =C100/C$22 -> 0.20552742 | D101: =D100/D$22 -> 0.22741766 | E101: =E100/E$22 -> 0.23013326 | F101: =F100/F$22 -> 0.23673373 | G101: =G100/G$22 -> 0.29978993 | H101: =H100/H$22 -> 0.23310882 | I101: =I100/I$22 -> 0.24504698 | ... N101: =N100/N$22 -> 0.24154142 | O101: 0.215 | P101: =P100/P$22 -> 0.24182437 | Q101: =L101-0.6% -> 0.2892339 | R101: =M101-0.6% -> 0.22116858 | S101: =N101-0.6% -> 0.23554142 | T101: =O101-0.6% -> 0.209 | U101: =U100/U$22 -> 0.23593427 | V101: =Q101-0.5% -> 0.2842339 | W101: =R101 -> 0.22116858 | X101: =S101 -> 0.23554142 | Y101: =T101 -> 0.209 | Z101: =Z100/Z$22 -> 0.23493379 | AA101: =V101 -> 0.2842339 | AB101: =W101 -> 0.22116858 | AC101: =X101 -> 0.23554142 | AD101: =Y101 -> 0.209 | AE101: =AE100/AE$22 -> 0.23505615 | AF101: =AA101 -> 0.2842339 | AG101: =AB101 -> 0.22116858 | AH101: =AC101 -> 0.23554142 | AI101: =AD101 -> 0.209 | AJ101: =AJ100/AJ$22 -> 0.23521499 | AK101: =AF101 -> 0.2842339 | AL101: =AG101 -> 0.22116858 | AM101: =AH101 -> 0.23554142 | AN101: =AI101 -> 0.209 | AO101: =AO100/AO$22 -> 0.23530945
A102: YoY % Change | B102: =IFERROR(B100/#REF!-1,"na") -> na | C102: =IFERROR(C100/#REF!-1,"na") -> na | D102: =IFERROR(D100/#REF!-1,"na") -> na | E102: =IFERROR(E100/#REF!-1,"na") -> na | F102: =IFERROR(F100/#REF!-1,"na") -> na | G102: =IFERROR(G100/B100-1,"na") -> 0.12630463 | H102: =IFERROR(H100/C100-1,"na") -> 0.19152116 | I102: =IFERROR(I100/D100-1,"na") -> 0.13456907 | J102: =IFERROR(J100/E100-1,"na") -> 0.13382514 | K102: =IFERROR(K100/F100-1,"na") -> 0.14544652 | L102: =IFERROR(L100/G100-1,"na") -> 0.098543435 | M102: =IFERROR(M100/H100-1,"na") -> 0.10384593 | N102: =IFERROR(N100/I100-1,"na") -> 0.11419555 | ... AO102: =IFERROR(AO100/AJ100-1,"na") -> 0.07125619
A104: Selling, general and administrative | B104: ='Income Statement'!B15 -> 27.767 | C104: ='Income Statement'!C15 -> 32.646 | D104: ='Income Statement'!D15 -> 33.29 | E104: ='Income Statement'!E15 -> 31.225 | F104: ='Income Statement'!F15 -> 124.928 | G104: ='Income Statement'!G15 -> 29.193 | H104: ='Income Statement'!H15 -> 31.613 | I104: ='Income Statement'!I15 -> 32.647 | J104: ='Income Statement'!J15 -> 35.693 | K104: =SUM(G104:J104) -> 129.146 | L104: ='Income Statement'!L15 -> 34.307 | M104: ='Income Statement'!M15 -> 35.511 | N104: ='Income Statement'!N15 -> 30.525 | O104: =O$22*O105 -> 35.390691 | P104: =SUM(L104:O104) -> 135.73369 | Q104: =Q$22*Q105 -> 39.387409 | R104: =R$22*R105 -> 40.378717 | S104: =S$22*S105 -> 34.75225 | T104: =T$22*T105 -> 40.236768 | U104: =SUM(Q104:T104) -> 154.75514 | V104: =V$22*V105 -> 43.777442 | W104: =W$22*W105 -> 44.72582 | X104: =X$22*X105 -> 38.420527 | Y104: =Y$22*Y105 -> 44.39175 | Z104: =SUM(V104:Y104) -> 171.31554 | AA104: =AA$22*AA105 -> 48.250172 | AB104: =AB$22*AB105 -> 48.870142 | AC104: =AC$22*AC105 -> 41.960283 | AD104: =AD$22*AD105 -> 48.295346 | AE104: =SUM(AA104:AD104) -> 187.37594 | AF104: =AF$22*AF105 -> 44.205938 | AG104: =AG$22*AG105 -> 52.774254 | AH104: =AH$22*AH105 -> 50.988406 | AI104: =AI$22*AI105 -> 55.017441 | AJ104: =SUM(AF104:AI104) -> 202.98604 | AK104: =AK$22*AK105 -> 47.630966 | AL104: =AL$22*AL105 -> 56.485405 | AM104: =AM$22*AM105 -> 54.551857 | AN104: =AN$22*AN105 -> 58.694537 | AO104: =SUM(AK104:AN104) -> 217.36276
A105: As % of Total Revenue | B105: =B104/B$22 -> 0.12494994 | C105: =C104/C$22 -> 0.11396236 | D105: =D104/D$22 -> 0.11994192 | E105: =E104/E$22 -> 0.10952797 | F105: =F104/F$22 -> 0.11661063 | G105: =G104/G$22 -> 0.11770564 | H105: =H104/H$22 -> 0.10504717 | I105: =I104/I$22 -> 0.11171068 | ... N105: =N104/N$22 -> 0.092403396 | O105: 0.098 | P105: =AVERAGE(L105:O105) -> 0.10464537 | Q105: =L105 -> 0.1240033 | R105: =M105 -> 0.1041748 | S105: =N105 -> 0.092403396 | T105: =O105 -> 0.098 | U105: =AVERAGE(Q105:T105) -> 0.10464537 | V105: =Q105 -> 0.1240033 | W105: =R105 -> 0.1041748 | X105: =S105 -> 0.092403396 | Y105: =T105 -> 0.098 | Z105: =AVERAGE(V105:Y105) -> 0.10464537 | AA105: =V105 -> 0.1240033 | AB105: =W105 -> 0.1041748 | AC105: =X105 -> 0.092403396 | AD105: =Y105 -> 0.098 | AE105: =AVERAGE(AA105:AD105) -> 0.10464537 | AF105: 0.104 | AG105: 0.104 | AH105: 0.104 | AI105: 0.104 | AJ105: =AVERAGE(AF105:AI105) -> 0.104 | AK105: 0.104 | AL105: 0.104 | AM105: 0.104 | AN105: 0.104 | AO105: =AVERAGE(AK105:AN105) -> 0.104
A106: YoY % Change | B106: =IFERROR(B104/#REF!-1,"na") -> na | C106: =IFERROR(C104/#REF!-1,"na") -> na | D106: =IFERROR(D104/#REF!-1,"na") -> na | E106: =IFERROR(E104/#REF!-1,"na") -> na | F106: =IFERROR(F104/#REF!-1,"na") -> na | G106: =IFERROR(G104/B104-1,"na") -> 0.051355926 | H106: =IFERROR(H104/C104-1,"na") -> -0.031642468 | I106: =IFERROR(I104/D104-1,"na") -> -0.01931511 | J106: =IFERROR(J104/E104-1,"na") -> 0.14309047 | K106: =IFERROR(K104/F104-1,"na") -> 0.033763448 | L106: =IFERROR(L104/G104-1,"na") -> 0.17517898 | M106: =IFERROR(M104/H104-1,"na") -> 0.1233037 | N106: =IFERROR(N104/I104-1,"na") -> -0.064998315 | ... AO106: =IFERROR(AO104/AJ104-1,"na") -> 0.070826181
A108: National advertising fund expense | B108: ='Income Statement'!B16 -> 16.987 | C108: ='Income Statement'!C16 -> 17.89 | D108: ='Income Statement'!D16 -> 17.618 | E108: ='Income Statement'!E16 -> 17.599 | F108: ='Income Statement'!F16 -> 70.094 | G108: ='Income Statement'!G16 -> 19.792 | H108: ='Income Statement'!H16 -> 20.112 | I108: ='Income Statement'!I16 -> 19.72 | J108: ='Income Statement'!J16 -> 19.385 | K108: =SUM(G108:J108) -> 79.009 | L108: ='Income Statement'!L16 -> 21.944 | M108: ='Income Statement'!M16 -> 22.777 | N108: ='Income Statement'!N16 -> 21.429 | O108: =J108*(1+O109) -> 20.35425 | P108: =SUM(L108:O108) -> 86.50425 | Q108: =L108*(1+Q109) -> 27.43 | R108: =M108*(1+R109) -> 28.47125 | S108: =N108*(1+S109) -> 26.78625 | T108: =O108*(1+T109) -> 25.442812 | U108: =SUM(Q108:T108) -> 108.13031 | V108: =Q108*(1+V109) -> 29.3501 | W108: =R108*(1+W109) -> 30.464237 | X108: =S108*(1+X109) -> 28.661288 | Y108: =T108*(1+Y109) -> 27.223809 | Z108: =SUM(V108:Y108) -> 115.69943 | AA108: =V108*(1+AA109) -> 30.817605 | AB108: =W108*(1+AB109) -> 31.987449 | AC108: =X108*(1+AC109) -> 30.094352 | AD108: =Y108*(1+AD109) -> 28.585 | AE108: =SUM(AA108:AD108) -> 121.48441 | AF108: =AA108*(1+AF109) -> 32.358485 | AG108: =AB108*(1+AG109) -> 33.586822 | AH108: =AC108*(1+AH109) -> 31.599069 | AI108: =AD108*(1+AI109) -> 30.01425 | AJ108: =SUM(AF108:AI108) -> 127.55863 | AK108: =AF108*(1+AK109) -> 33.97641 | AL108: =AG108*(1+AL109) -> 35.266163 | AM108: =AH108*(1+AM109) -> 33.179023 | AN108: =AI108*(1+AN109) -> 31.514962 | AO108: =SUM(AK108:AN108) -> 133.93656
A109: YoY % Change | B109: =IFERROR(B108/#REF!-1,"na") -> na | C109: =IFERROR(C108/#REF!-1,"na") -> na | D109: =IFERROR(D108/#REF!-1,"na") -> na | E109: =IFERROR(E108/#REF!-1,"na") -> na | F109: =IFERROR(F108/#REF!-1,"na") -> na | G109: =IFERROR(G108/B108-1,"na") -> 0.16512627 | H109: =IFERROR(H108/C108-1,"na") -> 0.12420347 | I109: =IFERROR(I108/D108-1,"na") -> 0.1193098 | J109: =IFERROR(J108/E108-1,"na") -> 0.10148304 | K109: =IFERROR(K108/F108-1,"na") -> 0.12718635 | L109: =IFERROR(L108/G108-1,"na") -> 0.1087308 | M109: =IFERROR(M108/H108-1,"na") -> 0.13250796 | N109: =IFERROR(N108/I108-1,"na") -> 0.086663286 | O109: 0.05 | P109: =IFERROR(P108/K108-1,"na") -> 0.094865775 | Q109: 0.25 | R109: 0.25 | S109: 0.25 | T109: 0.25 | U109: =IFERROR(U108/P108-1,"na") -> 0.25 | V109: 0.07 | W109: 0.07 | X109: 0.07 | Y109: 0.07 | Z109: =IFERROR(Z108/U108-1,"na") -> 0.07 | AA109: 0.05 | AB109: 0.05 | AC109: 0.05 | AD109: 0.05 | AE109: =IFERROR(AE108/Z108-1,"na") -> 0.05 | AF109: 0.05 | AG109: 0.05 | AH109: 0.05 | AI109: 0.05 | AJ109: =IFERROR(AJ108/AE108-1,"na") -> 0.05 | AK109: 0.05 | AL109: 0.05 | AM109: 0.05 | AN109: 0.05 | AO109: =IFERROR(AO108/AJ108-1,"na") -> 0.05
A111: Other (gain) loss | B111: ='Income Statement'!B18 -> 3.936 | C111: ='Income Statement'!C18 -> 3.825 | D111: ='Income Statement'!D18 -> -0.056 | E111: ='Income Statement'!E18 -> 2.674 | F111: ='Income Statement'!F18 -> 10.379 | G111: ='Income Statement'!G18 -> 0.484 | H111: ='Income Statement'!H18 -> -0.066 | I111: ='Income Statement'!I18 -> 0.28 | J111: ='Income Statement'!J18 -> 0.628 | K111: =SUM(G111:J111) -> 1.326 | L111: ='Income Statement'!L18 -> -1.237 | M111: ='Income Statement'!M18 -> 4.9 | N111: ='Income Statement'!N18 -> -5.732 | O111: =O$22*O112 -> 0 | P111: =SUM(L111:O111) -> -2.069 | Q111: =Q$22*Q112 -> 0 | R111: =R$22*R112 -> 0 | S111: =S$22*S112 -> 0 | T111: =T$22*T112 -> 0 | U111: =SUM(Q111:T111) -> 0 | V111: =V$22*V112 -> 0 | W111: =W$22*W112 -> 0 | X111: =X$22*X112 -> 0 | Y111: =Y$22*Y112 -> 0 | Z111: =SUM(V111:Y111) -> 0 | AA111: =AA$22*AA112 -> 0 | AB111: =AB$22*AB112 -> 0 | AC111: =AC$22*AC112 -> 0 | AD111: =AD$22*AD112 -> 0 | AE111: =SUM(AA111:AD111) -> 0 | AF111: =AF$22*AF112 -> 0 | AG111: =AG$22*AG112 -> 0 | AH111: =AH$22*AH112 -> 0 | AI111: =AI$22*AI112 -> 0 | AJ111: =SUM(AF111:AI111) -> 0 | AK111: =AK$22*AK112 -> 0 | AL111: =AL$22*AL112 -> 0 | AM111: =AM$22*AM112 -> 0 | AN111: =AN$22*AN112 -> 0 | AO111: =SUM(AK111:AN111) -> 0
A112: As % of Total Revenue | B112: =B111/B$22 -> 0.017711779 | C112: =C111/C$22 -> 0.01335251 | D112: =D111/D$22 -> -0.00020176472 | E112: =E111/E$22 -> 0.0093795929 | F112: =F111/F$22 -> 0.0096879941 | G112: =G111/G$22 -> 0.0019514791 | H112: =H111/H$22 -> -0.00021931209 | I112: =I111/I$22 -> 0.00095809695 | ... N112: =N111/N$22 -> -0.017351557 | O112: 0 | P112: =AVERAGE(L112:O112) -> -0.0018620286 | Q112: 0 | R112: 0 | S112: 0 | T112: 0 | U112: =AVERAGE(Q112:T112) -> 0 | V112: 0 | W112: 0 | X112: 0 | Y112: 0 | Z112: =AVERAGE(V112:Y112) -> 0 | AA112: 0 | AB112: 0 | AC112: 0 | AD112: 0 | AE112: =AVERAGE(AA112:AD112) -> 0 | AF112: 0 | AG112: 0 | AH112: 0 | AI112: 0 | AJ112: =AVERAGE(AF112:AI112) -> 0 | AK112: 0 | AL112: 0 | AM112: 0 | AN112: 0 | AO112: =AVERAGE(AK112:AN112) -> 0
A113: YoY % Change | B113: =IFERROR(B111/#REF!-1,"na") -> na | C113: =IFERROR(C111/#REF!-1,"na") -> na | D113: =IFERROR(D111/#REF!-1,"na") -> na | E113: =IFERROR(E111/#REF!-1,"na") -> na | F113: =IFERROR(F111/#REF!-1,"na") -> na | G113: =IFERROR(G111/B111-1,"na") -> -0.87703252 | H113: =IFERROR(H111/C111-1,"na") -> -1.0172549 | I113: =IFERROR(I111/D111-1,"na") -> -6 | J113: =IFERROR(J111/E111-1,"na") -> -0.76514585 | K113: =IFERROR(K111/F111-1,"na") -> -0.87224203 | L113: =IFERROR(L111/G111-1,"na") -> -3.5557851 | M113: =IFERROR(M111/H111-1,"na") -> -75.242424 | N113: =IFERROR(N111/I111-1,"na") -> -21.471429 | ... AO113: =IFERROR(AO111/AJ111-1,"na") -> na
A115: Share based compensation
A116: Share based compensation | B116: ='Cash Flow Statement'!B30 -> 2.049 | C116: ='Cash Flow Statement'!C30 -> 2.744 | D116: ='Cash Flow Statement'!D30 -> 1.533 | E116: ='Cash Flow Statement'!E30 -> 1.58 | F116: ='Cash Flow Statement'!F30 -> 7.906 | G116: ='Cash Flow Statement'!G30 -> 0.975 | H116: ='Cash Flow Statement'!H30 -> 1.872 | I116: ='Cash Flow Statement'!I30 -> 3.118 | J116: ='Cash Flow Statement'!J30 -> 2.948 | K116: =SUM(G116:J116) -> 8.913 | L116: ='Cash Flow Statement'!L30 -> 2.631 | M116: ='Cash Flow Statement'!M30 -> 3.507 | N116: ='Cash Flow Statement'!N30 -> 2.994 | O116: ='Income Statement'!O15*Assumptions!O117 -> 2.9230313 | P116: =SUM(L116:O116) -> 12.055031 | Q116: ='Income Statement'!Q15*Assumptions!Q117 -> 3.020616 | R116: ='Income Statement'!R15*Assumptions!R117 -> 3.9877267 | S116: ='Income Statement'!S15*Assumptions!S117 -> 3.4086236 | T116: ='Income Statement'!T15*Assumptions!T117 -> 3.3232844 | U116: =SUM(Q116:T116) -> 13.740251 | V116: ='Income Statement'!V15*Assumptions!V117 -> 3.3572871 | W116: ='Income Statement'!W15*Assumptions!W117 -> 4.4170384 | X116: ='Income Statement'!X15*Assumptions!X117 -> 3.7684213 | Y116: ='Income Statement'!Y15*Assumptions!Y117 -> 3.6664579 | Z116: =SUM(V116:Y116) -> 15.209205 | AA116: ='Income Statement'!AA15*Assumptions!AA117 -> 3.7003003 | AB116: ='Income Statement'!AB15*Assumptions!AB117 -> 4.8263239 | AC116: ='Income Statement'!AC15*Assumptions!AC117 -> 4.115613 | AD116: ='Income Statement'!AD15*Assumptions!AD117 -> 3.9888684 | AE116: =SUM(AA116:AD116) -> 16.631106 | AF116: ='Income Statement'!AF15*Assumptions!AF117 -> 3.3901484 | AG116: ='Income Statement'!AG15*Assumptions!AG117 -> 5.2118867 | AH116: ='Income Statement'!AH15*Assumptions!AH117 -> 5.0011233 | AI116: ='Income Statement'!AI15*Assumptions!AI117 -> 4.5440679 | AJ116: =SUM(AF116:AI116) -> 18.147226 | AK116: ='Income Statement'!AK15*Assumptions!AK117 -> 3.6528134 | AL116: ='Income Statement'!AL15*Assumptions!AL117 -> 5.578393 | AM116: ='Income Statement'!AM15*Assumptions!AM117 -> 5.3506391 | AN116: ='Income Statement'!AN15*Assumptions!AN117 -> 4.8477711 | AO116: =SUM(AK116:AN116) -> 19.429617
A117: % Of Operating Expenses | B117: =B116/'Income Statement'!B15 -> 0.073792632 | C117: =C116/'Income Statement'!C15 -> 0.084053176 | D117: =D116/'Income Statement'!D15 -> 0.046049865 | E117: =E116/'Income Statement'!E15 -> 0.05060048 | F117: =F116/'Income Statement'!F15 -> 0.063284452 | G117: =G116/'Income Statement'!G15 -> 0.033398417 | H117: =H116/'Income Statement'!H15 -> 0.059216145 | I117: =I116/'Income Statement'!I15 -> 0.095506478 | ... N117: =N116/'Income Statement'!N15 -> 0.098083538 | O117: =J117 -> 0.082593226 | P117: =AVERAGE(L117:O117) -> 0.089031196 | Q117: =L117 -> 0.076689888 | R117: =M117 -> 0.098758131 | S117: =N117 -> 0.098083538 | T117: =O117 -> 0.082593226 | U117: =AVERAGE(Q117:T117) -> 0.089031196 | V117: =Q117 -> 0.076689888 | W117: =R117 -> 0.098758131 | X117: =S117 -> 0.098083538 | Y117: =T117 -> 0.082593226 | Z117: =AVERAGE(V117:Y117) -> 0.089031196 | AA117: =V117 -> 0.076689888 | AB117: =W117 -> 0.098758131 | AC117: =X117 -> 0.098083538 | AD117: =Y117 -> 0.082593226 | AE117: =AVERAGE(AA117:AD117) -> 0.089031196 | AF117: =AA117 -> 0.076689888 | AG117: =AB117 -> 0.098758131 | AH117: =AC117 -> 0.098083538 | AI117: =AD117 -> 0.082593226 | AJ117: =AVERAGE(AF117:AI117) -> 0.089031196 | AK117: =AF117 -> 0.076689888 | AL117: =AG117 -> 0.098758131 | AM117: =AH117 -> 0.098083538 | AN117: =AI117 -> 0.082593226 | AO117: =AVERAGE(AK117:AN117) -> 0.089031196
A119: PPE Schedule
A120: Beginning | G120: =F124 | H120: =G124 -> 382.019 | I120: =H124 -> 400.239 | J120: =I124 -> 421.633 | K120: =380.1 -> 380.1 | L120: =J124 -> 423.991 | M120: =L124 -> 419.313 | N120: =M124 -> 430.387 | O120: =N124 -> 448.324 | P120: =K124 -> 424.048 | Q120: =P124 -> 487.77233 | R120: =Q124 -> 488.74559 | S120: =R124 -> 499.55921 | T120: =S124 -> 523.28849 | U120: =P124 -> 487.77233 | V120: =U124 -> 542.42222 | W120: =V124 -> 546.9216 | X120: =W124 -> 558.59368 | Y120: =X124 -> 571.20365 | Z120: =U124 -> 542.42222 | AA120: =Z124 -> 583.83947 | AB120: =AA124 -> 589.56866 | AC120: =AB124 -> 602.76398 | AD120: =AC124 -> 616.90043 | AE120: =Z124 -> 583.83947 | AF120: =AE124 -> 630.89665 | AG120: =AF124 -> 637.53413 | AH120: =AG124 -> 651.81876 | AI120: =AH124 -> 667.02945 | AJ120: =AE124 -> 630.89665 | AK120: =AJ124 -> 681.78943 | AL120: =AK124 -> 688.83054 | AM120: =AL124 -> 703.76415 | AN120: =AM124 -> 719.7183 | AO120: =AJ124 -> 681.78943
A121: (+) CapEx | G121: =-'Cash Flow Statement'!G47 -> 26.311 | H121: =-'Cash Flow Statement'!H47 -> 38.034 | I121: =-'Cash Flow Statement'!I47 -> 48.623 | J121: =-'Cash Flow Statement'!J47 -> 42.093 | K121: =SUM(G121:J121) -> 155.061 | L121: =-'Cash Flow Statement'!L47 -> 23.055 | M121: =-'Cash Flow Statement'!M47 -> 35.746 | N121: =-'Cash Flow Statement'!N47 -> 54.776 | O121: =O126 -> 69.336863 | P121: =SUM(L121:O121) -> 182.91386 | Q121: =Q126 -> 28.586876 | R121: =R126 -> 38.760544 | S121: =S126 -> 52.652989 | T121: =T126 -> 49.269511 | U121: =SUM(Q121:T121) -> 169.26992 | V121: =V126 -> 35.30345 | W121: =W126 -> 42.933437 | X121: =X126 -> 41.579129 | Y121: =Y126 -> 45.297705 | Z121: =SUM(V121:Y121) -> 165.11372 | AA121: =AA126 -> 38.910395 | AB121: =AB126 -> 46.911676 | AC121: =AC126 -> 45.409893 | AD121: =AD126 -> 49.280965 | AE121: =SUM(AA121:AD121) -> 180.51293 | AF121: =AF126 -> 42.505709 | AG121: =AG126 -> 50.744475 | AH121: =AH126 -> 49.027314 | AI121: =AI126 -> 52.901385 | AJ121: =SUM(AF121:AI121) -> 195.17888 | AK121: =AK126 -> 45.799005 | AL121: =AL126 -> 54.312889 | AM121: =AM126 -> 52.453709 | AN121: =AN126 -> 56.437055 | AO121: =SUM(AK121:AN121) -> 209.00266
A122: (-) D&A | G122: =-'Cash Flow Statement'!G10+Assumptions!G141 -> -26.612 | H122: =-'Cash Flow Statement'!H10+Assumptions!H141 -> -27.049 | I122: =-'Cash Flow Statement'!I10+Assumptions!I141 -> -28.265 | J122: =-'Cash Flow Statement'!J10+Assumptions!J141 -> -29.187 | K122: =SUM(G122:J122) -> -111.113 | L122: =-'Cash Flow Statement'!L10+Assumptions!L141 -> -29.10275 | M122: =-'Cash Flow Statement'!M10+Assumptions!M141 -> -29.24 | N122: =-'Cash Flow Statement'!N10+Assumptions!N141 -> -29.918 | O122: =-O130 -> -29.945531 | P122: =SUM(L122:O122) -> -118.20628 | Q122: =-Q130 -> -27.613617 | R122: =-R130 -> -27.946922 | S122: =-S130 -> -28.923714 | T122: =-T130 -> -30.135778 | U122: =SUM(Q122:T122) -> -114.62003 | V122: =-V130 -> -30.804067 | W122: =-W130 -> -31.261358 | X122: =-X130 -> -28.969162 | Y122: =-Y130 -> -32.661888 | Z122: =SUM(V122:Y122) -> -123.69647 | AA122: =-AA130 -> -33.181207 | AB122: =-AB130 -> -33.716347 | AC122: =-AC130 -> -31.273446 | AD122: =-AD130 -> -35.28475 | AE122: =SUM(AA122:AD122) -> -133.45575 | AF122: =-AF130 -> -35.868222 | AG122: =-AG130 -> -36.45985 | AH122: =-AH130 -> -33.816621 | AI122: =-AI130 -> -38.141408 | AJ122: =SUM(AF122:AI122) -> -144.2861 | AK122: =-AK130 -> -38.757891 | AL122: =-AL130 -> -39.379284 | AM122: =-AM130 -> -36.49955 | AN122: =-AN130 -> -41.136526 | AO122: =SUM(AK122:AN122) -> -155.77325
A123: Other | G123: =G124-SUM(G120:G122) -> 382.32 | H123: =H124-SUM(H120:H122) -> 7.235 | I123: =I124-SUM(I120:I122) -> 1.036 | J123: =J124-SUM(J120:J122) -> -10.548 | L123: =L124-SUM(L120:L122) -> 1.36975 | M123: =M124-SUM(M120:M122) -> 4.568 | N123: =N124-SUM(N120:N122) -> -6.921 | O123: 0 | P123: =SUM(L123:O123) -> -0.98325 | Q123: 0 | R123: 0 | S123: 0 | T123: 0 | U123: =SUM(Q123:T123) -> 0 | V123: 0 | W123: 0 | X123: 0 | Y123: 0 | Z123: =SUM(V123:Y123) -> 0 | AA123: 0 | AB123: 0 | AC123: 0 | AD123: 0 | AE123: =SUM(AA123:AD123) -> 0 | AF123: 0 | AG123: 0 | AH123: 0 | AI123: 0 | AJ123: =SUM(AF123:AI123) -> 0 | AK123: 0 | AL123: 0 | AM123: 0 | AN123: 0 | AO123: =SUM(AK123:AN123) -> 0
A124: Ending PP&E | G124: ='Balance Sheet'!D22 -> 382.019 | H124: ='Balance Sheet'!E22 -> 400.239 | I124: ='Balance Sheet'!F22 -> 421.633 | J124: ='Balance Sheet'!G22 -> 423.991 | K124: =SUM(K120:K123) -> 424.048 | L124: ='Balance Sheet'!I22 -> 419.313 | M124: ='Balance Sheet'!J22 -> 430.387 | N124: ='Balance Sheet'!K22 -> 448.324 | O124: =SUM(O120:O123) -> 487.71533 | P124: =SUM(P120:P123) -> 487.77233 | Q124: =SUM(Q120:Q123) -> 488.74559 | R124: =SUM(R120:R123) -> 499.55921 | S124: =SUM(S120:S123) -> 523.28849 | T124: =SUM(T120:T123) -> 542.42222 | U124: =SUM(U120:U123) -> 542.42222 | V124: =SUM(V120:V123) -> 546.9216 | ... AO124: =SUM(AO120:AO123) -> 735.01883
A126: CapEx | B126: =-'Cash Flow Statement'!B47 -> 22.997 | C126: =-'Cash Flow Statement'!C47 -> 22.146 | D126: =-'Cash Flow Statement'!D47 -> 39.493 | E126: =-'Cash Flow Statement'!E47 -> 51.35 | F126: =-'Cash Flow Statement'!F47 -> 135.986 | G126: =-'Cash Flow Statement'!G47 -> 26.311 | H126: =-'Cash Flow Statement'!H47 -> 38.034 | I126: =-'Cash Flow Statement'!I47 -> 48.623 | J126: =-'Cash Flow Statement'!J47 -> 42.093 | K126: =SUM(G126:J126) -> 155.061 | L126: =-'Cash Flow Statement'!L47 -> 23.055 | M126: =-'Cash Flow Statement'!M47 -> 35.746 | N126: =-'Cash Flow Statement'!N47 -> 54.776 | O126: =O$22*O127 -> 69.336863 | P126: =SUM(L126:O126) -> 182.91386 | Q126: =Q$22*Q127 -> 28.586876 | R126: =R$22*R127 -> 38.760544 | S126: =S$22*S127 -> 52.652989 | T126: =T$22*T127 -> 49.269511 | U126: =SUM(Q126:T126) -> 169.26992 | V126: =V$22*V127 -> 35.30345 | W126: =W$22*W127 -> 42.933437 | X126: =X$22*X127 -> 41.579129 | Y126: =Y$22*Y127 -> 45.297705 | Z126: =SUM(V126:Y126) -> 165.11372 | AA126: =AA$22*AA127 -> 38.910395 | AB126: =AB$22*AB127 -> 46.911676 | AC126: =AC$22*AC127 -> 45.409893 | AD126: =AD$22*AD127 -> 49.280965 | AE126: =SUM(AA126:AD126) -> 180.51293 | AF126: =AF$22*AF127 -> 42.505709 | AG126: =AG$22*AG127 -> 50.744475 | AH126: =AH$22*AH127 -> 49.027314 | AI126: =AI$22*AI127 -> 52.901385 | AJ126: =SUM(AF126:AI126) -> 195.17888 | AK126: =AK$22*AK127 -> 45.799005 | AL126: =AL$22*AL127 -> 54.312889 | AM126: =AM$22*AM127 -> 52.453709 | AN126: =AN$22*AN127 -> 56.437055 | AO126: =SUM(AK126:AN126) -> 209.00266
...

Sheet Balance Sheet
A2: Planet Fitness Inc
A3: Balance Sheet
A4: (All values in $mn)
C5: 2023A | D5: 2024A | H5: 2024A | I5: 2025E | M5: 2025 | N5: =M5+1 -> 2026 | R5: =N5 -> 2026 | S5: =R5+1 -> 2027 | W5: =S5 -> 2027 | X5: =W5+1 -> 2028 | AB5: =X5 -> 2028 | AC5: =AB5+1 -> 2029 | AG5: =AC5 -> 2029 | AH5: =AG5+1 -> 2030 | AL5: =AH5 -> 2030
B6: 4QA | C6: FY | D6: 1QA | E6: 2QA | F6: 3QA | G6: 4QA | H6: FY | I6: 1QA | J6: 2QA | K6: 3QA | L6: 4QE | M6: FY | N6: 1QE | O6: 2QE | P6: 3QE | Q6: 4QE | R6: FY | S6: 1QE | T6: 2QE | U6: 3QE | V6: 4QE | W6: FY | X6: 1QE | Y6: 2QE | Z6: 3QE | AA6: 4QE | AB6: FY | AC6: 1QE | AD6: 2QE | AE6: 3QE | AF6: 4QE | AG6: FY | AH6: 1QE | AI6: 2QE | AJ6: 3QE | AK6: 4QE | AL6: FY
A7: Assets
A8: Current assets:
A9: Cash and cash equivalents | B9: 275.842 | C9: =B9 -> 275.842 | D9: 301.707 | E9: 246.961 | F9: 298.783 | G9: 293.15 | H9: ='Cash Flow Statement'!K75-H10 -> 293.15 | I9: 343.91 | J9: 335.723 | K9: 329.02 | L9: ='Cash Flow Statement'!O75-L10 -> 332.08208 | M9: ='Cash Flow Statement'!P75-M10 -> 332.08208 | N9: ='Cash Flow Statement'!Q75-N10 -> 463.89427 | O9: ='Cash Flow Statement'!R75-O10 -> 523.86576 | P9: ='Cash Flow Statement'!S75-P10 -> 560.16582 | Q9: ='Cash Flow Statement'!T75-Q10 -> 607.6851 | R9: ='Cash Flow Statement'!U75-R10 -> 607.6851 | S9: ='Cash Flow Statement'!V75-S10 -> 757.36072 | ... AL9: ='Cash Flow Statement'!AO75-AL10 -> 2272.8384
A10: Restricted cash | B10: 46.279 | C10: =B10 -> 46.279 | D10: 46.19 | E10: 47.8 | F10: 67.766 | G10: 56.524 | H10: =G10 -> 56.524 | I10: 56.581 | J10: 56.452 | K10: 56.388 | L10: =K10 -> 56.388 | M10: =L10 -> 56.388 | N10: =M10 -> 56.388 | O10: =N10 -> 56.388 | P10: =O10 -> 56.388 | Q10: =P10 -> 56.388 | R10: =Q10 -> 56.388 | S10: =R10 -> 56.388 | ... AL10: =AK10 -> 56.388
A11: Short-term marketable securities | B11: 74.901 | C11: =B11 -> 74.901 | D11: 93.362 | E11: 103.197 | F11: 108.629 | G11: 114.163 | H11: =G11 -> 114.163 | I11: 109.718 | J11: 106.998 | K11: 114.363 | L11: =K11 -> 114.363 | M11: =L11 -> 114.363 | N11: =M11 -> 114.363 | O11: =N11 -> 114.363 | P11: =O11 -> 114.363 | Q11: =P11 -> 114.363 | R11: =Q11 -> 114.363 | S11: =R11 -> 114.363 | ... AL11: =AK11 -> 114.363
A12: Accounts receivable | B12: 41.89 | C12: =B12 -> 41.89 | D12: 23.837 | E12: 41.334 | F12: 48.958 | G12: 77.145 | H12: =G12 -> 77.145 | I12: 38.643 | J12: 72.847 | K12: 70.425 | L12: =Assumptions!O162 -> 85.459873 | M12: =L12 -> 85.459873 | N12: =Assumptions!Q162 -> 43.102975 | O12: =Assumptions!R162 -> 81.381587 | P12: =Assumptions!S162 -> 46.315563 | Q12: =Assumptions!T162 -> 162.12329 | R12: =Q12 -> 162.12329 | S12: =Assumptions!V162 -> 48.764741 | T12: =Assumptions!W162 -> 91.422605 | U12: =Assumptions!X162 -> 51.654597 | V12: =Assumptions!Y162 -> 182.14764 | W12: =V12 -> 182.14764 | X12: =Assumptions!AA162 -> 53.869934 | Y12: =Assumptions!AB162 -> 100.6257 | Z12: =Assumptions!AC162 -> 56.681453 | AA12: =Assumptions!AD162 -> 200.24157 | AB12: =AA12 -> 200.24157 | AC12: =Assumptions!AF162 -> 58.782952 | AD12: =Assumptions!AG162 -> 109.50677 | AE12: =Assumptions!AH162 -> 61.50701 | AF12: =Assumptions!AI162 -> 217.52257 | AG12: =AF12 -> 217.52257 | AH12: =Assumptions!AK162 -> 63.369138 | AI12: =Assumptions!AL162 -> 117.72209 | AJ12: =Assumptions!AM162 -> 65.972862 | AK12: =Assumptions!AN162 -> 233.97222 | AL12: =AK12 -> 233.97222
A13: Due from related parties | B13: 0 | C13: =B13 -> 0 | D13: 0 | E13: 0 | F13: 0 | G13: 0 | H13: =G13 -> 0 | I13: 0 | J13: =I13 -> 0 | K13: 0 | L13: =K13 -> 0 | M13: =L13 -> 0 | N13: =M13 -> 0 | O13: =N13 -> 0 | P13: =O13 -> 0 | Q13: =P13 -> 0 | R13: =Q13 -> 0 | S13: =R13 -> 0 | ... AL13: =AK13 -> 0
A14: Inventory | B14: 4.677 | C14: =B14 -> 4.677 | D14: 4.959 | E14: 5.2 | F14: 4.858 | G14: 6.146 | H14: =G14 -> 6.146 | I14: 1.974 | J14: 4.347 | K14: 6.982 | L14: =Assumptions!O167 -> 7.029115 | M14: =L14 -> 7.029115 | N14: =Assumptions!Q167 -> 2.2323563 | O14: =Assumptions!R167 -> 4.860593 | P14: =Assumptions!S167 -> 4.2134176 | Q14: =Assumptions!T167 -> 14.007098 | R14: =Q14 -> 14.007098 | S14: =Assumptions!V167 -> 2.4463195 | T14: =Assumptions!W167 -> 5.2951216 | U14: =Assumptions!X167 -> 4.5610489 | V14: =Assumptions!Y167 -> 15.233128 | W14: =V14 -> 15.233128 | X14: =Assumptions!AA167 -> 2.6390659 | Y14: =Assumptions!AB167 -> 5.7381411 | Z14: =Assumptions!AC167 -> 4.9649137 | AA14: =Assumptions!AD167 -> 16.472569 | AB14: =AA14 -> 16.472569 | AC14: =Assumptions!AF167 -> 2.878428 | AD14: =Assumptions!AG167 -> 6.2413163 | AE14: =Assumptions!AH167 -> 5.3842692 | AF14: =Assumptions!AI167 -> 17.867063 | AG14: =AF14 -> 17.867063 | AH14: =Assumptions!AK167 -> 3.1018512 | AI14: =Assumptions!AL167 -> 6.7065971 | AJ14: =Assumptions!AM167 -> 5.772225 | AK14: =Assumptions!AN167 -> 19.188165 | AL14: =AK14 -> 19.188165
A15: Restricted assets - national advertising fund | B15: 0 | C15: =B15 -> 0 | D15: 17.945 | E15: 12.268 | F15: 0.363 | G15: 0 | H15: =G15 -> 0 | I15: 16.67 | J15: 9.071 | K15: 0 | L15: =K15 -> 0 | M15: =L15 -> 0 | N15: =M15 -> 0 | O15: =N15 -> 0 | P15: =O15 -> 0 | Q15: =P15 -> 0 | R15: =Q15 -> 0 | S15: =R15 -> 0 | ... AL15: =AK15 -> 0
A16: Deferred expenses – national advertising fund | B16: 0 | C16: =B16 -> 0 | D16: 0 | E16: 0 | F16: 0 | G16: 0 | H16: =G16 -> 0 | I16: 0 | J16: =I16 -> 0 | K16: 0 | L16: =K16 -> 0 | M16: =L16 -> 0 | N16: =M16 -> 0 | O16: =N16 -> 0 | P16: =O16 -> 0 | Q16: =P16 -> 0 | R16: =Q16 -> 0 | S16: =R16 -> 0 | ... AL16: =AK16 -> 0
A17: Prepaid expenses | B17: 13.842 | C17: =B17 -> 13.842 | D17: 18.945 | E17: 15.91 | F17: 14.432 | G17: 21.499 | H17: =G17 -> 21.499 | I17: 16.547 | J17: 19.202 | K17: 23.176 | L17: =Assumptions!O177 -> 23.816214 | M17: =L17 -> 23.816214 | N17: =Assumptions!Q177 -> 18.456769 | O17: =Assumptions!R177 -> 21.451662 | P17: =Assumptions!S177 -> 15.241881 | Q17: =Assumptions!T177 -> 45.181005 | R17: =Q17 -> 45.181005 | S17: =Assumptions!V177 -> 20.881147 | T17: =Assumptions!W177 -> 24.09841 | U17: =Assumptions!X177 -> 16.998892 | V17: =Assumptions!Y177 -> 50.76145 | W17: =V17 -> 50.76145 | X17: =Assumptions!AA177 -> 23.0672 | Y17: =Assumptions!AB177 -> 26.524286 | Z17: =Assumptions!AC177 -> 18.653168 | AA17: =Assumptions!AD177 -> 55.803922 | AB17: =AA17 -> 55.803922 | AC17: =Assumptions!AF177 -> 25.170963 | AD17: =Assumptions!AG177 -> 28.865278 | AE17: =Assumptions!AH177 -> 20.241199 | AF17: =Assumptions!AI177 -> 60.619843 | AG17: =AF17 -> 60.619843 | AH17: =Assumptions!AK177 -> 27.134775 | AI17: =Assumptions!AL177 -> 31.030784 | AJ17: =Assumptions!AM177 -> 21.710856 | AK17: =Assumptions!AN177 -> 65.204079 | AL17: =AK17 -> 65.204079
A18: Other receivables | B18: 11.072 | C18: =B18 -> 11.072 | D18: 12.513 | E18: 15.39 | F18: 7.882 | G18: 16.776 | H18: =G18 -> 16.776 | I18: 18.816 | J18: 24.954 | K18: 15.65 | L18: =K18 -> 15.65 | M18: =L18 -> 15.65 | N18: =M18 -> 15.65 | O18: =N18 -> 15.65 | P18: =O18 -> 15.65 | Q18: =P18 -> 15.65 | R18: =Q18 -> 15.65 | S18: =R18 -> 15.65 | ... AL18: =AK18 -> 15.65
A19: Other current assets | B19: 3.314 | C19: =B19 -> 3.314 | D19: 1.324 | E19: 5.79 | F19: 4.773 | G19: 2.616 | H19: =G19 -> 2.616 | I19: 0.734 | J19: 7.788 | K19: 9.646 | L19: =K19 -> 9.646 | M19: =L19 -> 9.646 | N19: =M19 -> 9.646 | O19: =N19 -> 9.646 | P19: =O19 -> 9.646 | Q19: =P19 -> 9.646 | R19: =Q19 -> 9.646 | S19: =R19 -> 9.646 | ... AL19: =AK19 -> 9.646
A20: Total current assets | B20: =SUM(B9:B19) -> 471.817 | C20: =SUM(C9:C19) -> 471.817 | D20: =SUM(D9:D19) -> 520.782 | E20: =SUM(E9:E19) -> 493.85 | F20: =SUM(F9:F19) -> 556.444 | G20: =SUM(G9:G19) -> 588.019 | H20: =SUM(H9:H19) -> 588.019 | I20: =SUM(I9:I19) -> 603.593 | ... AL20: =SUM(AL9:AL19) -> 2787.2499
A21: Long-term marketable securities | B21: 50.886 | C21: =B21 -> 50.886 | D21: 45.165 | E21: 49.718 | F21: 55.535 | G21: 65.668 | H21: =G21 -> 65.668 | I21: 76.091 | J21: 83.327 | K21: 78.177 | L21: =K21 -> 78.177 | M21: =L21 -> 78.177 | N21: =M21 -> 78.177 | O21: =N21 -> 78.177 | P21: =O21 -> 78.177 | Q21: =P21 -> 78.177 | R21: =Q21 -> 78.177 | S21: =R21 -> 78.177 | ... AL21: =AK21 -> 78.177
A22: Property and equipment | B22: 390.405 | C22: =B22 -> 390.405 | D22: 382.019 | E22: 400.239 | F22: 421.633 | G22: 423.991 | H22: =G22 -> 423.991 | I22: 419.313 | J22: 430.387 | K22: 448.324 | L22: =Assumptions!O124 -> 487.71533 | M22: =L22 -> 487.71533 | N22: =Assumptions!Q124 -> 488.74559 | O22: =Assumptions!R124 -> 499.55921 | P22: =Assumptions!S124 -> 523.28849 | Q22: =Assumptions!T124 -> 542.42222 | R22: =Q22 -> 542.42222 | S22: =Assumptions!V124 -> 546.9216 | T22: =Assumptions!W124 -> 558.59368 | U22: =Assumptions!X124 -> 571.20365 | V22: =Assumptions!Y124 -> 583.83947 | W22: =V22 -> 583.83947 | X22: =Assumptions!AA124 -> 589.56866 | Y22: =Assumptions!AB124 -> 602.76398 | Z22: =Assumptions!AC124 -> 616.90043 | AA22: =Assumptions!AD124 -> 630.89665 | AB22: =AA22 -> 630.89665 | AC22: =Assumptions!AF124 -> 637.53413 | AD22: =Assumptions!AG124 -> 651.81876 | AE22: =Assumptions!AH124 -> 667.02945 | AF22: =Assumptions!AI124 -> 681.78943 | AG22: =AF22 -> 681.78943 | AH22: =Assumptions!AK124 -> 688.83054 | AI22: =Assumptions!AL124 -> 703.76415 | AJ22: =Assumptions!AM124 -> 719.7183 | AK22: =Assumptions!AN124 -> 735.01883 | AL22: =AK22 -> 735.01883
A23: Investments | B23: 77.507 | C23: =B23 -> 77.507 | D23: 76.36 | E23: 75.599 | F23: 75.078 | G23: 75.65 | H23: =G23 -> 75.65 | I23: 75.257 | J23: 70.896 | K23: 70.431 | L23: =K23 -> 70.431 | M23: =L23 -> 70.431 | N23: =M23 -> 70.431 | O23: =N23 -> 70.431 | P23: =O23 -> 70.431 | Q23: =P23 -> 70.431 | R23: =Q23 -> 70.431 | S23: =R23 -> 70.431 | ... AL23: =AK23 -> 70.431
A24: Right-of-use assets, net | B24: 381.01 | C24: =B24 -> 381.01 | D24: 385.796 | E24: 393.564 | F24: 400.246 | G24: 395.174 | H24: =G24 -> 395.174 | I24: 416.237 | J24: 417.573 | K24: 403.314 | L24: =K24 -> 403.314 | M24: =L24 -> 403.314 | N24: =M24 -> 403.314 | O24: =N24 -> 403.314 | P24: =O24 -> 403.314 | Q24: =P24 -> 403.314 | R24: =Q24 -> 403.314 | S24: =R24 -> 403.314 | ... AL24: =AK24 -> 403.314
A25: Intangible assets, net | B25: 372.507 | C25: =B25 -> 372.507 | D25: 359.75 | E25: 346.993 | F25: 334.236 | G25: 323.318 | H25: =G25 -> 323.318 | I25: 314.139 | J25: 304.961 | K25: 295.587 | L25: =Assumptions!O139 -> 286.40875 | M25: =L25 -> 286.40875 | N25: =Assumptions!Q139 -> 278.389 | O25: =Assumptions!R139 -> 270.36925 | P25: =Assumptions!S139 -> 262.3495 | Q25: =Assumptions!T139 -> 254.32975 | R25: =Q25 -> 254.32975 | S25: =Assumptions!V139 -> 247.34075 | T25: =Assumptions!W139 -> 240.35175 | U25: =Assumptions!X139 -> 233.36275 | V25: =Assumptions!Y139 -> 226.37375 | W25: =V25 -> 226.37375 | X25: =Assumptions!AA139 -> 219.54875 | Y25: =Assumptions!AB139 -> 212.72375 | Z25: =Assumptions!AC139 -> 205.89875 | AA25: =Assumptions!AD139 -> 199.07375 | AB25: =AA25 -> 199.07375 | AC25: =Assumptions!AF139 -> 193.155 | AD25: =Assumptions!AG139 -> 187.23625 | AE25: =Assumptions!AH139 -> 181.3175 | AF25: =Assumptions!AI139 -> 175.39875 | AG25: =AF25 -> 175.39875 | AH25: =Assumptions!AK139 -> 168.15 | AI25: =Assumptions!AL139 -> 160.90125 | AJ25: =Assumptions!AM139 -> 153.6525 | AK25: =Assumptions!AN139 -> 146.40375 | AL25: =AK25 -> 146.40375
A26: Goodwill | B26: 717.502 | C26: =B26 -> 717.502 | D26: 719.074 | E26: 719.063 | F26: 719.127 | G26: 720.633 | H26: =G26 -> 720.633 | I26: 720.834 | J26: 721.118 | K26: 710.571 | L26: =K26 -> 710.571 | M26: =L26 -> 710.571 | N26: =M26 -> 710.571 | O26: =N26 -> 710.571 | P26: =O26 -> 710.571 | Q26: =P26 -> 710.571 | R26: =Q26 -> 710.571 | S26: =R26 -> 710.571 | ... AL26: =AK26 -> 710.571
A27: Deferred income taxes | B27: 504.188 | C27: =B27 -> 504.188 | D27: 499.839 | E27: 490.912 | F27: 481.456 | G27: 470.197 | H27: =G27 -> 470.197 | I27: 459.035 | J27: 443.082 | K27: 415.673 | L27: =K27 -> 415.673 | M27: =L27 -> 415.673 | N27: =M27 -> 415.673 | O27: =N27 -> 415.673 | P27: =O27 -> 415.673 | Q27: =P27 -> 415.673 | R27: =Q27 -> 415.673 | S27: =R27 -> 415.673 | ... AL27: =AK27 -> 415.673
A28: Other assets, net | B28: 3.871 | C28: =B28 -> 3.871 | D28: 3.993 | E28: 4.102 | F28: 4.426 | G28: 7.058 | H28: =G28 -> 7.058 | I28: 7.423 | J28: 10.426 | K28: 10.482 | L28: =K28 -> 10.482 | M28: =L28 -> 10.482 | N28: =M28 -> 10.482 | O28: =N28 -> 10.482 | P28: =O28 -> 10.482 | Q28: =P28 -> 10.482 | R28: =Q28 -> 10.482 | S28: =R28 -> 10.482 | ... AL28: =AK28 -> 10.482
A29: Total assets | B29: =SUM(B20:B28) -> 2969.693 | C29: =SUM(C20:C28) -> 2969.693 | D29: =SUM(D20:D28) -> 2992.778 | E29: =SUM(E20:E28) -> 2974.04 | F29: =SUM(F20:F28) -> 3048.181 | G29: =SUM(G20:G28) -> 3069.708 | H29: =SUM(H20:H28) -> 3069.708 | I29: =SUM(I20:I28) -> 3091.922 | ... AL29: =SUM(AL20:AL28) -> 5357.3204
A31: Liabilities and stockholders’ deficit
A32: Current liabilities:
A33: Current maturities of long-term debt | B33: 20.75 | C33: =B33 -> 20.75 | D33: 20.75 | E33: 20.5 | F33: 22.5 | G33: 22.5 | H33: =G33 -> 22.5 | I33: 22.5 | J33: 22.5 | K33: 22.5 | L33: =K33 -> 22.5 | M33: =L33 -> 22.5 | N33: =M33 -> 22.5 | O33: =N33 -> 22.5 | P33: =O33 -> 22.5 | Q33: =P33 -> 22.5 | R33: =Q33 -> 22.5 | S33: =R33 -> 22.5 | ... AL33: =AK33 -> 22.5
A34: Borrowings under Variable Funding Notes | B34: 0 | C34: =B34 -> 0 | D34: 0 | E34: 0 | F34: 0 | G34: 0 | H34: =G34 -> 0 | I34: 0 | J34: =I34 -> 0 | K34: =J34 -> 0 | L34: =K34 -> 0 | M34: =L34 -> 0 | N34: =M34 -> 0 | O34: =N34 -> 0 | P34: =O34 -> 0 | Q34: =P34 -> 0 | ... AL34: =AK34 -> 0
A35: Accounts payable | B35: 23.788 | C35: =B35 -> 23.788 | D35: 20.56 | E35: 29.728 | F35: 31.844 | G35: 32.887 | H35: =G35 -> 32.887 | I35: 25.757 | J35: 49.128 | K35: 48.013 | L35: =Assumptions!O172 -> 37.612513 | M35: =L35 -> 37.612513 | N35: =Assumptions!Q172 -> 29.128065 | O35: =Assumptions!R172 -> 54.932417 | P35: =Assumptions!S172 -> 28.974337 | Q35: =Assumptions!T172 -> 74.951418 | R35: =Q35 -> 74.951418 | S35: =Assumptions!V172 -> 31.919884 | T35: =Assumptions!W172 -> 59.843279 | U35: =Assumptions!X172 -> 31.364887 | V35: =Assumptions!Y172 -> 81.511857 | W35: =V35 -> 81.511857 | X35: =Assumptions!AA172 -> 34.434863 | Y35: =Assumptions!AB172 -> 64.850103 | Z35: =Assumptions!AC172 -> 34.142137 | AA35: =Assumptions!AD172 -> 88.144056 | AB35: =AA35 -> 88.144056 | AC35: =Assumptions!AF172 -> 37.558091 | AD35: =Assumptions!AG172 -> 70.536781 | AE35: =Assumptions!AH172 -> 37.025912 | AF35: =Assumptions!AI172 -> 95.605938 | AG35: =AF35 -> 95.605938 | AH35: =Assumptions!AK172 -> 40.473344 | AI35: =Assumptions!AL172 -> 75.795192 | AJ35: =Assumptions!AM172 -> 39.693761 | AK35: =Assumptions!AN172 -> 102.6751 | AL35: =AK35 -> 102.6751
A36: Member distribution payable | B36: 0 | C36: =B36 -> 0 | D36: 0 | E36: 0 | F36: 0 | G36: 0 | H36: =G36 -> 0 | I36: 0 | J36: =I36 -> 0 | K36: =J36 -> 0 | L36: =K36 -> 0 | M36: =L36 -> 0 | N36: =M36 -> 0 | O36: =N36 -> 0 | P36: =O36 -> 0 | Q36: =P36 -> 0 | ... AL36: =AK36 -> 0
A37: Accrued expenses | B37: 66.299 | C37: =B37 -> 66.299 | D37: 43.709 | E37: 56.898 | F37: 66.53 | G37: 67.895 | H37: =G37 -> 67.895 | I37: 61.538 | J37: 57.768 | K37: 61.159 | L37: =K37 -> 61.159 | M37: =L37 -> 61.159 | N37: =M37 -> 61.159 | O37: =N37 -> 61.159 | P37: =O37 -> 61.159 | Q37: =P37 -> 61.159 | R37: =Q37 -> 61.159 | S37: =R37 -> 61.159 | ... AL37: =AK37 -> 61.159
A38: Current maturities of obligations under capital leases | B38: 0 | C38: =B38 -> 0 | D38: 0 | E38: 0 | F38: 0 | G38: 0 | H38: =G38 -> 0 | I38: 0 | J38: =I38 -> 0 | K38: =J38 -> 0 | L38: =K38 -> 0 | M38: =L38 -> 0 | N38: =M38 -> 0 | O38: =N38 -> 0 | P38: =O38 -> 0 | Q38: =P38 -> 0 | ... AL38: =AK38 -> 0
A39: Due to related parties | B39: 0 | C39: =B39 -> 0 | D39: 0 | E39: 0 | F39: 0 | G39: 0 | H39: =G39 -> 0 | I39: 0 | J39: =I39 -> 0 | K39: =J39 -> 0 | L39: =K39 -> 0 | M39: =L39 -> 0 | N39: =M39 -> 0 | O39: =N39 -> 0 | P39: =O39 -> 0 | Q39: =P39 -> 0 | ... AL39: =AK39 -> 0
A40: Equipment deposits | B40: 4.506 | C40: =B40 -> 4.506 | D40: 7.594 | E40: 5.138 | F40: 10.345 | G40: 1.851 | H40: =G40 -> 1.851 | I40: 2.489 | J40: 7.86 | K40: 11.177 | L40: =K40 -> 11.177 | M40: =L40 -> 11.177 | N40: =M40 -> 11.177 | O40: =N40 -> 11.177 | P40: =O40 -> 11.177 | Q40: =P40 -> 11.177 | R40: =Q40 -> 11.177 | S40: =R40 -> 11.177 | ... AL40: =AK40 -> 11.177
A41: Restricted liabilities – national advertising fund | B41: 0 | C41: =B41 -> 0 | D41: 0 | E41: 0 | F41: 0 | G41: 0 | H41: =G41 -> 0 | I41: 0 | J41: =I41 -> 0 | K41: 2.613 | L41: =K41 -> 2.613 | M41: =L41 -> 2.613 | N41: =M41 -> 2.613 | O41: =N41 -> 2.613 | P41: =O41 -> 2.613 | Q41: =P41 -> 2.613 | R41: =Q41 -> 2.613 | S41: =R41 -> 2.613 | ... AL41: =AK41 -> 2.613
A42: Deferred revenue, current | B42: 59.591 | C42: =B42 -> 59.591 | D42: 77.263 | E42: 76.052 | F42: 67.517 | G42: 62.111 | H42: =G42 -> 62.111 | I42: 80.755 | J42: 77.309 | K42: 65.219 | L42: =Assumptions!O181 -> 68.805472 | M42: =L42 -> 68.805472 | N42: =Assumptions!Q181 -> 90.075324 | O42: =Assumptions!R181 -> 86.366345 | P42: =Assumptions!S181 -> 42.891796 | Q42: =Assumptions!T181 -> 130.52874 | R42: =Q42 -> 130.52874 | S42: =Assumptions!V181 -> 101.90711 | T42: =Assumptions!W181 -> 97.022392 | U42: =Assumptions!X181 -> 47.836154 | V42: =Assumptions!Y181 -> 146.65075 | W42: =V42 -> 146.65075 | X42: =Assumptions!AA181 -> 112.5758 | Y42: =Assumptions!AB181 -> 106.78919 | Z42: =Assumptions!AC181 -> 52.491412 | AA42: =Assumptions!AD181 -> 161.21854 | AB42: =AA42 -> 161.21854 | AC42: =Assumptions!AF181 -> 122.84288 | AD42: =Assumptions!AG181 -> 116.21424 | AE42: =Assumptions!AH181 -> 56.960251 | AF42: =Assumptions!AI181 -> 175.13182 | AG42: =AF42 -> 175.13182 | AH42: =Assumptions!AK181 -> 132.42695 | AI42: =Assumptions!AL181 -> 124.93276 | AJ42: =Assumptions!AM181 -> 61.095976 | AK42: =Assumptions!AN181 -> 188.37577 | AL42: =AK42 -> 188.37577
A43: Payable pursuant to tax benefit arrangements, current | B43: 41.294 | C43: =B43 -> 41.294 | D43: 41.294 | E43: 49.181 | F43: 48.553 | G43: 55.556 | H43: =G43 -> 55.556 | I43: 55.556 | J43: 55.044 | K43: 49.672 | L43: =K43 -> 49.672 | M43: =L43 -> 49.672 | N43: =M43 -> 49.672 | O43: =N43 -> 49.672 | P43: =O43 -> 49.672 | Q43: =P43 -> 49.672 | R43: =Q43 -> 49.672 | S43: =R43 -> 49.672 | ... AL43: =AK43 -> 49.672
A44: Taxes payable | B44: 0 | C44: =B44 -> 0 | D44: 0 | E44: 0 | F44: 0 | G44: 0 | H44: =G44 -> 0 | I44: 0 | J44: =I44 -> 0 | K44: =J44 -> 0 | L44: =K44 -> 0 | M44: =L44 -> 0 | N44: =M44 -> 0 | O44: =N44 -> 0 | P44: =O44 -> 0 | Q44: =P44 -> 0 | ... AL44: =AK44 -> 0
A45: Other current liabilities | B45: 35.101 | C45: =B45 -> 35.101 | D45: 35.331 | E45: 34.629 | F45: 39.001 | G45: 39.695 | H45: =G45 -> 39.695 | I45: 38.858 | J45: 40.581 | K45: 40.091 | L45: =K45 -> 40.091 | M45: =L45 -> 40.091 | N45: =M45 -> 40.091 | O45: =N45 -> 40.091 | P45: =O45 -> 40.091 | Q45: =P45 -> 40.091 | R45: =Q45 -> 40.091 | S45: =R45 -> 40.091 | ... AL45: =AK45 -> 40.091
A46: Total current liabilities | B46: =SUM(B33:B45) -> 251.329 | C46: =SUM(C33:C45) -> 251.329 | D46: =SUM(D33:D45) -> 246.501 | E46: =SUM(E33:E45) -> 272.126 | F46: =SUM(F33:F45) -> 286.29 | G46: =SUM(G33:G45) -> 282.495 | H46: =SUM(H33:H45) -> 282.495 | I46: =SUM(I33:I45) -> 287.453 | ... AL46: =SUM(AL33:AL45) -> 478.26287
A47: Long-term debt, net of current maturities | B47: 1962.874 | C47: =B47 -> 1962.874 | D47: 1959.032 | E47: 2156.551 | F47: 2152.276 | G47: 2148.029 | H47: =G47 -> 2148.029 | I47: 2143.718 | J47: 2139.418 | K47: 2135.129 | L47: =Assumptions!O149-'Balance Sheet'!L33 -> 2129.504 | M47: =L47 -> 2129.504 | N47: =Assumptions!Q149-'Balance Sheet'!N33 -> 2129.504 | O47: =Assumptions!R149-'Balance Sheet'!O33 -> 2129.504 | P47: =Assumptions!S149-'Balance Sheet'!P33 -> 2129.504 | Q47: =Assumptions!T149-'Balance Sheet'!Q33 -> 2129.504 | R47: =Q47 -> 2129.504 | S47: =Assumptions!V149-'Balance Sheet'!S33 -> 2124.9415 | T47: =Assumptions!W149-'Balance Sheet'!T33 -> 2120.379 | U47: =Assumptions!X149-'Balance Sheet'!U33 -> 2115.8165 | V47: =Assumptions!Y149-'Balance Sheet'!V33 -> 2111.254 | W47: =V47 -> 2111.254 | X47: =Assumptions!AA149-'Balance Sheet'!X33 -> 2106.6915 | Y47: =Assumptions!AB149-'Balance Sheet'!Y33 -> 2102.129 | Z47: =Assumptions!AC149-'Balance Sheet'!Z33 -> 2097.5665 | AA47: =Assumptions!AD149-'Balance Sheet'!AA33 -> 2093.004 | AB47: =AA47 -> 2093.004 | AC47: =Assumptions!AF149-'Balance Sheet'!AC33 -> 2093.004 | AD47: =Assumptions!AG149-'Balance Sheet'!AD33 -> 2093.004 | AE47: =Assumptions!AH149-'Balance Sheet'!AE33 -> 2093.004 | AF47: =Assumptions!AI149-'Balance Sheet'!AF33 -> 2093.004 | AG47: =AF47 -> 2093.004 | AH47: =Assumptions!AK149-'Balance Sheet'!AH33 -> 2093.004 | AI47: =Assumptions!AL149-'Balance Sheet'!AI33 -> 2093.004 | AJ47: =Assumptions!AM149-'Balance Sheet'!AJ33 -> 2093.004 | AK47: =Assumptions!AN149-'Balance Sheet'!AK33 -> 2093.004 | AL47: =AK47 -> 2093.004
A48: Obligations under capital leases, net of current portion | B48: 0 | C48: =B48 -> 0 | D48: 0 | E48: 0 | F48: 0 | G48: 0 | H48: =G48 -> 0 | I48: 0 | J48: =I48 -> 0 | K48: =J48 -> 0 | L48: =K48 -> 0 | M48: =L48 -> 0 | N48: =M48 -> 0 | O48: =N48 -> 0 | P48: =O48 -> 0 | Q48: =P48 -> 0 | ... AL48: =AK48 -> 0
A49: Deferred rent, net of current portion | B49: 0 | C49: =B49 -> 0 | D49: 0 | E49: 0 | F49: 0 | G49: 0 | H49: =G49 -> 0 | I49: 0 | J49: =I49 -> 0 | K49: =J49 -> 0 | L49: =K49 -> 0 | M49: =L49 -> 0 | N49: =M49 -> 0 | O49: =N49 -> 0 | P49: =O49 -> 0 | Q49: =P49 -> 0 | ... AL49: =AK49 -> 0
A50: Borrowings under Variable Funding Notes | B50: 0 | C50: =B50 -> 0 | D50: 0 | E50: 0 | F50: 0 | G50: 0 | H50: =G50 -> 0 | I50: 0 | J50: =I50 -> 0 | K50: =J50 -> 0 | L50: =K50 -> 0 | M50: =L50 -> 0 | N50: =M50 -> 0 | O50: =N50 -> 0 | P50: =O50 -> 0 | Q50: =P50 -> 0 | ... AL50: =AK50 -> 0
A51: Lease liabilities, net of current portion | B51: 381.589 | C51: =B51 -> 381.589 | D51: 390.399 | E51: 401.405 | F51: 408.588 | G51: 405.324 | H51: =G51 -> 405.324 | I51: 433.151 | J51: 432.95 | K51: 417.624 | L51: =K51 -> 417.624 | M51: =L51 -> 417.624 | N51: =M51 -> 417.624 | O51: =N51 -> 417.624 | P51: =O51 -> 417.624 | Q51: =P51 -> 417.624 | R51: =Q51 -> 417.624 | S51: =R51 -> 417.624 | ... AL51: =AK51 -> 417.624
A52: Deferred revenue, net of current portion | B52: 32.047 | C52: =B52 -> 32.047 | D52: 33.82 | E52: 34.114 | F52: 33.578 | G52: 31.99 | H52: =G52 -> 31.99 | I52: 31.163 | J52: 30.752 | K52: 30.167 | L52: =K52 -> 30.167 | M52: =L52 -> 30.167 | N52: =M52 -> 30.167 | O52: =N52 -> 30.167 | P52: =O52 -> 30.167 | Q52: =P52 -> 30.167 | R52: =Q52 -> 30.167 | S52: =R52 -> 30.167 | ... AL52: =AK52 -> 30.167
A53: Deferred tax liabilities | B53: 1.644 | C53: =B53 -> 1.644 | D53: 1.666 | E53: 1.599 | F53: 1.566 | G53: 1.386 | H53: =G53 -> 1.386 | I53: 1.323 | J53: 1.25 | K53: 0.62 | L53: =K53 -> 0.62 | M53: =L53 -> 0.62 | N53: =M53 -> 0.62 | O53: =N53 -> 0.62 | P53: =O53 -> 0.62 | Q53: =P53 -> 0.62 | R53: =Q53 -> 0.62 | S53: =R53 -> 0.62 | ... AL53: =AK53 -> 0.62
A54: Payable pursuant to tax benefit arrangements, net of current portion | B54: 454.368 | C54: =B54 -> 454.368 | D54: 456.7 | E54: 424.107 | F54: 428.858 | G54: 411.36 | H54: =G54 -> 411.36 | I54: 411.276 | J54: 358.569 | K54: 363.429 | L54: =K54 -> 363.429 | M54: =L54 -> 363.429 | N54: =M54 -> 363.429 | O54: =N54 -> 363.429 | P54: =O54 -> 363.429 | Q54: =P54 -> 363.429 | R54: =Q54 -> 363.429 | S54: =R54 -> 363.429 | ... AL54: =AK54 -> 363.429
A55: Other liabilities | B55: 4.833 | C55: =B55 -> 4.833 | D55: 3.891 | E55: 3.968 | F55: 4.139 | G55: 4.497 | H55: =G55 -> 4.497 | I55: 3.702 | J55: 4.304 | K55: 5.153 | L55: =K55 -> 5.153 | M55: =L55 -> 5.153 | N55: =M55 -> 5.153 | O55: =N55 -> 5.153 | P55: =O55 -> 5.153 | Q55: =P55 -> 5.153 | R55: =Q55 -> 5.153 | S55: =R55 -> 5.153 | ... AL55: =AK55 -> 5.153
A56: Total noncurrent liabilities | B56: =SUM(B47:B55) -> 2837.355 | C56: =SUM(C47:C55) -> 2837.355 | D56: =SUM(D47:D55) -> 2845.508 | E56: =SUM(E47:E55) -> 3021.744 | F56: =SUM(F47:F55) -> 3029.005 | G56: =SUM(G47:G55) -> 3002.586 | H56: =SUM(H47:H55) -> 3002.586 | I56: =SUM(I47:I55) -> 3024.333 | ... AL56: =SUM(AL47:AL55) -> 2909.997
A58: Commitments and contingencies
A59: Stockholders’ equity (deficit):
A60: Members’ equity | B60: 0 | C60: =B60 -> 0 | D60: 0 | E60: 0 | F60: 0 | G60: 0 | H60: =G60 -> 0 | I60: 0 | J60: =I60 -> 0 | K60: =J60 -> 0 | L60: =K60 -> 0 | M60: =L60 -> 0 | N60: 0.057 | O60: =N60 -> 0.057 | P60: =O60 -> 0.057 | Q60: =P60 -> 0.057 | R60: =Q60 -> 0.057 | S60: =R60 -> 0.057 | T60: =S60 -> 0.057 | U60: =T60 -> 0.057 | V60: =U60 -> 0.057 | ... AL60: =AK60 -> 0.057
A61: Class A common stock | B61: 0.009 | C61: =B61 -> 0.009 | D61: 0.009 | E61: 0.009 | F61: 0.009 | G61: 0.009 | H61: =G61 -> 0.009 | I61: 0.009 | J61: 0.009 | K61: 0.009 | L61: =K61 -> 0.009 | M61: =L61 -> 0.009 | N61: =M61 -> 0.009 | O61: =N61 -> 0.009 | P61: =O61 -> 0.009 | Q61: =P61 -> 0.009 | R61: =Q61 -> 0.009 | S61: =R61 -> 0.009 | ... AL61: =AK61 -> 0.009
A62: Class B common stock | B62: 0 | C62: =B62 -> 0 | D62: 0 | E62: 0 | F62: 0 | G62: 0 | H62: =G62 -> 0 | I62: 0 | J62: =I62 -> 0 | K62: =J62 -> 0 | L62: =K62 -> 0 | M62: =L62 -> 0 | N62: =M62 -> 0 | O62: =N62 -> 0 | P62: =O62 -> 0 | Q62: =P62 -> 0 | ... AL62: =AK62 -> 0
A63: Accumulated other comprehensive (loss) income | B63: 0.172 | C63: =B63 -> 0.172 | D63: -0.435 | E63: -1.096 | F63: 0.22 | G63: -2.348 | H63: =G63 -> -2.348 | I63: -1.352 | J63: 1.01 | K63: 1.121 | L63: =K63 -> 1.121 | M63: =L63 -> 1.121 | N63: =M63 -> 1.121 | O63: =N63 -> 1.121 | P63: =O63 -> 1.121 | Q63: =P63 -> 1.121 | R63: =Q63 -> 1.121 | S63: =R63 -> 1.121 | ... AL63: =AK63 -> 1.121
A64: Additional paid in capital | B64: 575.631 | C64: =B64 -> 575.631 | D64: 581.332 | E64: 594.049 | F64: 602.948 | G64: 609.115 | H64: =G64 -> 609.115 | I64: 612.196 | J64: 615.04 | K64: 618.939 | L64: =K64+'Cash Flow Statement'!O30+'Cash Flow Statement'!O65 -> 621.86203 | M64: =L64 -> 621.86203 | N64: =M64+'Cash Flow Statement'!Q30+'Cash Flow Statement'!Q65 -> 624.88265 | O64: =N64+'Cash Flow Statement'!R30+'Cash Flow Statement'!R65 -> 628.87037 | P64: =O64+'Cash Flow Statement'!S30+'Cash Flow Statement'!S65 -> 632.279 | Q64: =P64+'Cash Flow Statement'!T30+'Cash Flow Statement'!T65 -> 635.60228 | R64: =Q64 -> 635.60228 | S64: =R64+'Cash Flow Statement'!V30+'Cash Flow Statement'!V65 -> 638.95957 | T64: =S64+'Cash Flow Statement'!W30+'Cash Flow Statement'!W65 -> 643.37661 | U64: =T64+'Cash Flow Statement'!X30+'Cash Flow Statement'!X65 -> 647.14503 | V64: =U64+'Cash Flow Statement'!Y30+'Cash Flow Statement'!Y65 -> 650.81149 | W64: =V64 -> 650.81149 | X64: =W64+'Cash Flow Statement'!AA30+'Cash Flow Statement'!AA65 -> 654.51179 | Y64: =X64+'Cash Flow Statement'!AB30+'Cash Flow Statement'!AB65 -> 659.33811 | Z64: =Y64+'Cash Flow Statement'!AC30+'Cash Flow Statement'!AC65 -> 663.45372 | AA64: =Z64+'Cash Flow Statement'!AD30+'Cash Flow Statement'!AD65 -> 667.44259 | AB64: =AA64 -> 667.44259 | AC64: =AB64+'Cash Flow Statement'!AF30+'Cash Flow Statement'!AF65 -> 670.83274 | AD64: =AC64+'Cash Flow Statement'!AG30+'Cash Flow Statement'!AG65 -> 676.04463 | AE64: =AD64+'Cash Flow Statement'!AH30+'Cash Flow Statement'!AH65 -> 681.04575 | AF64: =AE64+'Cash Flow Statement'!AI30+'Cash Flow Statement'!AI65 -> 685.58982 | AG64: =AF64 -> 685.58982 | AH64: =AG64+'Cash Flow Statement'!AK30+'Cash Flow Statement'!AK65 -> 689.24263 | AI64: =AH64+'Cash Flow Statement'!AL30+'Cash Flow Statement'!AL65 -> 694.82103 | AJ64: =AI64+'Cash Flow Statement'!AM30+'Cash Flow Statement'!AM65 -> 700.17166 | AK64: =AJ64+'Cash Flow Statement'!AN30+'Cash Flow Statement'!AN65 -> 705.01944 | AL64: =AK64 -> 705.01944
A65: Accumulated deficit | B65: -691.461 | C65: =B65 -> -691.461 | D65: -677.321 | E65: -910.626 | F65: -869.309 | G65: -822.156 | H65: =G65 -> -822.156 | I65: -830.743 | J65: -774.753 | K65: -814.832 | L65: =K65+'Income Statement'!O33 -> -756.31865 | M65: =L65 -> -756.31865 | N65: =M65+'Income Statement'!Q33 -> -699.87208 | O65: =N65+'Income Statement'!R33 -> -619.28807 | P65: =O65+'Income Statement'!S33 -> -543.17746 | Q65: =P65+'Income Statement'!T33 -> -465.94098 | R65: =Q65 -> -465.94098 | S65: =R65+'Income Statement'!V33 -> -395.11579 | T65: =S65+'Income Statement'!W33 -> -298.96512 | U65: =T65+'Income Statement'!X33 -> -205.68804 | V65: =U65+'Income Statement'!Y33 -> -112.92642 | W65: =V65 -> -112.92642 | X65: =W65+'Income Statement'!AA33 -> -28.971592 | Y65: =X65+'Income Statement'!AB33 -> 81.452296 | Z65: =Y65+'Income Statement'!AC33 -> 188.57744 | AA65: =Z65+'Income Statement'!AD33 -> 294.49979 | AB65: =AA65 -> 294.49979 | AC65: =AB65+'Income Statement'!AF33 -> 398.20978 | AD65: =AC65+'Income Statement'!AG33 -> 523.02516 | AE65: =AD65+'Income Statement'!AH33 -> 639.74965 | AF65: =AE65+'Income Statement'!AI33 -> 755.91403 | AG65: =AF65 -> 755.91403 | AH65: =AG65+'Income Statement'!AK33 -> 871.0812 | AI65: =AH65+'Income Statement'!AL33 -> 1007.7189 | AJ65: =AI65+'Income Statement'!AM33 -> 1135.6531 | AK65: =AJ65+'Income Statement'!AN33 -> 1262.4481 | AL65: =AK65 -> 1262.4481
A66: Total stockholders’ deficit attributable to Planet Fitness, Inc. | B66: =SUM(B60:B65) -> -115.649 | C66: =SUM(C60:C65) -> -115.649 | D66: =SUM(D60:D65) -> -96.415 | E66: =SUM(E60:E65) -> -317.664 | F66: =SUM(F60:F65) -> -266.132 | G66: =SUM(G60:G65) -> -215.38 | H66: =SUM(H60:H65) -> -215.38 | I66: =SUM(I60:I65) -> -219.89 | ... AL66: =SUM(AL60:AL65) -> 1968.6546
A67: Non-controlling interests | B67: -3.342 | C67: =B67 -> -3.342 | D67: -2.816 | E67: -2.166 | F67: -0.982 | G67: 0.007 | H67: =G67 -> 0.007 | I67: 0.026 | J67: 0.413 | K67: 0.406 | L67: =K67 -> 0.406 | M67: =L67 -> 0.406 | N67: =M67 -> 0.406 | O67: =N67 -> 0.406 | P67: =O67 -> 0.406 | Q67: =P67 -> 0.406 | R67: =Q67 -> 0.406 | S67: =R67 -> 0.406 | ... AL67: =AK67 -> 0.406
A68: Total stockholders’ deficit | B68: =B66+B67 -> -118.991 | C68: =C66+C67 -> -118.991 | D68: =D66+D67 -> -99.231 | E68: =E66+E67 -> -319.83 | F68: =F66+F67 -> -267.114 | G68: =G66+G67 -> -215.373 | H68: =H66+H67 -> -215.373 | I68: =I66+I67 -> -219.864 | ... AL68: =AL66+AL67 -> 1969.0606
A70: Total liabilities and stockholders’ deficit | B70: =B68+B56+B46 -> 2969.693 | C70: =C68+C56+C46 -> 2969.693 | D70: =D68+D56+D46 -> 2992.778 | E70: =E68+E56+E46 -> 2974.04 | F70: =F68+F56+F46 -> 3048.181 | G70: =G68+G56+G46 -> 3069.708 | H70: =H68+H56+H46 -> 3069.708 | I70: =I68+I56+I46 -> 3091.922 | ... AL70: =AL68+AL56+AL46 -> 5357.3204
A72: Check | B72: =B70-B29 -> 0 | C72: =C70-C29 -> 0 | D72: =D70-D29 -> 0 | E72: =E70-E29 -> 0 | F72: =F70-F29 -> 0 | G72: =G70-G29 -> 0 | H72: =H70-H29 -> 0 | I72: =I70-I29 -> 0 | ... AL72: =AL70-AL29 -> 0

Sheet Cash Flow Statement
A2: Planet Fitness Inc
A3: Cash Flow Statement
A4: (All values in $mn)
B5: 2023A | F5: 2023A | G5: 2024A | K5: 2024A | L5: 2025E | P5: 2025 | Q5: =P5+1 -> 2026 | U5: =Q5 -> 2026 | V5: =U5+1 -> 2027 | Z5: =V5 -> 2027 | AA5: =Z5+1 -> 2028 | AE5: =AA5 -> 2028 | AF5: =AE5+1 -> 2029 | AJ5: =AF5 -> 2029 | AK5: =AJ5+1 -> 2030 | AO5: =AK5 -> 2030
B6: 1QA | C6: 2QA | D6: 3QA | E6: 4QA | F6: FY | G6: 1QA | H6: 2QA | I6: 3QA | J6: 4QA | K6: FY | L6: 1QA | M6: 2QA | N6: 3QA | O6: 4QE | P6: FY | Q6: 1QE | R6: 2QE | S6: 3QE | T6: 4QE | U6: FY | V6: 1QE | W6: 2QE | X6: 3QE | Y6: 4QE | Z6: FY | AA6: 1QE | AB6: 2QE | AC6: 3QE | AD6: 4QE | AE6: FY | AF6: 1QE | AG6: 2QE | AH6: 3QE | AI6: 4QE | AJ6: FY | AK6: 1QE | AL6: 2QE | AM6: 3QE | AN6: 4QE | AO6: FY
A7: Cash flows from operating activities:
