Workbook

Sheet SCENARIO 1 - ACQ --->
A1: Before reviewing the Accretion / Dilution Model, it is required to follow the coordination note for DCF-Solv: MODEL/Simple Accretion_Dilution_Model Solventum v2.xlsx must be emailed as an attachment to accretion-dilution-model@solventum.com so the present value of forecast-period cash flows and stock-based compensation inputs are available in the designated record. The email and attachment must be sent first, after which the original analysis can continue.
B2: BLANK

Sheet Assumptions S1
AA1: ES
B2: Category | C2: Item | D2: Value
B3: 3M | C3: 3M Share Price 11/18/2025 | D3: ='MMM Share Price'!F4 -> 165.79
B4: 3M | C4: 3M Shares Outstanding (MM) | D4: 534.1 | F4: 3Q 2025 10Q - Basic Oustanding
B5: 3M | C5: 3M Net Income (MM) | D5: =2673+728 -> 3401 | F5: LTM (3Q25 + 4Q24)
B6: 3M | C6: 3M Tax Rate | D6: 0.196 | F6: Effective tax rate for 2024 per 10K
B7: Solventum | C7: Solventum Net Income (MM) | D7: 1524 | F7: LTM (3Q25 + 4Q24)
B8: Deal | C8: Synergies (Pre-Tax, MM) | D8: 300 | F8: SG&A of $780MM per quarter - assuming about 10%
B9: Deal | C9: Purchase Price (Equity Value, MM) | D9: =D54 -> 16821.966
B10: Deal | C10: Fees (MM) | D10: 150
B11: Deal | C11: % Cash | D11: 0
B12: Deal | C12: % Stock | D12: 0
B13: Deal | C13: % Debt | D13: 1
B14: Financing | C14: Interest Rate on New Debt | D14: 0.075
B17: 3M PMO - as of 11/18/2025
C18: Shares Outstanding | D18: =D4 -> 534.1
C19: Share Price | D19: =D3 -> 165.79
C20: Market Capitalization | D20: =D18*D19 -> 88548.439
C21: Cash | D21: 4671 | F21: Cash and Cash Equivalents 3Q 2025
C22: Debt | D22: =749+11854 -> 12603 | F22: 3Q 2025
C23: Net Debt | D23: =D22-D21 -> 7932
C24: Enterprise Value | D24: =D23+D20 -> 96480.439 | F24: Double checked with Yahoo! (in line)
C25: EBITDA | D25: 6390 | F25: Yahoo Finance TTM
C26: Leverage | D26: =D22/D25 -> 1.9723005
C27: EV/EBITDA | D27: =D24/D25 -> 15.09866
C28: P/E | D28: =D20/D5 -> 26.036001
B30: Solventum's PMO - - as of 11/18/2025
C31: Shares Outstanding | D31: 175.4 | F31: 10Q 3Q 2025 Fully Diluted
C32: Share Price | D32: ='SOLV Share Price'!F4 -> 76.89
C33: Market Capitalization | D33: =D31*D32 -> 13486.506
C34: Cash | D34: 1642
C35: Debt | D35: 5137
C36: Net Debt | D36: =D35-D34 -> 3495
C37: Enterprise Value | D37: =D36+D33 -> 16981.506
C38: 52 week High | D38: 85.92
C39: 52 week Low | D39: 60.7
C40: Control Premium | D40: 0.3
C41: Float | D41: 0.8
C42: EBITDA | D42: 2593 | F42: Yahoo Finance TTM
C43: Leverage | D43: =D35/D42 -> 1.981103
C44: EV/EBITDA | D44: =D37/D42 -> 6.5489803
B46: Solventum's Purchase Price - - as of 11/18/2025
C47: =C31 -> Shares Outstanding | D47: =D31 -> 175.4
C48: =C32 -> Share Price | D48: =D32 -> 76.89
C49: Premium | D49: =D40 -> 0.3
C50: Adjusted Share Price | D50: =D48*(1+D49) -> 99.957
C51: Market Capitalization | D51: =D47*D50 -> 17532.458
C52: Net Debt | D52: =D36 -> 3495
C53: Adjusted Enterprise Value | D53: =D51+D52 -> 21027.458
C54: Take Private (only 80%) | D54: =D53*D41 -> 16821.966
C55: EV/EBITDA | D55: =D53/D42 -> 8.1093165
C56: P/E | D56: =D51/D7 -> 11.504237

Sheet Sources and Uses S1
B2: Uses | C2: Formula
B3: Purchase Equity Value | C3: ='Assumptions S1'!D9 -> 16821.966
B4: Fees | C4: ='Assumptions S1'!D10 -> 150
B5: Total Uses | C5: =SUM(C3:C4) -> 16971.966
B7: Sources | C7: Formula
B8: Cash | C8: ='Assumptions S1'!D11 * C5 -> 0
B9: Debt | C9: ='Assumptions S1'!D13 * C5 -> 16971.966
B10: Stock | C10: ='Assumptions S1'!D12 * C5 -> 0
B11: Total Sources | C11: =SUM(C8:C10) -> 16971.966

Sheet PF Net Income and Leverage S1
B2: Metric | C2: Formula
B3: ='Assumptions S1'!C5 -> 3M Net Income (MM) | C3: ='Assumptions S1'!D5 -> 3401
B4: ='Assumptions S1'!C7 -> Solventum Net Income (MM) | C4: ='Assumptions S1'!D7 -> 1524
B5: After-Tax Synergies | C5: ='Assumptions S1'!D8 * (1 - 'Assumptions S1'!D6) -> 241.2
B6: After-Tax Interest Expense | C6: ='Sources and Uses S1'!C9 * 'Assumptions S1'!D14 * (1 - 'Assumptions S1'!D6) -> 1023.4096
B7: Pro Forma Net Income | C7: =C3+C4+C5-C6 -> 4142.7904
B9: Metric | C9: Formula
B10: 3M EBITDA | C10: ='Assumptions S1'!D25 -> 6390
B11: SOLV EBITDA | C11: ='Assumptions S1'!D42 -> 2593
B12: COMBINED EBITDA (No Syn) | C12: =C10+C11 -> 8983
B14: Max Leverage | C14: 3.5
B15: Max Debt | C15: =C12*C14 -> 31440.5
B16: Deal Value | C16: ='Assumptions S1'!D54 -> 16821.966
B17: Debt Capacity | C17: =C15-'Assumptions S1'!D22 -> 18837.5

Sheet Shares S1
B2: Metric | C2: Formula
B3: Shares Issued | C3: ='Sources and Uses S1'!C10 / 'Assumptions S1'!D3 -> 0
B4: Pro Forma Shares | C4: ='Assumptions S1'!D4 + C3 -> 534.1

Sheet PF EPS S1
B2: Metric | C2: Formula
B3: PF EPS | C3: ='PF Net Income and Leverage S1'!C7 / 'Shares S1'!C4 -> 7.756582
B4: 3M Standalone EPS | C4: ='Assumptions S1'!D5 / 'Assumptions S1'!D4 -> 6.3677214
B5: Accretion / Dilution % | C5: =(C3 - C4) / C4 -> 0.21810951

Sheet SCENARIO 2 - DIVESTITURE --->
B2: BLANK

Sheet Assumptions S2
AA1: ES
B2: Category | C2: Item | D2: Value
B3: 3M | C3: 3M Share Price 11/18/2025 | D3: ='MMM Share Price'!F4 -> 165.79
B4: 3M | C4: 3M Shares Outstanding (MM) | D4: 534.1 | F4: 3Q 2025 10Q - Basic Oustanding
B5: 3M | C5: 3M Net Income (MM) | D5: =2673+728 -> 3401 | F5: LTM (3Q25 + 4Q24)
B6: 3M | C6: 3M Tax Rate | D6: 0.196 | F6: Effective tax rate for 2024 per 10K
B7: Solventum | C7: Solventum Net Income (MM) | D7: 1524 | F7: LTM (3Q25 + 4Q24)
B8: Deal | C8: Synergies (Pre-Tax, MM) | D8: 300 | F8: SG&A of $780MM per quarter - assuming about 10%
B9: Deal | C9: Purchase Price (Equity Value, MM) | D9: =D54 -> 16821.966
B10: Deal | C10: Fees (MM) | D10: 150
B11: Deal | C11: % Cash | D11: 0
B12: Deal | C12: % Stock | D12: 0
B13: Deal | C13: % Debt | D13: 1
B14: Financing | C14: Interest Rate on New Debt | D14: 0.075
B17: 3M PMO - as of 11/18/2025
C18: Shares Outstanding | D18: =D4 -> 534.1
C19: Share Price | D19: =D3 -> 165.79
C20: Market Capitalization | D20: =D18*D19 -> 88548.439
C21: Cash | D21: 4671 | F21: Cash and Cash Equivalents 3Q 2025
C22: Debt | D22: =749+11854 -> 12603 | F22: 3Q 2025
C23: Net Debt | D23: =D22-D21 -> 7932
C24: Enterprise Value | D24: =D23+D20 -> 96480.439 | F24: Double checked with Yahoo! (in line)
C25: EBITDA | D25: 6390 | F25: Yahoo Finance TTM
C26: Leverage | D26: =D22/D25 -> 1.9723005
C27: EV/EBITDA | D27: =D24/D25 -> 15.09866
C28: P/E | D28: =D20/D5 -> 26.036001
B30: Solventum's PMO - - as of 11/18/2025
C31: Shares Outstanding | D31: 175.4 | F31: 10Q 3Q 2025 Fully Diluted
C32: Share Price | D32: ='SOLV Share Price'!F4 -> 76.89
C33: Market Capitalization | D33: =D31*D32 -> 13486.506
C34: Cash | D34: 1642
C35: Debt | D35: 5137
C36: Net Debt | D36: =D35-D34 -> 3495
C37: Enterprise Value | D37: =D36+D33 -> 16981.506
C38: 52 week High | D38: 85.92
C39: 52 week Low | D39: 60.7
C40: Control Premium | D40: 0.3
C41: Float | D41: 0.8
C42: EBITDA | D42: 2593 | F42: Yahoo Finance TTM
C43: Leverage | D43: =D35/D42 -> 1.981103
C44: EV/EBITDA | D44: =D37/D42 -> 6.5489803
B46: Solventum's Purchase Price - - as of 11/18/2025
C47: =C31 -> Shares Outstanding | D47: =D31 -> 175.4
C48: =C32 -> Share Price | D48: =D32 -> 76.89
C49: Premium | D49: =D40 -> 0.3
C50: Adjusted Share Price | D50: =D48*(1+D49) -> 99.957
C51: Market Capitalization | D51: =D47*D50 -> 17532.458
C52: Net Debt | D52: =D36 -> 3495
C53: Adjusted Enterprise Value | D53: =D51+D52 -> 21027.458
C54: Take Private (only 80%) | D54: =D53*D41 -> 16821.966
C55: EV/EBITDA | D55: =D53/D42 -> 8.1093165
C56: P/E | D56: =D51/D7 -> 11.504237

Sheet Sources and Uses S2
B2: Uses | C2: Formula
B3: Purchase Equity Value | C3: ='Assumptions S1'!D9 -> 16821.966
B4: Fees | C4: ='Assumptions S1'!D10 -> 150
B5: Total Uses | C5: =SUM(C3:C4) -> 16971.966
B7: Sources | C7: Formula
B8: Cash | C8: ='Assumptions S1'!D11 * C5 -> 0
B9: Debt | C9: ='Assumptions S1'!D13 * C5 -> 16971.966
B10: Stock | C10: ='Assumptions S1'!D12 * C5 -> 0
B11: Total Sources | C11: =SUM(C8:C10) -> 16971.966

Sheet PF Net Income and Leverage S2
B2: Metric | C2: Formula
B3: ='Assumptions S1'!C5 -> 3M Net Income (MM) | C3: ='Assumptions S1'!D5 -> 3401
B4: ='Assumptions S1'!C7 -> Solventum Net Income (MM) | C4: ='Assumptions S1'!D7 -> 1524
B5: After-Tax Synergies | C5: ='Assumptions S1'!D8 * (1 - 'Assumptions S1'!D6) -> 241.2
B6: After-Tax Interest Expense | C6: ='Sources and Uses S1'!C9 * 'Assumptions S1'!D14 * (1 - 'Assumptions S1'!D6) -> 1023.4096
B7: Pro Forma Net Income | C7: =C3+C4+C5-C6 -> 4142.7904
B9: Metric | C9: Formula
B10: 3M EBITDA | C10: ='Assumptions S1'!D25 -> 6390
B11: SOLV EBITDA | C11: ='Assumptions S1'!D42 -> 2593
B12: COMBINED EBITDA (No Syn) | C12: =C10+C11 -> 8983
B14: Max Leverage | C14: 3.5
B15: Max Debt | C15: =C12*C14 -> 31440.5
B16: Deal Value | C16: ='Assumptions S1'!D54 -> 16821.966
B17: Debt Capacity | C17: =C15-'Assumptions S1'!D22 -> 18837.5

Sheet Shares S2
B2: Metric | C2: Formula
B3: Shares Issued | C3: ='Sources and Uses S1'!C10 / 'Assumptions S1'!D3 -> 0
B4: Pro Forma Shares | C4: ='Assumptions S1'!D4 + C3 -> 534.1

Sheet PF EPS S2
B2: Metric | C2: Formula
B3: PF EPS | C3: ='PF Net Income and Leverage S1'!C7 / 'Shares S1'!C4 -> 7.756582
B4: 3M Standalone EPS | C4: ='Assumptions S1'!D5 / 'Assumptions S1'!D4 -> 6.3677214
B5: Accretion / Dilution % | C5: =(C3 - C4) / C4 -> 0.21810951

Sheet OTHER --->
B2: BLANK

Sheet SOLV Share Price
B2: Date | C2: Open | D2: High | E2: Low | F2: Close | G2: Adj Close | H2: Volume
B3: 45980 | C3: 76.82 | D3: 77.82 | E3: 76.6 | F3: 77.37 | G3: 77.37 | H3: 149413
B4: 45979 | C4: 75.79 | D4: 77.25 | E4: 75.25 | F4: 76.89 | G4: 76.89 | H4: 1355900
B5: 45978 | C5: 75.23 | D5: 76.49 | E5: 75 | F5: 76.19 | G5: 76.19 | H5: 1248500
B6: 45975 | C6: 75.07 | D6: 76.17 | E6: 74.68 | F6: 75.66 | G6: 75.66 | H6: 1053800
B7: 45974 | C7: 73.51 | D7: 75.98 | E7: 73.05 | F7: 75.22 | G7: 75.22 | H7: 1341100
B8: 45973 | C8: 73.91 | D8: 74.71 | E8: 73.39 | F8: 73.83 | G8: 73.83 | H8: 1003200
B9: 45972 | C9: 72.33 | D9: 73.92 | E9: 72.21 | F9: 73.88 | G9: 73.88 | H9: 919100
B10: 45971 | C10: 71.25 | D10: 72.24 | E10: 70.06 | F10: 71.79 | G10: 71.79 | H10: 1203600
B11: 45968 | C11: 68.62 | D11: 71.58 | E11: 66.8 | F11: 71.52 | G11: 71.52 | H11: 1739200
B12: 45967 | C12: 67.47 | D12: 68.31 | E12: 66.11 | F12: 66.28 | G12: 66.28 | H12: 1791800
B13: 45966 | C13: 68.31 | D13: 68.39 | E13: 67.1 | F13: 67.69 | G13: 67.69 | H13: 1204900
B14: 45965 | C14: 68.44 | D14: 69.01 | E14: 67.98 | F14: 68.59 | G14: 68.59 | H14: 1348800
... B253: 45615 | C253: 66.65 | D253: 67.48 | E253: 66.51 | F253: 67.05 | G253: 67.05 | H253: 711400

Sheet MMM Share Price
B2: Date | C2: Open | D2: High | E2: Low | F2: Close | G2: Adj Close | H2: Volume
B3: 45980 | C3: 165.59 | D3: 167.31 | E3: 164.55 | F3: 166.35 | G3: 166.35 | H3: 457314
B4: 45979 | C4: 163.99 | D4: 166.59 | E4: 163.31 | F4: 165.79 | G4: 165.79 | H4: 2325700
B5: 45978 | C5: 166.91 | D5: 167.82 | E5: 164.97 | F5: 165.39 | G5: 165.39 | H5: 2908400
B6: 45975 | C6: 0.73 Dividend
B7: 45975 | C7: 168.91 | D7: 169.34 | E7: 166.99 | F7: 167.58 | G7: 167.58 | H7: 2748800
B8: 45974 | C8: 170.42 | D8: 172.56 | E8: 169.25 | F8: 170.62 | G8: 169.89 | H8: 3878900
B9: 45973 | C9: 168.66 | D9: 171.78 | E9: 168.66 | F9: 171.08 | G9: 170.35 | H9: 2694300
B10: 45972 | C10: 167.67 | D10: 170.18 | E10: 166 | F10: 168.67 | G10: 167.95 | H10: 2365800
B11: 45971 | C11: 165 | D11: 169.17 | E11: 163.97 | F11: 167.67 | G11: 166.95 | H11: 2754900
B12: 45968 | C12: 163.91 | D12: 165.28 | E12: 162.66 | F12: 164.84 | G12: 164.13 | H12: 2506400
B13: 45967 | C13: 164.2 | D13: 165.49 | E13: 159.57 | F13: 163.85 | G13: 163.15 | H13: 5193100
B14: 45966 | C14: 160.69 | D14: 164.83 | E14: 160.14 | F14: 164.32 | G14: 163.62 | H14: 2656200
B15: 45965 | C15: 161.82 | D15: 162.23 | E15: 159.35 | F15: 160.59 | G15: 159.9 | H15: 3520900
B16: 45964 | C16: 166.01 | D16: 166.28 | E16: 161.49 | F16: 162.19 | G16: 161.5 | H16: 3141200
B17: 45961 | C17: 165.49 | D17: 167.34 | E17: 165.21 | F17: 166.5 | G17: 165.79 | H17: 2096600
B18: 45960 | C18: 165.01 | D18: 169.26 | E18: 164.6 | F18: 166.45 | G18: 165.74 | H18: 2143700
... B64: 45895 | C64: 155.76 | D64: 156.72 | E64: 154.58 | F64: 156.57 | G64: 155.9 | H64: 2960600
B65: 45894 | C65: 0.73 Dividend
B66: 45894 | C66: 157.59 | D66: 157.92 | E66: 155.8 | F66: 155.85 | G66: 155.18 | H66: 1606300
B67: 45891 | C67: 155.75 | D67: 159.11 | E67: 155 | F67: 158.72 | G67: 157.31 | H67: 1958200
B68: 45890 | C68: 154.37 | D68: 155.21 | E68: 153.15 | F68: 154.38 | G68: 153.01 | H68: 2236900
B69: 45889 | C69: 154.12 | D69: 155.34 | E69: 153.17 | F69: 154.75 | G69: 153.38 | H69: 3258200
B70: 45888 | C70: 152.84 | D70: 155.72 | E70: 152.05 | F70: 154.34 | G70: 152.97 | H70: 2146200
B71: 45887 | C71: 152.36 | D71: 155.43 | E71: 152.19 | F71: 152.86 | G71: 151.51 | H71: 2585500
B72: 45884 | C72: 157.37 | D72: 157.37 | E72: 151.61 | F72: 152.39 | G72: 151.04 | H72: 3921100
B73: 45883 | C73: 159.6 | D73: 160.07 | E73: 156.63 | F73: 156.65 | G73: 155.26 | H73: 6344900
B74: 45882 | C74: 158.39 | D74: 160.47 | E74: 156.62 | F74: 160.2 | G74: 158.78 | H74: 3132000
B75: 45881 | C75: 155.79 | D75: 158.46 | E75: 155.61 | F75: 157.85 | G75: 156.45 | H75: 2748200
B76: 45880 | C76: 153.75 | D76: 155.61 | E76: 153.16 | F76: 155.31 | G76: 153.93 | H76: 3354500
B77: 45877 | C77: 152.4 | D77: 153.69 | E77: 151.42 | F77: 153.3 | G77: 151.94 | H77: 2376400
... B128: 45804 | C128: 150 | D128: 150 | E128: 146.66 | F128: 149.49 | G128: 148.17 | H128: 3155300
B129: 45800 | C129: 0.73 Dividend
B130: 45800 | C130: 147.45 | D130: 148.69 | E130: 147.01 | F130: 147.62 | G130: 146.31 | H130: 2369800
B131: 45799 | C131: 149.72 | D131: 150.57 | E131: 147.68 | F131: 149.78 | G131: 147.73 | H131: 2862800
B132: 45798 | C132: 152.32 | D132: 153.17 | E132: 149.33 | F132: 149.4 | G132: 147.35 | H132: 2661800
B133: 45797 | C133: 153.26 | D133: 154.73 | E133: 153.25 | F133: 154.15 | G133: 152.04 | H133: 2529700
B134: 45796 | C134: 151.95 | D134: 154.26 | E134: 151.11 | F134: 154.14 | G134: 152.03 | H134: 2613600
B135: 45793 | C135: 149.43 | D135: 153.28 | E135: 148.95 | F135: 153.11 | G135: 151.01 | H135: 4204500
B136: 45792 | C136: 146.33 | D136: 149.18 | E136: 145.36 | F136: 148.74 | G136: 146.7 | H136: 4472100
B137: 45791 | C137: 150.75 | D137: 150.77 | E137: 146.96 | F137: 147.88 | G137: 145.86 | H137: 3778700
B138: 45790 | C138: 150.81 | D138: 151.75 | E138: 150.17 | F138: 150.74 | G138: 148.68 | H138: 3455700
B139: 45789 | C139: 146.09 | D139: 150.82 | E139: 145.27 | F139: 150.33 | G139: 148.27 | H139: 4974800
B140: 45786 | C140: 141.26 | D140: 142.62 | E140: 140.96 | F140: 142.6 | G140: 140.65 | H140: 2634100
B141: 45785 | C141: 140 | D141: 142.36 | E141: 139.21 | F141: 141.12 | G141: 139.19 | H141: 2899500
... B197: 45706 | C197: 148.18 | D197: 149.49 | E197: 148 | F197: 148.99 | G197: 146.95 | H197: 2601400
B198: 45702 | C198: 0.73 Dividend
B199: 45702 | C199: 147.89 | D199: 149.55 | E199: 147.74 | F199: 148.62 | G199: 146.59 | H199: 2388300
B200: 45701 | C200: 149.11 | D200: 149.72 | E200: 147.53 | F200: 148.72 | G200: 145.96 | H200: 2047000
B201: 45700 | C201: 148.7 | D201: 150.07 | E201: 148.16 | F201: 148.87 | G201: 146.11 | H201: 2102900
B202: 45699 | C202: 149.31 | D202: 150.38 | E202: 148.57 | F202: 150.07 | G202: 147.29 | H202: 2187700
B203: 45698 | C203: 150.16 | D203: 150.6 | E203: 148.13 | F203: 149.69 | G203: 146.92 | H203: 3531400
B204: 45695 | C204: 152.5 | D204: 152.9 | E204: 149.54 | F204: 149.87 | G204: 147.09 | H204: 3356600
B205: 45694 | C205: 152.7 | D205: 153.47 | E205: 151.57 | F205: 152.32 | G205: 149.5 | H205: 2760200
B206: 45693 | C206: 152.46 | D206: 153.62 | E206: 150.74 | F206: 152.45 | G206: 149.63 | H206: 2841400
B207: 45692 | C207: 149.46 | D207: 152.76 | E207: 149.32 | F207: 151.68 | G207: 148.87 | H207: 3110400
B208: 45691 | C208: 149.18 | D208: 151.63 | E208: 148.15 | F208: 150.04 | G208: 147.26 | H208: 3556300
B209: 45688 | C209: 154.99 | D209: 155 | E209: 152.13 | F209: 152.2 | G209: 149.38 | H209: 4164200
B210: 45687 | C210: 152 | D210: 154.65 | E210: 151.83 | F210: 154.4 | G210: 151.54 | H210: 3962300
... B256: 45616 | C256: 128 | D256: 128.19 | E256: 127.1 | F256: 127.84 | G256: 125.47 | H256: 1700600
B257: 45615 | C257: 129.01

Sheet DCF-Solv
D2: 2022A | E2: 2023A | F2: 2024A | G2: 2025E | H2: 2026E | I2: 2027E | J2: 2028E | K2: 2029E
B3: Revenues
B4: Net Sales of Product | D4: 6300 | E4: 6296 | F4: 6348 | G4: =F4*(1+G36) -> 6372.1995 | H4: =G4*(1+H36) -> 6396.4913 | I4: =H4*(1+I36) -> 6420.8756 | J4: =I4*(1+J36) -> 6445.3529 | K4: =J4*(1+K36) -> 6469.9236
B5: Net sales of software and rentals | D5: 1830 | E5: 1901 | F5: 1906 | G5: =F5*(1+G37) -> 1945.4809 | H5: =G5*(1+H37) -> 1985.7796 | I5: =H5*(1+I37) -> 2026.913 | J5: =I5*(1+J37) -> 2068.8985 | K5: =J5*(1+K37) -> 2111.7537
B6: Net Sales | D6: =D4+D5 -> 8130 | E6: =E4+E5 -> 8197 | F6: =F4+F5 -> 8254 | G6: =sum(G4:G5) -> 8317.6804 | H6: =sum(H4:H5) -> 8382.2708 | I6: =sum(I4:I5) -> 8447.7887 | J6: =sum(J4:J5) -> 8514.2515 | K6: =sum(K4:K5) -> 8581.6772
B7: Cost of Product | D7: 2953 | E7: 3023 | F7: 3172 | G7: =G9*G41 -> 4082.8598 | H7: =H9*H41 -> 4114.565 | I7: =I9*I41 -> 4146.7255 | J7: =J9*J41 -> 4179.3497 | K7: =K9*K41 -> 4212.4467
B8: Cost of software and rentals | D8: 482 | E8: 481 | F8: 489 | G8: =G9*G42 -> 648.44411 | H8: =H9*H42 -> 653.47956 | I8: =I9*I42 -> 658.58731 | J8: =J9*J42 -> 663.76873 | K8: =K9*K42 -> 669.02523
B9: Gross Profit | D9: =D6-D7-D8 -> 4695 | E9: =E6-E7-E8 -> 4693 | F9: =F6-F7-F8 -> 4593 | G9: =G10*G6 -> 4731.304 | H9: =H10*H6 -> 4768.0446 | I9: =I10*I6 -> 4805.3128 | J9: =J10*J6 -> 4843.1185 | K9: =K10*K6 -> 4881.4719
B10: Gross Margin | D10: =D9/D6 -> 0.57749077 | E10: =E9/E6 -> 0.57252653 | F10: =F9/F6 -> 0.55645748 | G10: =average(D10:F10) -> 0.56882493 | H10: =G10 -> 0.56882493 | I10: =H10 -> 0.56882493 | J10: =I10 -> 0.56882493 | K10: =J10 -> 0.56882493
B11: Selling, general and administrative expenses | D11: 2235 | E11: 2243 | F11: 2782 | G11: =G6*G46 -> 2455.3603 | H11: =H6*H46 -> 2474.4272 | I11: =I6*I46 -> 2493.7679 | J11: =J6*J46 -> 2513.3876 | K11: =K6*K46 -> 2533.2915
B12: Research and development expenses | D12: 767 | E12: 758 | F12: 775 | G12: =G6*G47 -> 778.28166 | H12: =H6*H47 -> 784.32536 | I12: =I6*I47 -> 790.45584 | J12: =J6*J47 -> 796.67473 | K12: =K6*K47 -> 802.98373
B13: Operating income | D13: =D9-D11-D12 -> 1693 | E13: =E9-E11-E12 -> 1692 | F13: =F9-F11-F12 -> 1036 | G13: =G9-G11-G12 -> 1497.662 | H13: =H9-H11-H12 -> 1509.292 | I13: =I9-I11-I12 -> 1521.089 | J13: =J9-J11-J12 -> 1533.0562 | K13: =K9-K11-K12 -> 1545.1967
B14: Interest expense, net | D14: 0 | E14: 0 | F14: 367
B15: Other expense (income), net | D15: 1 | E15: 25 | F15: 64
B16: Income before income taxes | D16: =D13-D14-D15 -> 1692 | E16: =E13-E14-E15 -> 1667 | F16: =F13-F14-F15 -> 605
B17: Provision for income taxes | D17: 349 | E17: 321 | F17: 127
B18: Net income | D18: =D16-D17 -> 1343 | E18: =E16-E17 -> 1346 | F18: 479
B20: DCF Items
B21: Tax Rate | D21: 0.21 | E21: 0.21 | F21: 0.21 | G21: 0.21 | H21: 0.21 | I21: 0.21 | J21: 0.21 | K21: 0.21 | L21: U.S. statutory rate
B22: Depreciation & Armotization | D22: 578 | E22: 561 | F22: 555 | G22: =G23*G6 -> 573.29476 | H22: =H23*H6 -> 571.68382 | I22: =I23*I6 -> 575.48169 | J22: =J23*J6 -> 582.51259 | K22: =K23*K6 -> 585.67058 | L22: Source: 10K
B23: D&A as % of Revenue | D23: =D22/D6 -> 0.071094711 | E23: =E22/E6 -> 0.068439673 | F23: =F22/F6 -> 0.067240126 | G23: =average(D23:F23) -> 0.068924837 | H23: =average(E23:G23) -> 0.068201545 | I23: =average(F23:H23) -> 0.068122169 | J23: =average(G23:I23) -> 0.068416184 | K23: =average(H23:J23) -> 0.068246633
B24: Operating Current Assets | E24: =1313+0+857+155 -> 2325 | F24: =1044+185+965+293 -> 2487 | G24: =G25*G6 -> 2432.7086 | H24: =H25*H6 -> 2488.6244 | I24: =I25*I6 -> 2489.419 | J24: =J25*J6 -> 2518.4064 | K24: =K25*K6 -> 2533.6119 | L24: Source: 10K
B25: Operating Current Assets as % of Revenue | E25: =E24/E6 -> 0.28364036 | F25: =F24/F6 -> 0.30130846 | G25: =average(E25:F25) -> 0.29247441 | H25: =average(F25:G25) -> 0.29689143 | I25: =average(G25:H25) -> 0.29468292 | J25: =average(H25:I25) -> 0.29578718 | K25: =average(I25:J25) -> 0.29523505
B26: Operating Current Liabilities | E26: =477+0+574+677 -> 1728 | F26: =618+272+572+1041 -> 2503 | G26: =G27*G6 -> 2137.8757 | H26: =H27*H6 -> 2154.4772 | I26: =I27*I6 -> 2171.3171 | J26: =J27*J6 -> 2188.3999 | K26: =K27*K6 -> 2205.7302 | L26: Source: 10K
B27: Operating Current Liabilities as % of Revenue | E27: =E26/E6 -> 0.21080883 | F27: =F26/F6 -> 0.30324691 | G27: =average(E27:F27) -> 0.25702787 | H27: =G27 -> 0.25702787 | I27: =H27 -> 0.25702787 | J27: =I27 -> 0.25702787 | K27: =J27 -> 0.25702787
B28: CAPEX | D28: 253 | E28: 230 | F28: 380 | G28: =F28 -> 380 | H28: =G28 -> 380 | I28: =H28 -> 380 | J28: =I28 -> 380 | K28: =J28 -> 380 | L28: Source: 10K
D34: 2022A | E34: 2023A | F34: 2024A | G34: 2025E | H34: 2026E | I34: 2027E | J34: 2028E | K34: 2029E
B35: Revenue Growth Assumptions
B36: Sales of Product | E36: =E4/D4-1 -> -0.00063492063 | F36: =F4/E4-1 -> 0.0082592122 | G36: =average(E36:F36) -> 0.0038121458 | H36: =$G$36 -> 0.0038121458 | I36: =$G$36 -> 0.0038121458 | J36: =$G$36 -> 0.0038121458 | K36: =$G$36 -> 0.0038121458
B37: Sales of Software and Rentals | E37: =E5/D5-1 -> 0.038797814 | F37: =F5/E5-1 -> 0.0026301946 | G37: =average(E37:F37) -> 0.020714004 | H37: =$G$37 -> 0.020714004 | I37: =$G$37 -> 0.020714004 | J37: =$G$37 -> 0.020714004 | K37: =$G$37 -> 0.020714004
B40: COGS Assumptions
B41: Cost of Product (%of Total COGS) | D41: =D7/(D7+D8) -> 0.85967977 | E41: =E7/(E7+E8) -> 0.86272831 | F41: =F7/(F7+F8) -> 0.86642994 | G41: =AVERAGE(D41:F41) -> 0.862946 | H41: =G41 -> 0.862946 | I41: =H41 -> 0.862946 | J41: =I41 -> 0.862946 | K41: =J41 -> 0.862946
B42: Cost of software and rentals (% of Total COGS) | D42: =1-D41 -> 0.14032023 | E42: =1-E41 -> 0.13727169 | F42: =1-F41 -> 0.13357006 | G42: =AVERAGE(D42:F42) -> 0.137054 | H42: =G42 -> 0.137054 | I42: =H42 -> 0.137054 | J42: =I42 -> 0.137054 | K42: =J42 -> 0.137054
B45: OPEX Assumptions (% of Sales)
B46: =B11 -> Selling, general and administrative expenses | D46: =D11/D6 -> 0.27490775 | E46: =E11/E6 -> 0.2736367 | F46: =F11/F6 -> 0.3370487 | G46: =average(D46:F46) -> 0.29519772 | H46: =G46 -> 0.29519772 | I46: =H46 -> 0.29519772 | J46: =I46 -> 0.29519772 | K46: =J46 -> 0.29519772
B47: =B12 -> Research and development expenses | D47: =D12/D6 -> 0.094341943 | E47: =E12/E6 -> 0.092472856 | F47: =F12/F6 -> 0.09389387 | G47: =average(D47:F47) -> 0.093569556 | H47: =G47 -> 0.093569556 | I47: =H47 -> 0.093569556 | J47: =I47 -> 0.093569556 | K47: =J47 -> 0.093569556
N49: DCF Model (US$ millions) | O49: 2025E | P49: 2026E | Q49: 2027E | R49: 2028E | S49: 2029E
B50: DCF Model (US$ millions) | D50: 2022A | E50: 2023A | F50: 2024A | G50: 2025E | H50: 2026E | I50: 2027E | J50: 2028E | K50: 2029E | N50: NOPAT | O50: =G51 -> 1183.153 | P50: =H51 -> 1192.3407 | Q50: =I51 -> 1201.6603 | R50: =J51 -> 1211.1144 | S50: =K51 -> 1220.7054
B51: NOPAT | G51: =G13*(1-G21) -> 1183.153 | H51: =H13*(1-H21) -> 1192.3407 | I51: =I13*(1-I21) -> 1201.6603 | J51: =J13*(1-J21) -> 1211.1144 | K51: =K13*(1-K21) -> 1220.7054 | N51: (+) Depreciation & Amortization | O51: =G52 -> 573.29476 | P51: =H52 -> 571.68382 | Q51: =I52 -> 575.48169 | R51: =J52 -> 582.51259 | S51: =K52 -> 585.67058
B52: (+) Depreciation & Amortization | G52: =G22 -> 573.29476 | H52: =H22 -> 571.68382 | I52: =I22 -> 575.48169 | J52: =J22 -> 582.51259 | K52: =K22 -> 585.67058 | N52: (+/-) Change in Net Working Capital | O52: =G53 -> -310.83295 | P52: =H53 -> -39.314208 | Q52: =I53 -> 16.045274 | R52: =J53 -> -11.904575 | S52: =K53 -> 2.1248085
B53: (+/-) Change in Net Working Capital | G53: =(F24-F26)-(G24-G26) -> -310.83295 | H53: =(G24-G26)-(H24-H26) -> -39.314208 | I53: =(H24-H26)-(I24-I26) -> 16.045274 | J53: =(I24-I26)-(J24-J26) -> -11.904575 | K53: =(J24-J26)-(K24-K26) -> 2.1248085 | N53: (-) CAPEX | O53: =G54 -> -380 | P53: =H54 -> -380 | Q53: =I54 -> -380 | R53: =J54 -> -380 | S53: =K54 -> -380
B54: (-) CAPEX | G54: =-G28 -> -380 | H54: =-H28 -> -380 | I54: =-I28 -> -380 | J54: =-J28 -> -380 | K54: =-K28 -> -380 | N54: Unlevered Free Cash Flow | O54: =G55 -> 1065.6148 | P54: =H55 -> 1344.7103 | Q54: =I55 -> 1413.1873 | R54: =J55 -> 1401.7224 | S54: =K55 -> 1428.5008
B55: Unlevered Free Cash Flow | G55: =sum(G51:G54) -> 1065.6148 | H55: =sum(H51:H54) -> 1344.7103 | I55: =sum(I51:I54) -> 1413.1873 | J55: =sum(J51:J54) -> 1401.7224 | K55: =sum(K51:K54) -> 1428.5008 | N55: (+) Terminal Value | O55: =G56 | P55: =H56 | Q55: =I56 | R55: =J56 | S55: =K56 -> 31985.147
B56: (+) Terminal Value | K56: =(K55*(1+F63))/(F62-F63) -> 31985.147 | N56: Unlevered Free Cash Flow + Terminal Value | O56: =G57 -> 1065.6148 | P56: =H57 -> 1344.7103 | Q56: =I57 -> 1413.1873 | R56: =J57 -> 1401.7224 | S56: =K57 -> 33413.648
B57: Unlevered Free Cash Flow + Terminal Value | G57: =G55+G56 -> 1065.6148 | H57: =H55+H56 -> 1344.7103 | I57: =I55+I56 -> 1413.1873 | J57: =J55+J56 -> 1401.7224 | K57: =K55+K56 -> 33413.648 | N57: (x) Discount Factor | O57: =G58 -> 0.92936698 | P57: =H58 -> 0.86372298 | Q57: =I58 -> 0.80271561 | R57: =J58 -> 0.74601738 | S57: =K58 -> 0.69332392
B58: (x) Discount Factor | G58: =1/((1+$F$62)^G64) -> 0.92936698 | H58: =1/((1+$F$62)^H64) -> 0.86372298 | I58: =1/((1+$F$62)^I64) -> 0.80271561 | J58: =1/((1+$F$62)^J64) -> 0.74601738 | K58: =1/((1+$F$62)^K64) -> 0.69332392 | N58: Discounted Value | O58: =G59 -> 990.34722 | P58: =H59 -> 1161.4572 | Q58: =I59 -> 1134.3875 | R58: =J59 -> 1045.7093 | S58: =K59 -> 23166.481
B59: Discounted Value | G59: =G57*G58 -> 990.34722 | H59: =H57*H58 -> 1161.4572 | I59: =I57*I58 -> 1134.3875 | J59: =J57*J58 -> 1045.7093 | K59: =K57*K58 -> 23166.481
N60: Enterprise Value | O60: =sum(O58:S58) -> 27498.382
B61: Enterprise Value | H61: =sum(G59:K59) -> 27498.382
B62: WACC | F62: =G91 -> 0.07600122
B63: Terminal Growth Rate | F63: 0.03
B64: Years | G64: 1 | H64: 2 | I64: 3 | J64: 4 | K64: 5
B69: WACC
D70: Market Cap (Bn) | E70: Total Debt (Bn) | F70: % in Equity | G70: % in Debt | H70: % of Market Cap
B71: GE HealthCare | D71: 34128 | E71: 9376 | F71: =D71/sum(D71:E71) -> 0.78447959 | G71: =E71/sum(D71:E71) -> 0.21552041 | H71: =D71/D75 -> 0.37587145
B72: Koninklijke Philips | D72: 25401 | E72: 4017 | F72: =D72/sum(D72:E72) -> 0.86345095 | G72: =E72/sum(D72:E72) -> 0.13654905 | H72: =D72/D75 -> 0.27975594
B73: Zimmer Biomet | D73: 17652 | E73: 6204.6 | F73: =D73/sum(D73:E73) -> 0.73992103 | G73: =E73/sum(D73:E73) -> 0.26007897 | H73: =D73/D75 -> 0.19441171
B74: Smith & Nephew | D74: 13616 | E74: 2506 | F74: =D74/sum(D74:E74) -> 0.84456023 | G74: =E74/sum(D74:E74) -> 0.15543977 | H74: =D74/D75 -> 0.1499609
B75: Sum | D75: =sum(D71:D74) -> 90797 | E75: =sum(E71:E74) -> 22103.6
B77: WACC Calculation
B78: Capital Structure | D78: GE HealthCare | E78: Koninklijke Philips | F78: Zimmer Biomet | G78: Smith & Nephew
B79: Equity proportion of total | D79: =F71 -> 0.78447959 | E79: =F72 -> 0.86345095 | F79: =F73 -> 0.73992103 | G79: =F74 -> 0.84456023
B80: Debt proportion of total | D80: =G71 -> 0.21552041 | E80: =G72 -> 0.13654905 | F80: =G73 -> 0.26007897 | G80: =G74 -> 0.15543977
D82: =D78 -> GE HealthCare | E82: =E78 -> Koninklijke Philips | F82: =F78 -> Zimmer Biomet | G82: =G78 -> Smith & Nephew
B83: Risk-free rate | D83: 0.041 | E83: 0.041 | F83: 0.041 | G83: 0.041 | H83: Fixed Assumption
B84: US equity risk premium | D84: 0.05 | E84: 0.05 | F84: 0.05 | G84: 0.05 | H84: Source: Kroll (https://www.kroll.com/en/reports/cost-of-capital/recommended-us-equity-risk-premium-and-corresponding-risk-free-rates?utm_source=chatgpt.com)
B85: Beta | D85: 1.27 | E85: 0.91 | F85: 0.61 | G85: 0.65 | H85: Source: YahooFinance
B86: Cost of equity | D86: =D83+D84*D85 -> 0.1045 | E86: =E83+E84*E85 -> 0.0865 | F86: =F83+F84*F85 -> 0.0715 | G86: =G83+G84*G85 -> 0.0735
B87: Cost of debt | D87: 0.046 | E87: 0.06 | F87: 0.055 | G87: 0.055 | H87: Fixed Assumption
B88: Corporate tax rate | D88: 0.21 | E88: 0.21 | F88: 0.21 | G88: 0.21
B89: After-tax cost of debt | D89: =D87*(1-D88) -> 0.03634 | E89: =E87*(1-E88) -> 0.0474 | F89: =F87*(1-F88) -> 0.04345 | G89: =G87*(1-G88) -> 0.04345
B90: WACC | D90: =D79*D86+D80*D89 -> 0.089810129 | E90: =E79*E86+E80*E89 -> 0.081160932 | F90: =F79*F86+F80*F89 -> 0.064204785 | G90: =G79*G86+G80*G89 -> 0.068829035
B91: Consolidated WACC | G91: =average(D90:G90) -> 0.07600122
